{
  "project_info": {
    "project_number": "484400594513",
    "project_id": "drivedemo-380502",
    "storage_bucket": "drivedemo-380502.appspot.com"
  },
  "client": [
    {
      "client_info": {
        "mobilesdk_app_id": "1:484400594513:android:9c9f88d51f08a82fd58270",
        "android_client_info": {
          "package_name": "com.linleiqin.wallet"
        }
      },
      "oauth_client": [
        {
          "client_id": "484400594513-9sdo8761376ju2ai260dltdud9mgpqrp.apps.googleusercontent.com",
          "client_type": 1,
          "android_info": {
            "package_name": "com.linleiqin.wallet",
            "certificate_hash": "35756f3db5b5b56ef6af460f5a1008015796bc61"
          }
        },
        {
          "client_id": "484400594513-n1tonkkhfg04v4hvu9i23k2op0q0k6g7.apps.googleusercontent.com",
          "client_type": 1,
          "android_info": {
            "package_name": "com.linleiqin.wallet",
            "certificate_hash": "5e8f16062ea3cd2c4a0d547876baa6f38cabf625"
          }
        },
        {
          "client_id": "484400594513-ih96lqpr6b7hs9a33fuam3rkie46e648.apps.googleusercontent.com",
          "client_type": 3
        }
      ],
      "api_key": [
        {
          "current_key": "AIzaSyBJOLPbypJCAMA2Dz_gnBhRmY6oocqgXvM"
        }
      ],
      "services": {
        "appinvite_service": {
          "other_platform_oauth_client": [
            {
              "client_id": "484400594513-ih96lqpr6b7hs9a33fuam3rkie46e648.apps.googleusercontent.com",
              "client_type": 3
            },
            {
              "client_id": "484400594513-gg9itutfft4v8ngev6oj0ecjplq823j5.apps.googleusercontent.com",
              "client_type": 2,
              "ios_info": {
                "bundle_id": "dev.so.onekey.wallet"
              }
            }
          ]
        }
      }
    }
  ],
  "configuration_version": "1"
}