{"v":"4.8.0","meta":{"g":"LottieFiles AE 3.0.0","a":"","k":"","d":"","tc":""},"fr":60,"ip":0,"op":195,"w":358,"h":205,"nm":"illus / Touch / Enter PIN Code","ddd":0,"assets":[{"id":"comp_0","layers":[{"ddd":0,"ind":1,"ty":4,"nm":"Shape Layer 1","sr":1,"ks":{"o":{"a":0,"k":100,"ix":11},"r":{"a":0,"k":0,"ix":10},"p":{"a":0,"k":[49.81,49.357,0],"ix":2},"a":{"a":0,"k":[-6.651,-11.806,0],"ix":1},"s":{"a":1,"k":[{"i":{"x":[0.499,0.499,0.667],"y":[1,1,1]},"o":{"x":[0.249,0.249,0.333],"y":[0.491,0.491,0]},"t":0,"s":[0,0,100]},{"t":40,"s":[100,100,100]}],"ix":6}},"ao":0,"hasMask":true,"masksProperties":[{"inv":false,"mode":"s","pt":{"a":1,"k":[{"i":{"x":0.503,"y":1},"o":{"x":0.503,"y":0},"t":0,"s":[{"i":[[3.581,0],[0,-3.581],[-3.581,0],[0,3.581]],"o":[[-3.581,0],[0,3.581],[3.581,0],[0,-3.581]],"v":[[-6.465,-17.663],[-12.949,-11.18],[-6.465,-4.696],[0.019,-11.18]],"c":true}]},{"t":40,"s":[{"i":[[22.468,0],[0,-22.466],[-22.468,0],[0,22.466]],"o":[[-22.468,0],[0,22.466],[22.468,0],[0,-22.466]],"v":[[-6.676,-52.163],[-47.357,-11.484],[-6.676,29.194],[34.006,-11.484]],"c":true}]}],"ix":1},"o":{"a":0,"k":100,"ix":3},"x":{"a":0,"k":0,"ix":4},"nm":"Mask 1"}],"shapes":[{"ty":"gr","it":[{"d":1,"ty":"el","s":{"a":0,"k":[80,80],"ix":2},"p":{"a":0,"k":[0,0],"ix":3},"nm":"Ellipse Path 1","mn":"ADBE Vector Shape - Ellipse","hd":false},{"ty":"fl","c":{"a":0,"k":[0.20000000298,0.776470601559,0.254901975393,1],"ix":4},"o":{"a":0,"k":100,"ix":5},"r":1,"bm":0,"nm":"Fill 1","mn":"ADBE Vector Graphic - Fill","hd":false},{"ty":"tr","p":{"a":0,"k":[-6.461,-11.163],"ix":2},"a":{"a":0,"k":[0,0],"ix":1},"s":{"a":0,"k":[100,100],"ix":3},"r":{"a":0,"k":0,"ix":6},"o":{"a":0,"k":100,"ix":7},"sk":{"a":0,"k":0,"ix":4},"sa":{"a":0,"k":0,"ix":5},"nm":"Transform"}],"nm":"Ellipse 1","np":3,"cix":2,"bm":0,"ix":1,"mn":"ADBE Vector Group","hd":false}],"ip":0,"op":61,"st":0,"bm":0}]},{"id":"comp_1","layers":[{"ddd":0,"ind":1,"ty":3,"nm":"▽ Keyboard/ASCII","sr":1,"ks":{"o":{"a":0,"k":100,"ix":11},"r":{"a":0,"k":0,"ix":10},"p":{"a":0,"k":[68,159.612,0],"ix":2},"a":{"a":0,"k":[51,25.612,0],"ix":1},"s":{"a":0,"k":[100,100,100],"ix":6}},"ao":0,"ip":0,"op":300,"st":0,"bm":0},{"ddd":0,"ind":2,"ty":4,"nm":"Keys","parent":1,"sr":1,"ks":{"o":{"a":0,"k":100,"ix":11},"r":{"a":0,"k":0,"ix":10},"p":{"a":0,"k":[51.008,25.433,0],"ix":2},"a":{"a":0,"k":[0,0,0],"ix":1},"s":{"a":0,"k":[100,100,100],"ix":6}},"ao":0,"shapes":[{"ty":"gr","it":[{"ind":0,"ty":"sh","ix":1,"ks":{"a":0,"k":{"i":[[0,0],[0,0],[0,0],[0,0],[0,0],[0,0],[0,0],[0,0],[0.168,0.155],[0.285,0],[0.206,-0.235],[0,-0.403],[0,0],[-0.206,-0.235],[-0.348,0],[-0.168,0.155],[0,0.273],[0,0],[0,0]],"o":[[0,0],[0,0],[0,0],[0,0],[0,0],[0,0],[0,0],[0,-0.273],[-0.168,-0.159],[-0.348,0],[-0.206,0.231],[0,0],[0,0.403],[0.206,0.235],[0.285,0],[0.168,-0.159],[0,0],[0,0],[0,0]],"v":[[-45.833,-17.65],[-45.833,-16.662],[-45.154,-16.662],[-45.154,-21.254],[-45.827,-21.254],[-45.827,-20.594],[-45.972,-20.594],[-45.827,-20.436],[-46.079,-21.078],[-46.758,-21.317],[-47.589,-20.965],[-47.897,-20.015],[-47.897,-19.04],[-47.589,-18.084],[-46.758,-17.731],[-46.079,-17.964],[-45.827,-18.612],[-45.972,-18.455],[-45.815,-18.455]],"c":true},"ix":2},"nm":"Path 1","mn":"ADBE Vector Shape - Group","hd":false},{"ind":1,"ty":"sh","ix":2,"ks":{"a":0,"k":{"i":[[0.126,-0.134],[0.214,0],[0.122,0.126],[0,0.243],[0,0],[-0.117,0.126],[-0.222,0],[-0.122,-0.134],[0,-0.235],[0,0]],"o":[[-0.122,0.13],[-0.222,0],[-0.117,-0.13],[0,0],[0,-0.243],[0.122,-0.13],[0.214,0],[0.126,0.13],[0,0],[0,0.235]],"v":[[-46.022,-18.518],[-46.525,-18.323],[-47.041,-18.511],[-47.217,-19.071],[-47.217,-19.977],[-47.041,-20.531],[-46.525,-20.726],[-46.022,-20.525],[-45.833,-19.977],[-45.833,-19.071]],"c":true},"ix":2},"nm":"Path 2","mn":"ADBE Vector Shape - Group","hd":false},{"ind":2,"ty":"sh","ix":3,"ks":{"a":0,"k":{"i":[[0,0],[0,0],[0,0],[0,0],[-0.017,0.13],[-0.013,0.08],[-0.021,-0.134],[-0.017,-0.117],[0,0],[0,0],[0,0],[0,0],[0,0],[0.021,-0.13],[0.008,-0.088],[0.021,0.126],[0.017,0.109],[0,0],[0,0],[0,0],[0.021,-0.126],[0.008,-0.084],[0.017,0.126],[0.017,0.105],[0,0]],"o":[[0,0],[0,0],[0,0],[0.017,-0.117],[0.021,-0.134],[0.008,0.08],[0.021,0.13],[0,0],[0,0],[0,0],[0,0],[0,0],[-0.017,0.105],[-0.017,0.126],[-0.008,-0.084],[-0.017,-0.13],[0,0],[0,0],[0,0],[-0.017,0.109],[-0.017,0.126],[-0.008,-0.084],[-0.013,-0.13],[0,0],[0,0]],"v":[[-37.889,-21.254],[-37.354,-17.794],[-36.631,-17.794],[-36.279,-20.053],[-36.228,-20.424],[-36.178,-20.745],[-36.134,-20.424],[-36.077,-20.053],[-35.738,-17.794],[-35.021,-17.794],[-34.467,-21.254],[-35.021,-21.254],[-35.348,-18.971],[-35.404,-18.618],[-35.442,-18.298],[-35.486,-18.612],[-35.536,-18.971],[-35.889,-21.254],[-36.461,-21.254],[-36.82,-18.971],[-36.876,-18.618],[-36.914,-18.304],[-36.952,-18.618],[-36.996,-18.971],[-37.317,-21.254]],"c":true},"ix":2},"nm":"Path 3","mn":"ADBE Vector Shape - Group","hd":false},{"ind":3,"ty":"sh","ix":4,"ks":{"a":0,"k":{"i":[[-0.21,-0.113],[-0.281,0],[-0.252,0.172],[-0.05,0.294],[0,0],[0.122,-0.071],[0.197,0],[0.13,0.134],[0,0.256],[0,0],[0,0],[0,0],[0.113,0.197],[0.21,0.109],[0.285,0],[0.214,-0.113],[0.113,-0.201],[0,-0.273],[0,0],[-0.113,-0.201]],"o":[[0.214,0.109],[0.369,0],[0.252,-0.176],[0,0],[-0.029,0.134],[-0.122,0.067],[-0.243,0],[-0.126,-0.134],[0,0],[0,0],[0,0],[0,-0.273],[-0.113,-0.201],[-0.21,-0.113],[-0.281,0],[-0.21,0.109],[-0.113,0.197],[0,0],[0,0.268],[0.113,0.201]],"v":[[-26.586,-17.895],[-25.843,-17.731],[-24.912,-17.989],[-24.459,-18.694],[-25.132,-18.694],[-25.359,-18.386],[-25.837,-18.285],[-26.397,-18.486],[-26.586,-19.071],[-26.586,-19.361],[-24.447,-19.361],[-24.447,-19.977],[-24.617,-20.682],[-25.101,-21.147],[-25.843,-21.317],[-26.586,-21.147],[-27.07,-20.682],[-27.24,-19.977],[-27.24,-19.071],[-27.07,-18.367]],"c":true},"ix":2},"nm":"Path 4","mn":"ADBE Vector Shape - Group","hd":false},{"ind":4,"ty":"sh","ix":5,"ks":{"a":0,"k":{"i":[[0,-0.252],[0,0],[0,0],[0,0],[0,0],[-0.126,0.138],[-0.239,0],[-0.126,-0.138]],"o":[[0,0],[0,0],[0,0],[0,0],[0,-0.256],[0.13,-0.138],[0.243,0],[0.126,0.138]],"v":[[-25.101,-19.983],[-25.101,-19.77],[-25.051,-19.826],[-26.586,-19.82],[-26.586,-19.977],[-26.397,-20.569],[-25.843,-20.776],[-25.29,-20.569]],"c":true},"ix":2},"nm":"Path 5","mn":"ADBE Vector Shape - Group","hd":false},{"ind":5,"ty":"sh","ix":6,"ks":{"a":0,"k":{"i":[[0,0],[0,0],[0,0],[0,0],[-0.122,0.134],[-0.222,0],[-0.122,-0.134],[0,-0.247],[0,0],[0,0],[0,0],[0.218,0.226],[0.369,0],[0.164,-0.193],[0,-0.373],[0,0],[0,0],[0,0]],"o":[[0,0],[0,0],[0,0],[0,-0.243],[0.126,-0.134],[0.222,0],[0.126,0.13],[0,0],[0,0],[0,0],[0,-0.398],[-0.214,-0.231],[-0.323,0],[-0.164,0.189],[0,0],[0,0],[0,0],[0,0]],"v":[[-16.754,-21.254],[-16.754,-17.794],[-16.075,-17.794],[-16.075,-19.977],[-15.892,-20.543],[-15.37,-20.745],[-14.854,-20.543],[-14.666,-19.977],[-14.666,-19.801],[-13.967,-19.801],[-13.967,-20.034],[-14.294,-20.971],[-15.169,-21.317],[-15.899,-21.028],[-16.144,-20.185],[-15.936,-20.594],[-16.1,-20.594],[-16.1,-21.254]],"c":true},"ix":2},"nm":"Path 6","mn":"ADBE Vector Shape - Group","hd":false},{"ind":6,"ty":"sh","ix":7,"ks":{"a":0,"k":{"i":[[-0.176,-0.172],[-0.315,0],[0,0],[0,0],[0,0],[0,0.239],[0,0],[0,0],[0,0],[0,0],[0,0],[0,0],[0,0],[0,0],[0,0],[0,0],[0,0]],"o":[[0.176,0.172],[0,0],[0,0],[0,0],[-0.231,0],[0,0],[0,0],[0,0],[0,0],[0,0],[0,0],[0,0],[0,0],[0,0],[0,0],[0,0],[0,0.306]],"v":[[-5.532,-18.052],[-4.796,-17.794],[-3.827,-17.794],[-3.827,-18.411],[-4.771,-18.411],[-5.117,-18.769],[-5.117,-20.638],[-3.765,-20.638],[-3.765,-21.254],[-5.117,-21.254],[-5.117,-22.229],[-5.796,-22.229],[-5.796,-21.254],[-6.753,-21.254],[-6.753,-20.638],[-5.796,-20.638],[-5.796,-18.769]],"c":true},"ix":2},"nm":"Path 7","mn":"ADBE Vector Shape - Group","hd":false},{"ind":7,"ty":"sh","ix":8,"ks":{"a":0,"k":{"i":[[0,0],[0,0],[0,0],[0,0],[0,0],[0,0],[0.029,-0.117],[0.017,-0.075],[0.029,0.117],[0.029,0.084],[0,0],[0,0]],"o":[[0,0],[0,0],[0,0],[0,0],[0,0],[-0.029,0.084],[-0.029,0.117],[-0.021,-0.075],[-0.029,-0.117],[0,0],[0,0],[0,0]],"v":[[4.853,-17.996],[4.356,-16.662],[5.073,-16.662],[6.759,-21.254],[6.036,-21.254],[5.356,-19.304],[5.268,-19.002],[5.199,-18.713],[5.123,-19.002],[5.035,-19.304],[4.312,-21.254],[3.563,-21.254]],"c":true},"ix":2},"nm":"Path 8","mn":"ADBE Vector Shape - Group","hd":false},{"ind":8,"ty":"sh","ix":9,"ks":{"a":0,"k":{"i":[[-0.247,-0.243],[-0.415,0],[-0.247,0.239],[0,0.415],[0,0],[0,0],[0,0],[0.126,-0.134],[0.218,0],[0.122,0.13],[0,0.239],[0,0],[0,0],[0,0]],"o":[[0.247,0.239],[0.419,0],[0.252,-0.243],[0,0],[0,0],[0,0],[0,0.239],[-0.122,0.13],[-0.214,0],[-0.122,-0.134],[0,0],[0,0],[0,0],[0,0.415]],"v":[[14.496,-18.09],[15.49,-17.731],[16.49,-18.09],[16.867,-19.078],[16.867,-21.254],[16.188,-21.254],[16.188,-19.078],[15.999,-18.518],[15.49,-18.323],[14.986,-18.518],[14.804,-19.078],[14.804,-21.254],[14.125,-21.254],[14.125,-19.078]],"c":true},"ix":2},"nm":"Path 9","mn":"ADBE Vector Shape - Group","hd":false},{"ind":9,"ty":"sh","ix":10,"ks":{"a":0,"k":{"i":[[0,0],[0,0],[0,0],[0,0],[0,0],[0,0],[0,0],[0,0],[0,0],[0,0]],"o":[[0,0],[0,0],[0,0],[0,0],[0,0],[0,0],[0,0],[0,0],[0,0],[0,0]],"v":[[24.453,-18.411],[24.453,-17.794],[27.441,-17.794],[27.441,-18.411],[26.328,-18.411],[26.328,-21.254],[24.61,-21.254],[24.61,-20.638],[25.667,-20.638],[25.667,-18.411]],"c":true},"ix":2},"nm":"Path 10","mn":"ADBE Vector Shape - Group","hd":false},{"ind":10,"ty":"sh","ix":11,"ks":{"a":0,"k":{"i":[[-0.088,-0.08],[-0.147,0],[-0.088,0.075],[0,0.13],[0.088,0.075],[0.147,0],[0.088,-0.08],[0,-0.134]],"o":[[0.088,0.075],[0.147,0],[0.088,-0.08],[0,-0.134],[-0.088,-0.08],[-0.147,0],[-0.088,0.075],[0,0.13]],"v":[[25.579,-21.965],[25.931,-21.852],[26.284,-21.965],[26.416,-22.28],[26.284,-22.594],[25.931,-22.714],[25.579,-22.594],[25.447,-22.28]],"c":true},"ix":2},"nm":"Path 11","mn":"ADBE Vector Shape - Group","hd":false},{"ind":11,"ty":"sh","ix":12,"ks":{"a":0,"k":{"i":[[-0.21,-0.109],[-0.285,0],[-0.21,0.109],[-0.113,0.201],[0,0.273],[0,0],[0.113,0.197],[0.21,0.109],[0.285,0],[0.21,-0.109],[0.113,-0.201],[0,-0.277],[0,0],[-0.113,-0.201]],"o":[[0.21,0.109],[0.285,0],[0.21,-0.109],[0.113,-0.201],[0,0],[0,-0.277],[-0.113,-0.201],[-0.21,-0.109],[-0.285,0],[-0.21,0.109],[-0.113,0.197],[0,0],[0,0.273],[0.113,0.201]],"v":[[35.423,-17.901],[36.166,-17.738],[36.908,-17.901],[37.392,-18.367],[37.562,-19.078],[37.562,-19.971],[37.392,-20.682],[36.908,-21.147],[36.166,-21.311],[35.423,-21.147],[34.939,-20.682],[34.769,-19.971],[34.769,-19.078],[34.939,-18.367]],"c":true},"ix":2},"nm":"Path 12","mn":"ADBE Vector Shape - Group","hd":false},{"ind":12,"ty":"sh","ix":13,"ks":{"a":0,"k":{"i":[[0.126,-0.13],[0.231,0],[0.13,0.126],[0,0.239],[0,0],[-0.126,0.126],[-0.226,0],[-0.126,-0.126],[0,-0.243],[0,0]],"o":[[-0.126,0.126],[-0.226,0],[-0.126,-0.13],[0,0],[0,-0.243],[0.13,-0.126],[0.231,0],[0.126,0.126],[0,0],[0,0.239]],"v":[[36.7,-18.524],[36.166,-18.335],[35.631,-18.524],[35.442,-19.078],[35.442,-19.971],[35.631,-20.525],[36.166,-20.713],[36.7,-20.525],[36.889,-19.971],[36.889,-19.078]],"c":true},"ix":2},"nm":"Path 13","mn":"ADBE Vector Shape - Group","hd":false},{"ind":13,"ty":"sh","ix":14,"ks":{"a":0,"k":{"i":[[0,0],[0,0],[0,0],[0,0],[0,0],[0,0],[0,0],[-0.172,-0.159],[-0.281,0],[-0.168,0.105],[-0.092,0.193],[0,0.268],[0,0],[0.21,0.231],[0.348,0],[0.172,-0.159],[0,-0.273],[0,0],[0,0],[0,0]],"o":[[0,0],[0,0],[0,0],[0,0],[0,0],[0,0],[0,0.273],[0.172,0.155],[0.235,0],[0.172,-0.109],[0.096,-0.197],[0,0],[0,-0.403],[-0.206,-0.235],[-0.285,0],[-0.168,0.155],[0,0],[0,0],[0,0],[0,0]],"v":[[45.142,-21.254],[45.142,-16.662],[45.821,-16.662],[45.821,-17.65],[45.802,-18.455],[45.959,-18.455],[45.815,-18.612],[46.073,-17.964],[46.752,-17.731],[47.356,-17.889],[47.752,-18.342],[47.897,-19.04],[47.897,-20.015],[47.582,-20.965],[46.752,-21.317],[46.066,-21.078],[45.815,-20.436],[45.959,-20.594],[45.815,-20.594],[45.815,-21.254]],"c":true},"ix":2},"nm":"Path 14","mn":"ADBE Vector Shape - Group","hd":false},{"ind":14,"ty":"sh","ix":15,"ks":{"a":0,"k":{"i":[[0.126,-0.13],[0.222,0],[0.126,0.13],[0,0.235],[0,0],[-0.126,0.13],[-0.214,0],[-0.122,-0.13],[0,-0.243],[0,0]],"o":[[-0.122,0.126],[-0.214,0],[-0.126,-0.134],[0,0],[0,-0.235],[0.126,-0.134],[0.222,0],[0.126,0.126],[0,0],[0,0.243]],"v":[[47.035,-18.511],[46.519,-18.323],[46.01,-18.518],[45.821,-19.071],[45.821,-19.977],[46.01,-20.525],[46.519,-20.726],[47.035,-20.531],[47.224,-19.977],[47.224,-19.071]],"c":true},"ix":2},"nm":"Path 15","mn":"ADBE Vector Shape - Group","hd":false},{"ind":15,"ty":"sh","ix":16,"ks":{"a":0,"k":{"i":[[-0.206,-0.189],[-0.361,0],[-0.193,0.147],[0,0.252],[0,0],[0,0],[0,0],[0,0],[0,0],[0.239,0.206],[0.411,0],[0.252,-0.185],[0.038,-0.31],[0,0],[-0.126,0.08],[-0.189,0],[-0.117,-0.105],[0,-0.189],[0,0],[0,0],[0.222,-0.189],[0,-0.327]],"o":[[0.21,0.185],[0.319,0],[0.193,-0.151],[0,0],[0,0],[0,0],[0,0],[0,0],[0,-0.356],[-0.239,-0.21],[-0.382,0],[-0.247,0.185],[0,0],[0.021,-0.134],[0.126,-0.084],[0.214,0],[0.117,0.105],[0,0],[0,0],[-0.386,0],[-0.218,0.185],[0,0.323]],"v":[[-42.547,-4.528],[-41.691,-4.251],[-40.924,-4.471],[-40.635,-5.075],[-40.748,-4.95],[-40.635,-4.95],[-40.635,-4.314],[-39.974,-4.314],[-39.974,-6.679],[-40.333,-7.522],[-41.308,-7.837],[-42.258,-7.56],[-42.685,-6.818],[-42.019,-6.818],[-41.798,-7.139],[-41.327,-7.264],[-40.83,-7.107],[-40.654,-6.667],[-40.654,-6.346],[-41.616,-6.346],[-42.528,-6.063],[-42.855,-5.296]],"c":true},"ix":2},"nm":"Path 16","mn":"ADBE Vector Shape - Group","hd":false},{"ind":16,"ty":"sh","ix":17,"ks":{"a":0,"k":{"i":[[0.159,-0.126],[0.243,0],[0.122,0.101],[0,0.176],[-0.101,0.096],[-0.176,0],[0,0],[0,0]],"o":[[-0.155,0.122],[-0.214,0],[-0.122,-0.105],[0,-0.168],[0.105,-0.096],[0,0],[0,0],[0,0.193]],"v":[[-40.893,-4.956],[-41.49,-4.773],[-41.993,-4.924],[-42.176,-5.346],[-42.025,-5.742],[-41.603,-5.887],[-40.654,-5.887],[-40.654,-5.434]],"c":true},"ix":2},"nm":"Path 17","mn":"ADBE Vector Shape - Group","hd":false},{"ind":17,"ty":"sh","ix":18,"ks":{"a":0,"k":{"i":[[-0.185,-0.08],[-0.247,0],[0,0],[-0.214,0.185],[0,0.331],[0.185,0.159],[0.39,0.055],[0,0],[0.08,0.063],[0,0.126],[-0.088,0.071],[-0.197,0],[0,0],[-0.092,-0.063],[-0.017,-0.101],[0,0],[0.218,0.164],[0.361,0],[0,0],[0.21,-0.176],[0,-0.319],[-0.172,-0.155],[-0.369,-0.059],[0,0],[-0.092,-0.08],[0,-0.134],[0.105,-0.084],[0.206,0],[0,0],[0.105,0.067],[0.017,0.113],[0,0],[-0.105,-0.143]],"o":[[0.189,0.08],[0,0],[0.428,0],[0.218,-0.185],[0,-0.306],[-0.18,-0.164],[0,0],[-0.168,-0.025],[-0.08,-0.063],[0,-0.143],[0.092,-0.075],[0,0],[0.164,0],[0.096,0.063],[0,0],[-0.029,-0.277],[-0.214,-0.168],[0,0],[-0.407,0],[-0.206,0.172],[0,0.302],[0.176,0.151],[0,0],[0.185,0.025],[0.096,0.075],[0,0.138],[-0.105,0.084],[0,0],[-0.172,0],[-0.105,-0.071],[0,0],[0.017,0.193],[0.109,0.138]],"v":[[-31.784,-4.377],[-31.13,-4.258],[-30.86,-4.258],[-29.897,-4.534],[-29.57,-5.308],[-29.847,-6.006],[-30.702,-6.333],[-31.162,-6.409],[-31.533,-6.541],[-31.652,-6.824],[-31.52,-7.145],[-31.086,-7.258],[-30.847,-7.258],[-30.463,-7.164],[-30.294,-6.919],[-29.614,-6.919],[-29.985,-7.579],[-30.847,-7.831],[-31.086,-7.831],[-32.011,-7.566],[-32.319,-6.83],[-32.061,-6.145],[-31.243,-5.83],[-30.797,-5.761],[-30.382,-5.604],[-30.237,-5.289],[-30.394,-4.956],[-30.86,-4.83],[-31.13,-4.83],[-31.545,-4.931],[-31.728,-5.207],[-32.407,-5.207],[-32.225,-4.704]],"c":true},"ix":2},"nm":"Path 18","mn":"ADBE Vector Shape - Group","hd":false},{"ind":18,"ty":"sh","ix":19,"ks":{"a":0,"k":{"i":[[-0.21,-0.235],[-0.348,0],[-0.168,0.155],[0,0.273],[0,0],[0,0],[0,0],[0,0],[0,0],[0,0],[0,0],[0,0],[0,0],[0,0],[0.168,0.155],[0.285,0],[0.21,-0.235],[0,-0.403],[0,0]],"o":[[0.21,0.235],[0.285,0],[0.168,-0.159],[0,0],[0,0],[0,0],[0,0],[0,0],[0,0],[0,0],[0,0],[0,0],[0,0],[0,-0.273],[-0.168,-0.159],[-0.348,0],[-0.21,0.235],[0,0],[0,0.398]],"v":[[-21.758,-4.604],[-20.921,-4.251],[-20.242,-4.484],[-19.99,-5.132],[-20.135,-4.975],[-19.99,-4.975],[-19.99,-4.314],[-19.317,-4.314],[-19.317,-8.906],[-19.996,-8.906],[-19.996,-7.919],[-19.978,-7.114],[-20.135,-7.114],[-19.99,-6.956],[-20.242,-7.598],[-20.921,-7.837],[-21.758,-7.485],[-22.072,-6.528],[-22.072,-5.553]],"c":true},"ix":2},"nm":"Path 19","mn":"ADBE Vector Shape - Group","hd":false},{"ind":19,"ty":"sh","ix":20,"ks":{"a":0,"k":{"i":[[0.126,-0.134],[0.214,0],[0.126,0.126],[0,0.243],[0,0],[-0.126,0.126],[-0.222,0],[-0.122,-0.134],[0,-0.235],[0,0]],"o":[[-0.122,0.13],[-0.222,0],[-0.126,-0.13],[0,0],[0,-0.243],[0.126,-0.13],[0.214,0],[0.126,0.13],[0,0],[0,0.235]],"v":[[-20.185,-5.038],[-20.688,-4.843],[-21.211,-5.031],[-21.399,-5.591],[-21.399,-6.497],[-21.211,-7.051],[-20.688,-7.246],[-20.185,-7.044],[-19.996,-6.497],[-19.996,-5.591]],"c":true},"ix":2},"nm":"Path 20","mn":"ADBE Vector Shape - Group","hd":false},{"ind":20,"ty":"sh","ix":21,"ks":{"a":0,"k":{"i":[[0,0],[0,0],[0,0],[0,0],[0,0],[0,0],[0,0],[0,0],[-0.063,0.059],[-0.117,0],[0,0],[0,0],[0,0],[0.185,-0.168],[0,-0.289],[0,0],[0,0],[0,0]],"o":[[0,0],[0,0],[0,0],[0,0],[0,0],[0,0],[0,0],[0,-0.109],[0.067,-0.059],[0,0],[0,0],[0,0],[-0.319,0],[-0.185,0.168],[0,0],[0,0],[0,0],[0,0]],"v":[[-10.888,-6.793],[-10.888,-4.314],[-10.215,-4.314],[-10.215,-6.793],[-8.844,-6.793],[-8.844,-7.409],[-10.215,-7.409],[-10.215,-7.963],[-10.121,-8.214],[-9.844,-8.302],[-8.844,-8.302],[-8.844,-8.906],[-9.857,-8.906],[-10.612,-8.655],[-10.888,-7.969],[-10.888,-7.409],[-11.87,-7.409],[-11.87,-6.793]],"c":true},"ix":2},"nm":"Path 21","mn":"ADBE Vector Shape - Group","hd":false},{"ind":21,"ty":"sh","ix":22,"ks":{"a":0,"k":{"i":[[0,0],[0,0],[0,0],[-0.21,0.193],[0,0.331],[0,0],[0,0],[0,0],[0,0],[0,0],[0.168,0.151],[0.281,0],[0.206,-0.235],[0,-0.398],[0,0],[-0.206,-0.235],[-0.356,0],[-0.164,0.151],[0,0.264],[0,0],[0,0],[0,0],[0,0],[0.088,-0.084],[0.176,0]],"o":[[0,0],[0,0],[0.373,0],[0.21,-0.189],[0,0],[0,0],[0,0],[0,0],[0,0],[0,-0.264],[-0.164,-0.155],[-0.356,0],[-0.206,0.235],[0,0],[0,0.398],[0.206,0.235],[0.281,0],[0.168,-0.151],[0,0],[0,0],[0,0],[0,0],[0,0.164],[-0.084,0.084],[0,0]],"v":[[-0.912,-3.767],[-0.912,-3.182],[0.157,-3.182],[1.032,-3.471],[1.346,-4.251],[1.346,-7.774],[0.673,-7.774],[0.679,-7.114],[0.541,-7.114],[0.679,-6.981],[0.428,-7.604],[-0.239,-7.837],[-1.082,-7.485],[-1.39,-6.535],[-1.39,-5.83],[-1.082,-4.88],[-0.239,-4.528],[0.428,-4.754],[0.679,-5.377],[0.541,-5.251],[0.686,-5.251],[0.673,-4.61],[0.673,-4.264],[0.541,-3.893],[0.151,-3.767]],"c":true},"ix":2},"nm":"Path 22","mn":"ADBE Vector Shape - Group","hd":false},{"ind":22,"ty":"sh","ix":23,"ks":{"a":0,"k":{"i":[[0.126,-0.134],[0.214,0],[0.122,0.13],[0,0.239],[0,0],[-0.117,0.126],[-0.222,0],[-0.122,-0.134],[0,-0.235],[0,0]],"o":[[-0.122,0.13],[-0.222,0],[-0.117,-0.13],[0,0],[0,-0.243],[0.122,-0.13],[0.214,0],[0.126,0.13],[0,0],[0,0.235]],"v":[[0.484,-5.308],[-0.019,-5.113],[-0.535,-5.308],[-0.711,-5.862],[-0.711,-6.497],[-0.535,-7.051],[-0.019,-7.246],[0.484,-7.044],[0.673,-6.497],[0.673,-5.862]],"c":true},"ix":2},"nm":"Path 23","mn":"ADBE Vector Shape - Group","hd":false},{"ind":23,"ty":"sh","ix":24,"ks":{"a":0,"k":{"i":[[0,0],[0,0],[0,0],[0,0],[-0.122,0.13],[-0.214,0],[-0.122,-0.126],[0,-0.226],[0,0],[0,0],[0,0],[0.206,0.218],[0.344,0],[0.164,-0.155],[0,-0.277],[0,0],[0,0],[0,0],[0,0]],"o":[[0,0],[0,0],[0,0],[0,-0.243],[0.126,-0.134],[0.21,0],[0.122,0.126],[0,0],[0,0],[0,0],[0,-0.373],[-0.206,-0.222],[-0.289,0],[-0.164,0.155],[0,0],[0,0],[0,0],[0,0],[0,0]],"v":[[8.97,-8.906],[8.97,-4.314],[9.649,-4.314],[9.649,-6.497],[9.832,-7.057],[10.341,-7.258],[10.838,-7.069],[11.02,-6.541],[11.02,-4.314],[11.7,-4.314],[11.7,-6.617],[11.392,-7.504],[10.568,-7.837],[9.888,-7.604],[9.643,-6.956],[9.806,-7.114],[9.643,-7.114],[9.649,-7.774],[9.649,-8.906]],"c":true},"ix":2},"nm":"Path 24","mn":"ADBE Vector Shape - Group","hd":false},{"ind":24,"ty":"sh","ix":25,"ks":{"a":0,"k":{"i":[[0,0],[0,0],[0,0],[-0.252,0.243],[0,0.415],[0,0],[0,0],[0,0],[0,0],[0,0],[0.13,-0.126],[0.231,0]],"o":[[0,0],[0,0],[0.428,0],[0.252,-0.239],[0,0],[0,0],[0,0],[0,0],[0,0],[0,0.231],[-0.13,0.126],[0,0]],"v":[[19.305,-3.811],[19.305,-3.182],[20.192,-3.182],[21.211,-3.547],[21.588,-4.528],[21.588,-7.774],[19.493,-7.774],[19.493,-7.151],[20.909,-7.151],[20.909,-4.534],[20.714,-4],[20.173,-3.811]],"c":true},"ix":2},"nm":"Path 25","mn":"ADBE Vector Shape - Group","hd":false},{"ind":25,"ty":"sh","ix":26,"ks":{"a":0,"k":{"i":[[-0.088,-0.08],[-0.147,0],[-0.088,0.075],[0,0.13],[0.088,0.075],[0.147,0],[0.088,-0.08],[0,-0.134]],"o":[[0.088,0.075],[0.147,0],[0.088,-0.08],[0,-0.134],[-0.088,-0.08],[-0.147,0],[-0.088,0.075],[0,0.13]],"v":[[20.865,-8.485],[21.217,-8.372],[21.569,-8.485],[21.701,-8.799],[21.569,-9.114],[21.217,-9.234],[20.865,-9.114],[20.733,-8.799]],"c":true},"ix":2},"nm":"Path 26","mn":"ADBE Vector Shape - Group","hd":false},{"ind":26,"ty":"sh","ix":27,"ks":{"a":0,"k":{"i":[[0,0],[0,0],[0,0],[0,0],[0,0],[0,0],[0,0],[0,0],[0,0],[0,0],[0,0],[0,0],[0,0]],"o":[[0,0],[0,0],[0,0],[0,0],[0,0],[0,0],[0,0],[0,0],[0,0],[0,0],[0,0],[0,0],[0,0]],"v":[[29.658,-8.906],[29.658,-4.314],[30.338,-4.314],[30.338,-5.799],[30.948,-5.799],[31.873,-4.314],[32.653,-4.314],[31.533,-6.113],[32.634,-7.774],[31.866,-7.774],[30.948,-6.384],[30.338,-6.384],[30.338,-8.906]],"c":true},"ix":2},"nm":"Path 27","mn":"ADBE Vector Shape - Group","hd":false},{"ind":27,"ty":"sh","ix":28,"ks":{"a":0,"k":{"i":[[-0.159,-0.088],[-0.214,0],[0,0],[0,0],[0,0],[0.075,0.075],[0,0.134],[0,0],[0,0],[0,0],[0,0],[0,0],[-0.088,-0.159]],"o":[[0.159,0.084],[0,0],[0,0],[0,0],[-0.13,0],[-0.075,-0.08],[0,0],[0,0],[0,0],[0,0],[0,0],[0,0.21],[0.092,0.159]],"v":[[41.27,-4.44],[41.83,-4.314],[42.931,-4.314],[42.931,-4.931],[41.861,-4.931],[41.553,-5.044],[41.44,-5.365],[41.44,-8.906],[39.628,-8.906],[39.628,-8.29],[40.76,-8.29],[40.76,-5.365],[40.893,-4.811]],"c":true},"ix":2},"nm":"Path 28","mn":"ADBE Vector Shape - Group","hd":false},{"ind":28,"ty":"sh","ix":29,"ks":{"a":0,"k":{"i":[[0,0],[0,0],[0,0],[0,0],[0,0],[0,0],[0,0],[0,0]],"o":[[0,0],[0,0],[0,0],[0,0],[0,0],[0,0],[0,0],[0,0]],"v":[[-39.493,5.109],[-40.412,8.717],[-39.869,8.717],[-39.651,7.802],[-38.628,7.802],[-38.411,8.717],[-37.872,8.717],[-38.791,5.109]],"c":true},"ix":2},"nm":"Path 29","mn":"ADBE Vector Shape - Group","hd":false},{"ind":29,"ty":"sh","ix":30,"ks":{"a":0,"k":{"i":[[0,0],[0,0],[0,0],[-0.026,0.135],[-0.01,0.049],[-0.026,-0.138],[-0.043,-0.185]],"o":[[0,0],[0,0],[0.046,-0.181],[0.026,-0.138],[0.01,0.049],[0.03,0.135],[0,0]],"v":[[-38.732,7.362],[-39.552,7.362],[-39.305,6.315],[-39.196,5.84],[-39.142,5.558],[-39.088,5.84],[-38.979,6.319]],"c":true},"ix":2},"nm":"Path 30","mn":"ADBE Vector Shape - Group","hd":false},{"ind":30,"ty":"sh","ix":31,"ks":{"a":0,"k":{"i":[[0,0],[0,0],[0,0],[-0.165,0.082],[-0.089,0.152],[0,0.204],[0.079,0.138],[0.138,0.069],[0.181,-0.003],[0,0],[-0.125,0.066],[-0.069,0.119],[0,0.165],[0.194,0.165],[0.343,0]],"o":[[0,0],[0,0],[0.227,0],[0.168,-0.082],[0.092,-0.155],[0,-0.191],[-0.079,-0.138],[-0.138,-0.072],[0,0],[0.168,0],[0.125,-0.066],[0.072,-0.122],[0,-0.29],[-0.194,-0.165],[0,0]],"v":[[-37.241,5.109],[-37.241,8.717],[-36.109,8.717],[-35.521,8.593],[-35.135,8.242],[-34.997,7.703],[-35.116,7.209],[-35.442,6.898],[-35.921,6.794],[-35.921,6.843],[-35.481,6.745],[-35.19,6.468],[-35.081,6.038],[-35.373,5.356],[-36.178,5.109]],"c":true},"ix":2},"nm":"Path 31","mn":"ADBE Vector Shape - Group","hd":false},{"ind":31,"ty":"sh","ix":32,"ks":{"a":0,"k":{"i":[[0.191,0],[0,0],[0,0],[0,0],[-0.112,-0.112],[0,-0.185],[0.112,-0.102]],"o":[[0,0],[0,0],[0,0],[0.191,0],[0.112,0.112],[0,0.181],[-0.112,0.102]],"v":[[-36.154,8.257],[-36.722,8.257],[-36.722,7.066],[-36.154,7.066],[-35.699,7.234],[-35.531,7.679],[-35.699,8.104]],"c":true},"ix":2},"nm":"Path 32","mn":"ADBE Vector Shape - Group","hd":false},{"ind":32,"ty":"sh","ix":33,"ks":{"a":0,"k":{"i":[[0.178,0],[0,0],[0,0],[0,0],[-0.102,-0.096],[0,-0.161],[0.102,-0.096]],"o":[[0,0],[0,0],[0,0],[0.175,0],[0.102,0.092],[0,0.161],[-0.102,0.096]],"v":[[-36.183,6.621],[-36.722,6.621],[-36.722,5.568],[-36.178,5.568],[-35.763,5.712],[-35.61,6.092],[-35.763,6.478]],"c":true},"ix":2},"nm":"Path 33","mn":"ADBE Vector Shape - Group","hd":false},{"ind":33,"ty":"sh","ix":34,"ks":{"a":0,"k":{"i":[[-0.165,-0.086],[-0.224,0],[-0.165,0.086],[-0.089,0.158],[0,0.214],[0,0],[0.099,-0.102],[0.181,0],[0.102,0.099],[0,0.185],[0,0],[-0.099,0.099],[-0.181,0],[-0.099,-0.099],[0,-0.188],[0,0],[0.092,0.155],[0.165,0.086],[0.224,0],[0.168,-0.086],[0.092,-0.158],[0,-0.217],[0,0],[-0.089,-0.161]],"o":[[0.168,0.082],[0.224,0],[0.165,-0.086],[0.092,-0.158],[0,0],[0,0.185],[-0.099,0.099],[-0.181,0],[-0.099,-0.102],[0,0],[0,-0.185],[0.102,-0.099],[0.181,0],[0.099,0.099],[0,0],[0,-0.217],[-0.089,-0.158],[-0.165,-0.086],[-0.224,0],[-0.165,0.082],[-0.089,0.158],[0,0],[0,0.214],[0.092,0.158]],"v":[[-33.783,8.643],[-33.195,8.766],[-32.612,8.638],[-32.231,8.272],[-32.093,7.713],[-32.626,7.713],[-32.775,8.143],[-33.195,8.292],[-33.62,8.143],[-33.768,7.713],[-33.768,6.107],[-33.62,5.682],[-33.195,5.534],[-32.775,5.682],[-32.626,6.112],[-32.093,6.112],[-32.231,5.553],[-32.612,5.188],[-33.195,5.059],[-33.783,5.188],[-34.169,5.548],[-34.302,6.112],[-34.302,7.713],[-34.169,8.277]],"c":true},"ix":2},"nm":"Path 34","mn":"ADBE Vector Shape - Group","hd":false},{"ind":34,"ty":"sh","ix":35,"ks":{"a":0,"k":{"i":[[0,0],[0,0],[0,0],[0,0],[0,0],[0,0],[0,0],[0,0],[0,0],[0,0]],"o":[[0,0],[0,0],[0,0],[0,0],[0,0],[0,0],[0,0],[0,0],[0,0],[0,0]],"v":[[-24.506,8.524],[-24.506,9.166],[-21.788,9.166],[-21.788,8.562],[-23.751,8.562],[-21.858,6.348],[-21.858,5.706],[-24.449,5.706],[-24.449,6.31],[-22.638,6.31]],"c":true},"ix":2},"nm":"Path 35","mn":"ADBE Vector Shape - Group","hd":false},{"ind":35,"ty":"sh","ix":36,"ks":{"a":0,"k":{"i":[[0,0],[0,0],[0,0],[0,0],[-0.029,0.063],[-0.017,0.038],[-0.029,-0.063],[-0.029,-0.05],[0,0],[0,0],[0,0],[0,0],[0,0],[0,0],[0.029,-0.059],[0.013,-0.038],[0.029,0.055],[0.029,0.05],[0,0],[0,0]],"o":[[0,0],[0,0],[0,0],[0.034,-0.05],[0.034,-0.063],[0.017,0.038],[0.029,0.063],[0,0],[0,0],[0,0],[0,0],[0,0],[0,0],[-0.029,0.05],[-0.029,0.055],[-0.017,-0.038],[-0.029,-0.059],[0,0],[0,0],[0,0]],"v":[[-13.215,7.379],[-14.429,9.166],[-13.655,9.166],[-12.976,8.128],[-12.882,7.958],[-12.806,7.807],[-12.737,7.958],[-12.649,8.128],[-11.976,9.166],[-11.196,9.166],[-12.404,7.386],[-11.265,5.706],[-12.045,5.706],[-12.655,6.662],[-12.743,6.826],[-12.806,6.964],[-12.875,6.826],[-12.963,6.662],[-13.574,5.706],[-14.354,5.706]],"c":true},"ix":2},"nm":"Path 36","mn":"ADBE Vector Shape - Group","hd":false},{"ind":36,"ty":"sh","ix":37,"ks":{"a":0,"k":{"i":[[-0.214,-0.109],[-0.285,0],[-0.252,0.218],[-0.013,0.377],[0,0],[0.126,-0.109],[0.214,0],[0.134,0.13],[0,0.235],[0,0],[-0.134,0.126],[-0.231,0],[-0.126,-0.109],[-0.013,-0.197],[0,0],[0.252,0.218],[0.415,0],[0.218,-0.109],[0.117,-0.201],[0,-0.277],[0,0],[-0.113,-0.206]],"o":[[0.218,0.105],[0.415,0],[0.252,-0.218],[0,0],[-0.013,0.197],[-0.126,0.109],[-0.231,0],[-0.134,-0.13],[0,0],[0,-0.235],[0.134,-0.13],[0.214,0],[0.126,0.109],[0,0],[-0.013,-0.377],[-0.252,-0.218],[-0.285,0],[-0.214,0.105],[-0.113,0.201],[0,0],[0,0.273],[0.117,0.201]],"v":[[-3.207,9.072],[-2.452,9.229],[-1.452,8.902],[-1.056,8.009],[-1.735,8.009],[-1.943,8.468],[-2.452,8.631],[-3,8.436],[-3.201,7.889],[-3.201,6.977],[-3,6.436],[-2.452,6.241],[-1.943,6.404],[-1.735,6.864],[-1.056,6.864],[-1.452,5.97],[-2.452,5.643],[-3.207,5.807],[-3.704,6.266],[-3.874,6.983],[-3.874,7.889],[-3.704,8.606]],"c":true},"ix":2},"nm":"Path 37","mn":"ADBE Vector Shape - Group","hd":false},{"ind":37,"ty":"sh","ix":38,"ks":{"a":0,"k":{"i":[[0,0],[0,0],[0,0],[0,0],[0,0],[0,0],[0.038,-0.134],[0.021,-0.075],[0.038,0.13],[0.046,0.13],[0,0]],"o":[[0,0],[0,0],[0,0],[0,0],[0,0],[-0.038,0.13],[-0.034,0.13],[-0.017,-0.075],[-0.034,-0.134],[0,0],[0,0]],"v":[[6.266,5.706],[7.411,9.166],[8.304,9.166],[9.449,5.706],[8.763,5.706],[8.065,7.92],[7.952,8.317],[7.87,8.625],[7.788,8.317],[7.668,7.92],[6.958,5.706]],"c":true},"ix":2},"nm":"Path 38","mn":"ADBE Vector Shape - Group","hd":false},{"ind":38,"ty":"sh","ix":39,"ks":{"a":0,"k":{"i":[[-0.168,-0.159],[-0.285,0],[-0.21,0.235],[0,0.398],[0,0],[0.21,0.235],[0.348,0],[0.172,-0.159],[0,-0.273],[0,0],[0,0],[0,0],[0,0],[0,0],[0,0],[0,0],[0,0],[0,0],[0,0]],"o":[[0.168,0.155],[0.348,0],[0.21,-0.235],[0,0],[0,-0.403],[-0.21,-0.235],[-0.281,0],[-0.168,0.155],[0,0],[0,0],[0,0],[0,0],[0,0],[0,0],[0,0],[0,0],[0,0],[0,0],[0,0.273]],"v":[[17.758,8.996],[18.437,9.229],[19.274,8.877],[19.588,7.927],[19.588,6.952],[19.274,5.995],[18.437,5.643],[17.758,5.882],[17.506,6.524],[17.651,6.367],[17.494,6.367],[17.513,5.561],[17.513,4.574],[16.833,4.574],[16.833,9.166],[17.506,9.166],[17.506,8.506],[17.651,8.506],[17.506,8.348]],"c":true},"ix":2},"nm":"Path 39","mn":"ADBE Vector Shape - Group","hd":false},{"ind":39,"ty":"sh","ix":40,"ks":{"a":0,"k":{"i":[[0.126,-0.13],[0.222,0],[0.126,0.13],[0,0.235],[0,0],[-0.122,0.13],[-0.214,0],[-0.126,-0.13],[0,-0.243],[0,0]],"o":[[-0.126,0.126],[-0.214,0],[-0.122,-0.134],[0,0],[0,-0.235],[0.126,-0.134],[0.222,0],[0.126,0.126],[0,0],[0,0.243]],"v":[[18.727,8.449],[18.205,8.638],[17.695,8.443],[17.513,7.889],[17.513,6.983],[17.695,6.436],[18.205,6.235],[18.727,6.43],[18.915,6.983],[18.915,7.889]],"c":true},"ix":2},"nm":"Path 40","mn":"ADBE Vector Shape - Group","hd":false},{"ind":40,"ty":"sh","ix":41,"ks":{"a":0,"k":{"i":[[0,0],[0,0],[0,0],[0,0],[-0.122,0.126],[-0.214,0],[-0.122,-0.122],[0,-0.226],[0,0],[0,0],[0,0],[0.206,0.218],[0.344,0],[0.164,-0.155],[0,-0.277],[0,0],[0,0],[0,0]],"o":[[0,0],[0,0],[0,0],[0,-0.243],[0.126,-0.13],[0.21,0],[0.122,0.122],[0,0],[0,0],[0,0],[0,-0.373],[-0.206,-0.222],[-0.289,0],[-0.164,0.155],[0,0],[0,0],[0,0],[0,0]],"v":[[27.168,5.706],[27.168,9.166],[27.847,9.166],[27.847,6.983],[28.03,6.43],[28.539,6.235],[29.036,6.417],[29.219,6.939],[29.219,9.166],[29.898,9.166],[29.898,6.864],[29.59,5.977],[28.766,5.643],[28.086,5.876],[27.841,6.524],[28.005,6.367],[27.841,6.367],[27.841,5.706]],"c":true},"ix":2},"nm":"Path 41","mn":"ADBE Vector Shape - Group","hd":false},{"ind":41,"ty":"sh","ix":42,"ks":{"a":0,"k":{"i":[[0,0],[0,0],[0,0],[0,0],[-0.05,0.067],[-0.105,0],[-0.059,-0.071],[0,-0.134],[0,0],[0,0],[0,0],[-0.055,0.067],[-0.105,0],[-0.055,-0.071],[0,-0.13],[0,0],[0,0],[0,0],[0.122,0.159],[0.214,0],[0.109,-0.117],[0,-0.193],[0,0],[0,0],[0,0],[0.105,0.147],[0.189,0],[0.105,-0.117],[0,-0.193],[0,0],[0,0],[0,0]],"o":[[0,0],[0,0],[0,0],[0,-0.13],[0.055,-0.071],[0.109,0],[0.059,0.067],[0,0],[0,0],[0,0],[0,-0.13],[0.059,-0.071],[0.105,0],[0.059,0.071],[0,0],[0,0],[0,0],[0,-0.268],[-0.122,-0.164],[-0.18,0],[-0.105,0.113],[0,0],[0,0],[0,0],[0,-0.256],[-0.101,-0.147],[-0.176,0],[-0.105,0.113],[0,0],[0,0],[0,0],[0,0]],"v":[[37.345,5.706],[37.345,9.166],[37.956,9.166],[37.956,6.543],[38.031,6.247],[38.27,6.14],[38.522,6.247],[38.61,6.549],[38.61,9.166],[39.119,9.166],[39.119,6.543],[39.201,6.247],[39.447,6.14],[39.686,6.247],[39.774,6.549],[39.774,9.166],[40.378,9.166],[40.378,6.53],[40.195,5.889],[39.692,5.643],[39.258,5.819],[39.101,6.279],[39.201,6.146],[38.962,6.146],[39.113,6.467],[38.956,5.863],[38.522,5.643],[38.1,5.819],[37.943,6.279],[38.037,6.146],[37.912,6.146],[37.912,5.706]],"c":true},"ix":2},"nm":"Path 42","mn":"ADBE Vector Shape - Group","hd":false},{"ind":42,"ty":"sh","ix":43,"ks":{"a":0,"k":{"i":[[-0.133,0.034],[-0.2,0],[0,0],[-0.164,-0.013],[-0.152,-0.077],[-0.118,-0.233],[-0.014,-0.171],[0,-0.24],[0,0],[0.013,-0.164],[0.077,-0.152],[0.233,-0.118],[0.171,-0.014],[0.24,0],[0,0],[0.151,0.039],[0.115,0.076],[0.135,0.148],[0,0],[-0.117,0.129],[0,0],[-0.13,0.086]],"o":[[0.151,-0.039],[0,0],[0.24,0],[0.171,0.014],[0.233,0.118],[0.077,0.152],[0.013,0.164],[0,0],[0,0.24],[-0.014,0.171],[-0.118,0.233],[-0.152,0.077],[-0.164,0.013],[0,0],[-0.2,0],[-0.133,-0.034],[-0.13,-0.086],[0,0],[-0.117,-0.129],[0,0],[0.135,-0.148],[0.115,-0.076]],"v":[[-42.693,18.124],[-42.183,18.085],[-40.255,18.085],[-39.651,18.099],[-39.168,18.22],[-38.628,18.76],[-38.507,19.243],[-38.493,19.847],[-38.493,20.952],[-38.507,21.556],[-38.628,22.039],[-39.168,22.579],[-39.651,22.7],[-40.255,22.714],[-42.183,22.714],[-42.693,22.675],[-43.067,22.509],[-43.438,22.158],[-44.831,20.626],[-44.831,20.173],[-43.438,18.641],[-43.067,18.29]],"c":true},"ix":2},"nm":"Path 43","mn":"ADBE Vector Shape - Group","hd":false},{"ind":43,"ty":"sh","ix":44,"ks":{"a":0,"k":{"i":[[0,0],[0.059,-0.015],[0.052,-0.034],[0.169,-0.186],[0,0],[0,0],[-0.051,-0.033],[-0.061,-0.015],[-0.251,0],[0,0],[-0.133,0.011],[-0.041,0.021],[-0.054,0.106],[-0.011,0.129],[0,0.257],[0,0],[0.011,0.133],[0.021,0.041],[0.106,0.054],[0.129,0.011],[0.257,0]],"o":[[-0.251,0],[-0.061,0.015],[-0.051,0.033],[0,0],[0,0],[0.169,0.186],[0.052,0.034],[0.059,0.015],[0,0],[0.257,0],[0.129,-0.011],[0.106,-0.054],[0.021,-0.041],[0.011,-0.133],[0,0],[0,-0.257],[-0.011,-0.129],[-0.054,-0.106],[-0.041,-0.021],[-0.133,-0.011],[0,0]],"v":[[-42.149,18.759],[-42.526,18.777],[-42.696,18.852],[-42.963,19.12],[-44.127,20.4],[-42.963,21.679],[-42.696,21.947],[-42.526,22.022],[-42.149,22.04],[-40.268,22.04],[-39.706,22.029],[-39.474,21.978],[-39.229,21.733],[-39.179,21.502],[-39.167,20.939],[-39.167,19.86],[-39.179,19.298],[-39.229,19.066],[-39.474,18.821],[-39.706,18.771],[-40.268,18.759]],"c":true},"ix":2},"nm":"Path 44","mn":"ADBE Vector Shape - Group","hd":false},{"ind":44,"ty":"sh","ix":45,"ks":{"a":0,"k":{"i":[[-0.132,0.132],[-0.132,-0.132],[0,0],[0,0],[-0.132,-0.132],[0.132,-0.132],[0,0],[0,0],[0.132,-0.132],[0.132,0.132],[0,0],[0,0],[0.132,0.132],[-0.132,0.132],[0,0],[0,0]],"o":[[0.132,-0.132],[0,0],[0,0],[0.132,-0.132],[0.132,0.132],[0,0],[0,0],[0.132,0.132],[-0.132,0.132],[0,0],[0,0],[-0.132,0.132],[-0.132,-0.132],[0,0],[0,0],[-0.132,-0.132]],"v":[[-42.168,19.399],[-41.691,19.399],[-41.167,19.923],[-40.643,19.399],[-40.166,19.399],[-40.166,19.875],[-40.69,20.4],[-40.166,20.924],[-40.166,21.4],[-40.643,21.4],[-41.167,20.876],[-41.691,21.4],[-42.168,21.4],[-42.168,20.924],[-41.644,20.4],[-42.168,19.875]],"c":true},"ix":2},"nm":"Path 45","mn":"ADBE Vector Shape - Group","hd":false},{"ind":45,"ty":"sh","ix":46,"ks":{"a":0,"k":{"i":[[0,0],[0,0],[0,0],[0,0],[0,0],[0,0],[0,0],[0,0],[0,0],[0,0],[0,0]],"o":[[0,0],[0,0],[0,0],[0,0],[0,0],[0,0],[0,0],[0,0],[0,0],[0,0],[0,0]],"v":[[-28.063,21.722],[-28.063,22.197],[-25.794,22.197],[-25.794,21.722],[-26.57,21.722],[-26.57,18.589],[-27.242,18.589],[-28.068,19.192],[-28.068,19.77],[-27.104,19.053],[-27.104,21.722]],"c":true},"ix":2},"nm":"Path 46","mn":"ADBE Vector Shape - Group","hd":false},{"ind":46,"ty":"sh","ix":47,"ks":{"a":0,"k":{"i":[[0,0],[0,0],[0,0],[0,0],[0,0],[0,0],[-0.109,0.204],[0,0.214],[0.089,0.155],[0.165,0.086],[0.221,0],[0.171,-0.089],[0.096,-0.165],[0.007,-0.224],[0,0],[-0.109,0.109],[-0.191,0],[-0.099,-0.105],[0,-0.185],[0.082,-0.145],[0.171,-0.178]],"o":[[0,0],[0,0],[0,0],[0,0],[0,0],[0.25,-0.25],[0.112,-0.204],[0,-0.211],[-0.089,-0.155],[-0.165,-0.086],[-0.231,0],[-0.171,0.089],[-0.096,0.161],[0,0],[0,-0.191],[0.112,-0.112],[0.175,0],[0.102,0.105],[0,0.142],[-0.079,0.142],[0,0]],"v":[[-25.109,21.668],[-25.109,22.197],[-22.904,22.197],[-22.904,21.712],[-24.481,21.712],[-23.666,20.887],[-23.127,20.205],[-22.959,19.577],[-23.092,19.029],[-23.473,18.668],[-24.051,18.539],[-24.654,18.673],[-25.055,19.053],[-25.208,19.632],[-24.674,19.632],[-24.511,19.182],[-24.056,19.014],[-23.646,19.172],[-23.493,19.607],[-23.616,20.037],[-23.992,20.516]],"c":true},"ix":2},"nm":"Path 47","mn":"ADBE Vector Shape - Group","hd":false},{"ind":47,"ty":"sh","ix":48,"ks":{"a":0,"k":{"i":[[-0.168,-0.086],[-0.227,0],[-0.168,0.086],[-0.092,0.155],[0,0.208],[0,0],[0.201,0.188],[0.343,0],[0,0],[0,0],[0,0],[0,0],[0,0],[0,0],[0,0],[0,0],[0,0],[-0.102,-0.102],[0,-0.185],[0,0],[0.102,-0.105],[0.188,0],[0.105,0.102],[0,0.181],[0,0],[-0.089,-0.158]],"o":[[0.168,0.086],[0.227,0],[0.171,-0.086],[0.092,-0.158],[0,0],[0,-0.316],[-0.201,-0.188],[0,0],[0,0],[0,0],[0,0],[0,0],[0,0],[0,0],[0,0],[0,0],[0.188,0],[0.102,0.099],[0,0],[0,0.175],[-0.102,0.105],[-0.185,0],[-0.102,-0.102],[0,0],[0,0.208],[0.092,0.155]],"v":[[-21.72,22.118],[-21.127,22.246],[-20.534,22.118],[-20.138,21.757],[-20,21.208],[-20,20.936],[-20.302,20.18],[-21.117,19.898],[-21.117,20.027],[-20.124,19.093],[-20.124,18.589],[-22.091,18.589],[-22.091,19.058],[-20.667,19.058],[-21.508,19.859],[-21.508,20.363],[-21.122,20.363],[-20.687,20.516],[-20.534,20.941],[-20.534,21.208],[-20.687,21.628],[-21.122,21.787],[-21.557,21.633],[-21.71,21.208],[-22.244,21.208],[-22.111,21.757]],"c":true},"ix":2},"nm":"Path 48","mn":"ADBE Vector Shape - Group","hd":false},{"ind":48,"ty":"sh","ix":49,"ks":{"a":0,"k":{"i":[[0,0],[0.175,0.175],[0.175,-0.175],[0,0],[0,0],[0.175,-0.175],[-0.175,-0.175],[0,0],[-0.175,0.175]],"o":[[0.175,-0.175],[-0.175,-0.175],[0,0],[0,0],[-0.175,-0.175],[-0.175,0.175],[0,0],[0.175,0.175],[0,0]],"v":[[43.971,19.219],[43.971,18.584],[43.335,18.584],[40.658,21.262],[39.777,20.381],[39.142,20.381],[39.142,21.017],[40.34,22.215],[40.975,22.215]],"c":true},"ix":2},"nm":"Path 49","mn":"ADBE Vector Shape - Group","hd":false},{"ty":"mm","mm":1,"nm":"Merge Paths 1","mn":"ADBE Vector Filter - Merge","hd":false},{"ty":"fl","c":{"a":0,"k":[1,1,1,1],"ix":4},"o":{"a":0,"k":100,"ix":5},"r":1,"bm":0,"nm":"Fill 1","mn":"ADBE Vector Graphic - Fill","hd":false},{"ty":"tr","p":{"a":0,"k":[0,0],"ix":2},"a":{"a":0,"k":[0,0],"ix":1},"s":{"a":0,"k":[100,100],"ix":3},"r":{"a":0,"k":0,"ix":6},"o":{"a":0,"k":100,"ix":7},"sk":{"a":0,"k":0,"ix":4},"sa":{"a":0,"k":0,"ix":5},"nm":"Transform"}],"nm":"Keys","np":51,"cix":2,"bm":0,"ix":1,"mn":"ADBE Vector Group","hd":false}],"ip":0,"op":300,"st":0,"bm":0},{"ddd":0,"ind":3,"ty":4,"nm":"Gray Background","parent":1,"sr":1,"ks":{"o":{"a":0,"k":100,"ix":11},"r":{"a":0,"k":0,"ix":10},"p":{"a":0,"k":[51,25.612,0],"ix":2},"a":{"a":0,"k":[0,0,0],"ix":1},"s":{"a":0,"k":[100,100,100],"ix":6}},"ao":0,"shapes":[{"ty":"gr","it":[{"ind":0,"ty":"sh","ix":1,"ks":{"a":0,"k":{"i":[[0,0],[0,-0.993],[0,0],[-0.993,0],[0,0],[0,0.993],[0,0],[0.993,0]],"o":[[-0.993,0],[0,0],[0,0.993],[0,0],[0.993,0],[0,0],[0,-0.993],[0,0]],"v":[[-49.203,-25.612],[-51,-23.815],[-51,-16.626],[-49.203,-14.828],[-43.811,-14.828],[-42.013,-16.626],[-42.013,-23.815],[-43.811,-25.612]],"c":true},"ix":2},"nm":"Path 1","mn":"ADBE Vector Shape - Group","hd":false},{"ind":1,"ty":"sh","ix":2,"ks":{"a":0,"k":{"i":[[0,0],[0,-0.993],[0,0],[-0.993,0],[0,0],[0,0.993],[0,0],[0.993,0]],"o":[[-0.993,0],[0,0],[0,0.993],[0,0],[0.993,0],[0,0],[0,-0.993],[0,0]],"v":[[-38.868,-25.612],[-40.665,-23.815],[-40.665,-16.626],[-38.868,-14.828],[-33.476,-14.828],[-31.678,-16.626],[-31.678,-23.815],[-33.476,-25.612]],"c":true},"ix":2},"nm":"Path 2","mn":"ADBE Vector Shape - Group","hd":false},{"ind":2,"ty":"sh","ix":3,"ks":{"a":0,"k":{"i":[[0,0],[-0.993,0],[0,0],[0,-0.993],[0,0],[0.993,0],[0,0],[0,0.993]],"o":[[0,-0.993],[0,0],[0.993,0],[0,0],[0,0.993],[0,0],[-0.993,0],[0,0]],"v":[[-30.33,-23.815],[-28.533,-25.612],[-23.141,-25.612],[-21.344,-23.815],[-21.344,-16.626],[-23.141,-14.828],[-28.533,-14.828],[-30.33,-16.626]],"c":true},"ix":2},"nm":"Path 3","mn":"ADBE Vector Shape - Group","hd":false},{"ind":3,"ty":"sh","ix":4,"ks":{"a":0,"k":{"i":[[0,0],[0,-0.993],[0,0],[-0.993,0],[0,0],[0,0.993],[0,0],[0.993,0]],"o":[[-0.993,0],[0,0],[0,0.993],[0,0],[0.993,0],[0,0],[0,-0.993],[0,0]],"v":[[-18.198,-25.612],[-19.996,-23.815],[-19.996,-16.626],[-18.198,-14.828],[-12.806,-14.828],[-11.009,-16.626],[-11.009,-23.815],[-12.806,-25.612]],"c":true},"ix":2},"nm":"Path 4","mn":"ADBE Vector Shape - Group","hd":false},{"ind":4,"ty":"sh","ix":5,"ks":{"a":0,"k":{"i":[[0,0],[-0.993,0],[0,0],[0,-0.993],[0,0],[0.993,0],[0,0],[0,0.993]],"o":[[0,-0.993],[0,0],[0.993,0],[0,0],[0,0.993],[0,0],[-0.993,0],[0,0]],"v":[[-9.661,-23.815],[-7.863,-25.612],[-2.471,-25.612],[-0.674,-23.815],[-0.674,-16.626],[-2.471,-14.828],[-7.863,-14.828],[-9.661,-16.626]],"c":true},"ix":2},"nm":"Path 5","mn":"ADBE Vector Shape - Group","hd":false},{"ind":5,"ty":"sh","ix":6,"ks":{"a":0,"k":{"i":[[0,0],[0,-0.993],[0,0],[-0.993,0],[0,0],[0,0.993],[0,0],[0.993,0]],"o":[[-0.993,0],[0,0],[0,0.993],[0,0],[0.993,0],[0,0],[0,-0.993],[0,0]],"v":[[2.471,-25.612],[0.674,-23.815],[0.674,-16.626],[2.471,-14.828],[7.863,-14.828],[9.661,-16.626],[9.661,-23.815],[7.863,-25.612]],"c":true},"ix":2},"nm":"Path 6","mn":"ADBE Vector Shape - Group","hd":false},{"ind":6,"ty":"sh","ix":7,"ks":{"a":0,"k":{"i":[[0,0],[-0.993,0],[0,0],[0,-0.993],[0,0],[0.993,0],[0,0],[0,0.993]],"o":[[0,-0.993],[0,0],[0.993,0],[0,0],[0,0.993],[0,0],[-0.993,0],[0,0]],"v":[[11.009,-23.815],[12.806,-25.612],[18.198,-25.612],[19.996,-23.815],[19.996,-16.626],[18.198,-14.828],[12.806,-14.828],[11.009,-16.626]],"c":true},"ix":2},"nm":"Path 7","mn":"ADBE Vector Shape - Group","hd":false},{"ind":7,"ty":"sh","ix":8,"ks":{"a":0,"k":{"i":[[0,0],[0,-0.993],[0,0],[-0.993,0],[0,0],[0,0.993],[0,0],[0.993,0]],"o":[[-0.993,0],[0,0],[0,0.993],[0,0],[0.993,0],[0,0],[0,-0.993],[0,0]],"v":[[23.141,-25.612],[21.344,-23.815],[21.344,-16.626],[23.141,-14.828],[28.533,-14.828],[30.33,-16.626],[30.33,-23.815],[28.533,-25.612]],"c":true},"ix":2},"nm":"Path 8","mn":"ADBE Vector Shape - Group","hd":false},{"ind":8,"ty":"sh","ix":9,"ks":{"a":0,"k":{"i":[[0,0],[-0.993,0],[0,0],[0,-0.993],[0,0],[0.993,0],[0,0],[0,0.993]],"o":[[0,-0.993],[0,0],[0.993,0],[0,0],[0,0.993],[0,0],[-0.993,0],[0,0]],"v":[[31.678,-23.815],[33.476,-25.612],[38.868,-25.612],[40.665,-23.815],[40.665,-16.626],[38.868,-14.828],[33.476,-14.828],[31.678,-16.626]],"c":true},"ix":2},"nm":"Path 9","mn":"ADBE Vector Shape - Group","hd":false},{"ind":9,"ty":"sh","ix":10,"ks":{"a":0,"k":{"i":[[0,0],[0,-0.993],[0,0],[-0.993,0],[0,0],[0,0.993],[0,0],[0.993,0]],"o":[[-0.993,0],[0,0],[0,0.993],[0,0],[0.993,0],[0,0],[0,-0.993],[0,0]],"v":[[43.811,-25.612],[42.013,-23.815],[42.013,-16.626],[43.811,-14.828],[49.203,-14.828],[51,-16.626],[51,-23.815],[49.203,-25.612]],"c":true},"ix":2},"nm":"Path 10","mn":"ADBE Vector Shape - Group","hd":false},{"ind":10,"ty":"sh","ix":11,"ks":{"a":0,"k":{"i":[[0,0],[-0.993,0],[0,0],[0,-0.993],[0,0],[0.993,0],[0,0],[0,0.993]],"o":[[0,-0.993],[0,0],[0.993,0],[0,0],[0,0.993],[0,0],[-0.993,0],[0,0]],"v":[[-45.833,-10.335],[-44.035,-12.132],[-38.643,-12.132],[-36.846,-10.335],[-36.846,-3.145],[-38.643,-1.348],[-44.035,-1.348],[-45.833,-3.145]],"c":true},"ix":2},"nm":"Path 11","mn":"ADBE Vector Shape - Group","hd":false},{"ind":11,"ty":"sh","ix":12,"ks":{"a":0,"k":{"i":[[0,0],[0,-0.993],[0,0],[-0.993,0],[0,0],[0,0.993],[0,0],[0.993,0]],"o":[[-0.993,0],[0,0],[0,0.993],[0,0],[0.993,0],[0,0],[0,-0.993],[0,0]],"v":[[-33.7,-12.132],[-35.498,-10.335],[-35.498,-3.145],[-33.7,-1.348],[-28.308,-1.348],[-26.511,-3.145],[-26.511,-10.335],[-28.308,-12.132]],"c":true},"ix":2},"nm":"Path 12","mn":"ADBE Vector Shape - Group","hd":false},{"ind":12,"ty":"sh","ix":13,"ks":{"a":0,"k":{"i":[[0,0],[-0.993,0],[0,0],[0,-0.993],[0,0],[0.993,0],[0,0],[0,0.993]],"o":[[0,-0.993],[0,0],[0.993,0],[0,0],[0,0.993],[0,0],[-0.993,0],[0,0]],"v":[[-25.163,-10.335],[-23.366,-12.132],[-17.974,-12.132],[-16.176,-10.335],[-16.176,-3.145],[-17.974,-1.348],[-23.366,-1.348],[-25.163,-3.145]],"c":true},"ix":2},"nm":"Path 13","mn":"ADBE Vector Shape - Group","hd":false},{"ind":13,"ty":"sh","ix":14,"ks":{"a":0,"k":{"i":[[0,0],[0,-0.993],[0,0],[-0.993,0],[0,0],[0,0.993],[0,0],[0.993,0]],"o":[[-0.993,0],[0,0],[0,0.993],[0,0],[0.993,0],[0,0],[0,-0.993],[0,0]],"v":[[-13.031,-12.132],[-14.828,-10.335],[-14.828,-3.145],[-13.031,-1.348],[-7.639,-1.348],[-5.841,-3.145],[-5.841,-10.335],[-7.639,-12.132]],"c":true},"ix":2},"nm":"Path 14","mn":"ADBE Vector Shape - Group","hd":false},{"ind":14,"ty":"sh","ix":15,"ks":{"a":0,"k":{"i":[[0,0],[-0.993,0],[0,0],[0,-0.993],[0,0],[0.993,0],[0,0],[0,0.993]],"o":[[0,-0.993],[0,0],[0.993,0],[0,0],[0,0.993],[0,0],[-0.993,0],[0,0]],"v":[[-4.493,-10.335],[-2.696,-12.132],[2.696,-12.132],[4.493,-10.335],[4.493,-3.145],[2.696,-1.348],[-2.696,-1.348],[-4.493,-3.145]],"c":true},"ix":2},"nm":"Path 15","mn":"ADBE Vector Shape - Group","hd":false},{"ind":15,"ty":"sh","ix":16,"ks":{"a":0,"k":{"i":[[0,0],[0,-0.993],[0,0],[-0.993,0],[0,0],[0,0.993],[0,0],[0.993,0]],"o":[[-0.993,0],[0,0],[0,0.993],[0,0],[0.993,0],[0,0],[0,-0.993],[0,0]],"v":[[7.639,-12.132],[5.841,-10.335],[5.841,-3.145],[7.639,-1.348],[13.031,-1.348],[14.828,-3.145],[14.828,-10.335],[13.031,-12.132]],"c":true},"ix":2},"nm":"Path 16","mn":"ADBE Vector Shape - Group","hd":false},{"ind":16,"ty":"sh","ix":17,"ks":{"a":0,"k":{"i":[[0,0],[-0.993,0],[0,0],[0,-0.993],[0,0],[0.993,0],[0,0],[0,0.993]],"o":[[0,-0.993],[0,0],[0.993,0],[0,0],[0,0.993],[0,0],[-0.993,0],[0,0]],"v":[[16.176,-10.335],[17.974,-12.132],[23.366,-12.132],[25.163,-10.335],[25.163,-3.145],[23.366,-1.348],[17.974,-1.348],[16.176,-3.145]],"c":true},"ix":2},"nm":"Path 17","mn":"ADBE Vector Shape - Group","hd":false},{"ind":17,"ty":"sh","ix":18,"ks":{"a":0,"k":{"i":[[0,0],[0,-0.993],[0,0],[-0.993,0],[0,0],[0,0.993],[0,0],[0.993,0]],"o":[[-0.993,0],[0,0],[0,0.993],[0,0],[0.993,0],[0,0],[0,-0.993],[0,0]],"v":[[28.308,-12.132],[26.511,-10.335],[26.511,-3.145],[28.308,-1.348],[33.7,-1.348],[35.498,-3.145],[35.498,-10.335],[33.7,-12.132]],"c":true},"ix":2},"nm":"Path 18","mn":"ADBE Vector Shape - Group","hd":false},{"ind":18,"ty":"sh","ix":19,"ks":{"a":0,"k":{"i":[[0,0],[-0.993,0],[0,0],[0,-0.993],[0,0],[0.993,0],[0,0],[0,0.993]],"o":[[0,-0.993],[0,0],[0.993,0],[0,0],[0,0.993],[0,0],[-0.993,0],[0,0]],"v":[[36.846,-10.335],[38.643,-12.132],[44.035,-12.132],[45.833,-10.335],[45.833,-3.145],[44.035,-1.348],[38.643,-1.348],[36.846,-3.145]],"c":true},"ix":2},"nm":"Path 19","mn":"ADBE Vector Shape - Group","hd":false},{"ind":19,"ty":"sh","ix":20,"ks":{"a":0,"k":{"i":[[0,0],[0,-0.993],[0,0],[-0.993,0],[0,0],[0,0.993],[0,0],[0.993,0]],"o":[[-0.993,0],[0,0],[0,0.993],[0,0],[0.993,0],[0,0],[0,-0.993],[0,0]],"v":[[-41.564,1.348],[-43.361,3.145],[-43.361,10.335],[-41.564,12.132],[-30.78,12.132],[-28.982,10.335],[-28.982,3.145],[-30.78,1.348]],"c":true},"ix":2},"nm":"Path 20","mn":"ADBE Vector Shape - Group","hd":false},{"ind":20,"ty":"sh","ix":21,"ks":{"a":0,"k":{"i":[[0,0],[-0.993,0],[0,0],[0,-0.993],[0,0],[0.993,0],[0,0],[0,0.993]],"o":[[0,-0.993],[0,0],[0.993,0],[0,0],[0,0.993],[0,0],[-0.993,0],[0,0]],"v":[[-27.634,3.145],[-25.837,1.348],[-20.445,1.348],[-18.648,3.145],[-18.648,10.335],[-20.445,12.132],[-25.837,12.132],[-27.634,10.335]],"c":true},"ix":2},"nm":"Path 21","mn":"ADBE Vector Shape - Group","hd":false},{"ind":21,"ty":"sh","ix":22,"ks":{"a":0,"k":{"i":[[0,0],[0,-0.993],[0,0],[-0.993,0],[0,0],[0,0.993],[0,0],[0.993,0]],"o":[[-0.993,0],[0,0],[0,0.993],[0,0],[0.993,0],[0,0],[0,-0.993],[0,0]],"v":[[-15.502,1.348],[-17.3,3.145],[-17.3,10.335],[-15.502,12.132],[-10.11,12.132],[-8.313,10.335],[-8.313,3.145],[-10.11,1.348]],"c":true},"ix":2},"nm":"Path 22","mn":"ADBE Vector Shape - Group","hd":false},{"ind":22,"ty":"sh","ix":23,"ks":{"a":0,"k":{"i":[[0,0],[-0.993,0],[0,0],[0,-0.993],[0,0],[0.993,0],[0,0],[0,0.993]],"o":[[0,-0.993],[0,0],[0.993,0],[0,0],[0,0.993],[0,0],[-0.993,0],[0,0]],"v":[[-6.965,3.145],[-5.167,1.348],[0.225,1.348],[2.022,3.145],[2.022,10.335],[0.225,12.132],[-5.167,12.132],[-6.965,10.335]],"c":true},"ix":2},"nm":"Path 23","mn":"ADBE Vector Shape - Group","hd":false},{"ind":23,"ty":"sh","ix":24,"ks":{"a":0,"k":{"i":[[0,0],[0,-0.993],[0,0],[-0.993,0],[0,0],[0,0.993],[0,0],[0.993,0]],"o":[[-0.993,0],[0,0],[0,0.993],[0,0],[0.993,0],[0,0],[0,-0.993],[0,0]],"v":[[5.167,1.348],[3.37,3.145],[3.37,10.335],[5.167,12.132],[10.559,12.132],[12.357,10.335],[12.357,3.145],[10.559,1.348]],"c":true},"ix":2},"nm":"Path 24","mn":"ADBE Vector Shape - Group","hd":false},{"ind":24,"ty":"sh","ix":25,"ks":{"a":0,"k":{"i":[[0,0],[-0.993,0],[0,0],[0,-0.993],[0,0],[0.993,0],[0,0],[0,0.993]],"o":[[0,-0.993],[0,0],[0.993,0],[0,0],[0,0.993],[0,0],[-0.993,0],[0,0]],"v":[[13.705,3.145],[15.502,1.348],[20.894,1.348],[22.692,3.145],[22.692,10.335],[20.894,12.132],[15.502,12.132],[13.705,10.335]],"c":true},"ix":2},"nm":"Path 25","mn":"ADBE Vector Shape - Group","hd":false},{"ind":25,"ty":"sh","ix":26,"ks":{"a":0,"k":{"i":[[0,0],[0,-0.993],[0,0],[-0.993,0],[0,0],[0,0.993],[0,0],[0.993,0]],"o":[[-0.993,0],[0,0],[0,0.993],[0,0],[0.993,0],[0,0],[0,-0.993],[0,0]],"v":[[25.837,1.348],[24.04,3.145],[24.04,10.335],[25.837,12.132],[31.229,12.132],[33.026,10.335],[33.026,3.145],[31.229,1.348]],"c":true},"ix":2},"nm":"Path 26","mn":"ADBE Vector Shape - Group","hd":false},{"ind":26,"ty":"sh","ix":27,"ks":{"a":0,"k":{"i":[[0,0],[-0.993,0],[0,0],[0,-0.993],[0,0],[0.993,0],[0,0],[0,0.993]],"o":[[0,-0.993],[0,0],[0.993,0],[0,0],[0,0.993],[0,0],[-0.993,0],[0,0]],"v":[[34.374,3.145],[36.172,1.348],[41.564,1.348],[43.361,3.145],[43.361,10.335],[41.564,12.132],[36.172,12.132],[34.374,10.335]],"c":true},"ix":2},"nm":"Path 27","mn":"ADBE Vector Shape - Group","hd":false},{"ind":27,"ty":"sh","ix":28,"ks":{"a":0,"k":{"i":[[0,0],[0,-0.993],[0,0],[-0.993,0],[0,0],[0,0.993],[0,0],[0.993,0]],"o":[[-0.993,0],[0,0],[0,0.993],[0,0],[0.993,0],[0,0],[0,-0.993],[0,0]],"v":[[-29.432,14.828],[-31.229,16.626],[-31.229,23.815],[-29.432,25.612],[-18.648,25.612],[-16.85,23.815],[-16.85,16.626],[-18.648,14.828]],"c":true},"ix":2},"nm":"Path 28","mn":"ADBE Vector Shape - Group","hd":false},{"ind":28,"ty":"sh","ix":29,"ks":{"a":0,"k":{"i":[[0,0],[-0.993,0],[0,0],[0,-0.993],[0,0],[0.993,0],[0,0],[0,0.993]],"o":[[0,-0.993],[0,0],[0.993,0],[0,0],[0,0.993],[0,0],[-0.993,0],[0,0]],"v":[[-15.502,16.626],[-13.705,14.828],[29.432,14.828],[31.229,16.626],[31.229,23.815],[29.432,25.612],[-13.705,25.612],[-15.502,23.815]],"c":true},"ix":2},"nm":"Path 29","mn":"ADBE Vector Shape - Group","hd":false},{"ty":"mm","mm":1,"nm":"Merge Paths 1","mn":"ADBE Vector Filter - Merge","hd":false},{"ty":"fl","c":{"a":0,"k":[0.45360827446,0.45360827446,0.54639172554,1],"ix":4},"o":{"a":0,"k":100,"ix":5},"r":1,"bm":0,"nm":"Fill 1","mn":"ADBE Vector Graphic - Fill","hd":false},{"ty":"tr","p":{"a":0,"k":[0,0],"ix":2},"a":{"a":0,"k":[0,0],"ix":1},"s":{"a":0,"k":[100,100],"ix":3},"r":{"a":0,"k":0,"ix":6},"o":{"a":0,"k":100,"ix":7},"sk":{"a":0,"k":0,"ix":4},"sa":{"a":0,"k":0,"ix":5},"nm":"Transform"}],"nm":"Gray Background","np":31,"cix":2,"bm":0,"ix":1,"mn":"ADBE Vector Group","hd":false}],"ip":0,"op":300,"st":0,"bm":0},{"ddd":0,"ind":4,"ty":4,"nm":"Red Backgroud","parent":1,"sr":1,"ks":{"o":{"a":0,"k":100,"ix":11},"r":{"a":0,"k":0,"ix":10},"p":{"a":0,"k":[9.436,45.832,0],"ix":2},"a":{"a":0,"k":[0,0,0],"ix":1},"s":{"a":0,"k":[100,100,100],"ix":6}},"ao":0,"shapes":[{"ty":"gr","it":[{"ty":"rc","d":1,"s":{"a":0,"k":[17.974,10.784],"ix":2},"p":{"a":0,"k":[0,0],"ix":3},"r":{"a":0,"k":8,"ix":4},"nm":"Rectangle Path 1","mn":"ADBE Vector Shape - Rect","hd":false},{"ty":"fl","c":{"a":0,"k":[0.874000012875,0.197799995542,0.046000003815,1],"ix":4},"o":{"a":0,"k":100,"ix":5},"r":1,"bm":0,"nm":"Fill 1","mn":"ADBE Vector Graphic - Fill","hd":false},{"ty":"tr","p":{"a":0,"k":[0,0],"ix":2},"a":{"a":0,"k":[0,0],"ix":1},"s":{"a":0,"k":[100,100],"ix":3},"r":{"a":0,"k":0,"ix":6},"o":{"a":0,"k":100,"ix":7},"sk":{"a":0,"k":0,"ix":4},"sa":{"a":0,"k":0,"ix":5},"nm":"Transform"}],"nm":"Red Backgroud","np":2,"cix":2,"bm":0,"ix":1,"mn":"ADBE Vector Group","hd":false}],"ip":0,"op":300,"st":0,"bm":0},{"ddd":0,"ind":5,"ty":4,"nm":"Green Background","parent":1,"sr":1,"ks":{"o":{"a":0,"k":100,"ix":11},"r":{"a":0,"k":0,"ix":10},"p":{"a":0,"k":[92.564,45.832,0],"ix":2},"a":{"a":0,"k":[0,0,0],"ix":1},"s":{"a":0,"k":[100,100,100],"ix":6}},"ao":0,"shapes":[{"ty":"gr","it":[{"ty":"rc","d":1,"s":{"a":0,"k":[17.974,10.784],"ix":2},"p":{"a":0,"k":[0,0],"ix":3},"r":{"a":0,"k":8,"ix":4},"nm":"Rectangle Path 1","mn":"ADBE Vector Shape - Rect","hd":false},{"ty":"fl","c":{"a":0,"k":[0,0.800000011921,0.211764708161,1],"ix":4},"o":{"a":0,"k":100,"ix":5},"r":1,"bm":0,"nm":"Fill 1","mn":"ADBE Vector Graphic - Fill","hd":false},{"ty":"tr","p":{"a":0,"k":[0,0],"ix":2},"a":{"a":0,"k":[0,0],"ix":1},"s":{"a":0,"k":[100,100],"ix":3},"r":{"a":0,"k":0,"ix":6},"o":{"a":0,"k":100,"ix":7},"sk":{"a":0,"k":0,"ix":4},"sa":{"a":0,"k":0,"ix":5},"nm":"Transform"}],"nm":"Green Background","np":2,"cix":2,"bm":0,"ix":1,"mn":"ADBE Vector Group","hd":false}],"ip":0,"op":300,"st":0,"bm":0},{"ddd":0,"ind":6,"ty":4,"nm":"Enter Passphrase","sr":1,"ks":{"o":{"a":0,"k":100,"ix":11},"r":{"a":0,"k":0,"ix":10},"p":{"a":0,"k":[68.66,47.362,0],"ix":2},"a":{"a":0,"k":[0,0,0],"ix":1},"s":{"a":0,"k":[100,100,100],"ix":6}},"ao":0,"shapes":[{"ty":"gr","it":[{"ind":0,"ty":"sh","ix":1,"ks":{"a":0,"k":{"i":[[0,0],[0,0],[0,0],[0,0],[0,0],[0,0],[0,0],[0,0],[0,0],[0,0],[0,0],[0,0]],"o":[[0,0],[0,0],[0,0],[0,0],[0,0],[0,0],[0,0],[0,0],[0,0],[0,0],[0,0],[0,0]],"v":[[-34.221,2.638],[-38.909,2.638],[-38.909,-4.418],[-34.221,-4.418],[-34.221,-3.282],[-37.621,-3.282],[-37.621,-1.473],[-34.41,-1.473],[-34.41,-0.336],[-37.621,-0.336],[-37.621,1.501],[-34.221,1.501]],"c":true},"ix":2},"nm":"Path 1","mn":"ADBE Vector Shape - Group","hd":false},{"ind":1,"ty":"sh","ix":2,"ks":{"a":0,"k":{"i":[[0,0],[0,0],[0,0],[0,0],[0,0],[-0.253,0.126],[-0.322,0],[-0.29,-0.164],[-0.164,-0.297],[0,-0.385],[0,0],[0,0],[0,0],[0.196,0.196],[0.309,0],[0.196,-0.202],[0,-0.335]],"o":[[0,0],[0,0],[0,0],[0,0],[0.139,-0.246],[0.259,-0.126],[0.379,0],[0.297,0.164],[0.164,0.29],[0,0],[0,0],[0,0],[0,-0.341],[-0.189,-0.202],[-0.309,0],[-0.189,0.202],[0,0]],"v":[[-32.14,2.638],[-33.381,2.638],[-33.381,-2.514],[-32.216,-2.514],[-32.216,-1.88],[-31.629,-2.439],[-30.757,-2.628],[-29.754,-2.382],[-29.062,-1.69],[-28.816,-0.677],[-28.816,2.638],[-30.057,2.638],[-30.057,-0.384],[-30.35,-1.189],[-31.098,-1.492],[-31.856,-1.189],[-32.14,-0.384]],"c":true},"ix":2},"nm":"Path 2","mn":"ADBE Vector Shape - Group","hd":false},{"ind":2,"ty":"sh","ix":3,"ks":{"a":0,"k":{"i":[[0,0],[0.208,0],[0.322,0.322],[0,0.575],[0,0],[0,0],[0,0],[0,0],[-0.139,0.133],[0,0.253],[0,0],[0,0],[0,0],[0,0],[0,0],[0,0],[0,0],[-0.139,-0.139],[-0.303,0],[-0.12,0.019]],"o":[[-0.202,0.032],[-0.581,0],[-0.316,-0.322],[0,0],[0,0],[0,0],[0,0],[0.253,0],[0.139,-0.133],[0,0],[0,0],[0,0],[0,0],[0,0],[0,0],[0,0],[0,0.259],[0.139,0.139],[0.101,0],[0,0]],"v":[[-24.803,2.647],[-25.418,2.694],[-26.772,2.211],[-27.246,0.867],[-27.246,-1.406],[-28.136,-1.406],[-28.136,-2.514],[-28.041,-2.514],[-27.454,-2.713],[-27.246,-3.291],[-27.246,-3.689],[-26.005,-3.689],[-26.005,-2.514],[-24.822,-2.514],[-24.822,-1.406],[-26.005,-1.406],[-26.005,0.8],[-25.797,1.397],[-25.134,1.605],[-24.803,1.577]],"c":true},"ix":2},"nm":"Path 3","mn":"ADBE Vector Shape - Group","hd":false},{"ind":3,"ty":"sh","ix":4,"ks":{"a":0,"k":{"i":[[0.398,-0.24],[0.524,0],[0.398,0.24],[0.221,0.41],[0,0.499],[-0.221,0.398],[-0.385,0.234],[-0.48,0],[-0.373,-0.234],[-0.196,-0.379],[0,-0.461],[0.013,-0.095],[0.025,-0.069],[0,0],[-0.253,-0.227],[-0.373,0],[-0.196,0.12],[-0.114,0.196],[0,0]],"o":[[-0.391,0.234],[-0.53,0],[-0.398,-0.24],[-0.221,-0.41],[0,-0.518],[0.227,-0.404],[0.391,-0.234],[0.537,0],[0.373,0.227],[0.196,0.379],[0,0.095],[-0.006,0.088],[0,0],[0.038,0.379],[0.253,0.227],[0.284,0],[0.202,-0.126],[0,0],[-0.158,0.366]],"v":[[-20.084,2.401],[-21.458,2.751],[-22.85,2.391],[-23.778,1.416],[-24.109,0.052],[-23.778,-1.321],[-22.859,-2.278],[-21.552,-2.628],[-20.189,-2.278],[-19.336,-1.368],[-19.043,-0.109],[-19.062,0.175],[-19.109,0.412],[-22.821,0.412],[-22.386,1.321],[-21.448,1.662],[-20.728,1.482],[-20.255,0.999],[-19.251,1.492]],"c":true},"ix":2},"nm":"Path 4","mn":"ADBE Vector Shape - Group","hd":false},{"ind":4,"ty":"sh","ix":5,"ks":{"a":0,"k":{"i":[[0.221,0.196],[0.328,0],[0.227,-0.189],[0.069,-0.341],[0,0]],"o":[[-0.215,-0.202],[-0.309,0],[-0.221,0.183],[0,0],[-0.025,-0.316]],"v":[[-20.738,-1.302],[-21.552,-1.605],[-22.357,-1.321],[-22.793,-0.535],[-20.368,-0.535]],"c":true},"ix":2},"nm":"Path 5","mn":"ADBE Vector Shape - Group","hd":false},{"ind":5,"ty":"sh","ix":6,"ks":{"a":0,"k":{"i":[[0,0],[0,0],[0,0],[0,0],[0,0],[-0.24,0.114],[-0.316,0],[0,0],[0,0],[0,0],[0.221,-0.221],[0,-0.391]],"o":[[0,0],[0,0],[0,0],[0,0],[0.133,-0.297],[0.24,-0.114],[0,0],[0,0],[0,0],[-0.347,0],[-0.215,0.215],[0,0]],"v":[[-16.861,2.638],[-18.102,2.638],[-18.102,-2.514],[-16.937,-2.514],[-16.937,-1.785],[-16.378,-2.401],[-15.545,-2.571],[-15.242,-2.571],[-15.242,-1.473],[-15.687,-1.473],[-16.539,-1.141],[-16.861,-0.232]],"c":true},"ix":2},"nm":"Path 6","mn":"ADBE Vector Shape - Group","hd":false},{"ind":6,"ty":"sh","ix":7,"ks":{"a":0,"k":{"i":[[0,0],[0,0],[0,0],[0,0],[-0.366,-0.177],[-0.208,-0.328],[0,-0.48],[0.215,-0.335],[0.366,-0.177],[0.48,0],[0,0]],"o":[[0,0],[0,0],[0,0],[0.48,0],[0.373,0.17],[0.208,0.328],[0,0.467],[-0.208,0.335],[-0.366,0.17],[0,0],[0,0]],"v":[[-11.484,2.638],[-12.772,2.638],[-12.772,-4.418],[-10.14,-4.418],[-8.871,-4.153],[-7.999,-3.405],[-7.687,-2.192],[-8.009,-0.99],[-8.871,-0.223],[-10.14,0.033],[-11.484,0.033]],"c":true},"ix":2},"nm":"Path 7","mn":"ADBE Vector Shape - Group","hd":false},{"ind":7,"ty":"sh","ix":8,"ks":{"a":0,"k":{"i":[[0,0],[0,0],[0,0],[-0.208,0.196],[0,0.328],[0.208,0.196],[0.347,0]],"o":[[0,0],[0,0],[0.347,0],[0.208,-0.202],[0,-0.335],[-0.208,-0.196],[0,0]],"v":[[-11.484,-3.282],[-11.484,-1.103],[-10.121,-1.103],[-9.287,-1.397],[-8.975,-2.192],[-9.287,-2.988],[-10.121,-3.282]],"c":true},"ix":2},"nm":"Path 8","mn":"ADBE Vector Shape - Group","hd":false},{"ind":8,"ty":"sh","ix":9,"ks":{"a":0,"k":{"i":[[0,0],[0.669,0],[0.322,0.265],[0,0.455],[-0.29,0.284],[-0.606,0.101],[0,0],[0,0],[0.177,0.145],[0.284,0],[0.202,-0.145],[0.095,-0.234],[0,0],[-0.404,0.246],[-0.518,0],[-0.316,-0.158],[-0.183,-0.278],[0,-0.36],[0,0],[0,0]],"o":[[-0.404,0.442],[-0.537,0],[-0.322,-0.265],[0,-0.429],[0.29,-0.284],[0,0],[0,0],[0,-0.221],[-0.17,-0.152],[-0.271,0],[-0.202,0.139],[0,0],[0.152,-0.404],[0.404,-0.246],[0.423,0],[0.322,0.152],[0.183,0.278],[0,0],[0,0],[0,0]],"v":[[-3.877,2.088],[-5.487,2.751],[-6.775,2.353],[-7.258,1.274],[-6.823,0.204],[-5.478,-0.374],[-3.944,-0.62],[-3.944,-0.791],[-4.209,-1.34],[-4.891,-1.567],[-5.601,-1.35],[-6.046,-0.791],[-7.06,-1.283],[-6.226,-2.259],[-4.843,-2.628],[-3.735,-2.391],[-2.978,-1.747],[-2.703,-0.791],[-2.703,2.638],[-3.877,2.638]],"c":true},"ix":2},"nm":"Path 9","mn":"ADBE Vector Shape - Group","hd":false},{"ind":9,"ty":"sh","ix":10,"ks":{"a":0,"k":{"i":[[0,0],[0,-0.36],[-0.133,-0.107],[-0.208,0],[-0.24,0.246],[0,0.354],[0,0]],"o":[[-0.486,0.095],[0,0.177],[0.133,0.101],[0.391,0],[0.246,-0.246],[0,0],[0,0]],"v":[[-5.241,0.545],[-5.97,1.226],[-5.772,1.653],[-5.26,1.804],[-4.313,1.435],[-3.944,0.535],[-3.944,0.327]],"c":true},"ix":2},"nm":"Path 10","mn":"ADBE Vector Shape - Group","hd":false},{"ind":10,"ty":"sh","ix":11,"ks":{"a":0,"k":{"i":[[0.29,-0.133],[0.391,0],[0.41,0.265],[0.152,0.442],[0,0],[-0.234,-0.164],[-0.29,0],[-0.133,0.095],[0,0.17],[0.12,0.082],[0.164,0.044],[0,0],[0.227,0.259],[0,0.354],[-0.158,0.234],[-0.284,0.133],[-0.373,0],[-0.373,-0.24],[-0.158,-0.417],[0,0],[0.215,0.139],[0.259,0],[0.12,-0.095],[0,-0.152],[-0.114,-0.082],[-0.177,-0.051],[0,0],[-0.227,-0.259],[0,-0.36],[0.164,-0.24]],"o":[[-0.29,0.133],[-0.549,0],[-0.404,-0.265],[0,0],[0.139,0.29],[0.234,0.164],[0.221,0],[0.139,-0.101],[0,-0.145],[-0.114,-0.088],[0,0],[-0.436,-0.126],[-0.221,-0.259],[0,-0.316],[0.164,-0.24],[0.29,-0.133],[0.486,0],[0.373,0.234],[0,0],[-0.082,-0.234],[-0.208,-0.139],[-0.208,0],[-0.12,0.095],[0,0.145],[0.114,0.082],[0,0],[0.429,0.12],[0.227,0.259],[0,0.309],[-0.164,0.234]],"v":[[1.427,2.552],[0.404,2.751],[-1.036,2.353],[-1.869,1.293],[-0.941,0.848],[-0.382,1.529],[0.404,1.776],[0.934,1.634],[1.143,1.226],[0.963,0.885],[0.546,0.687],[-0.297,0.45],[-1.291,-0.128],[-1.623,-1.046],[-1.386,-1.87],[-0.714,-2.429],[0.281,-2.628],[1.569,-2.268],[2.364,-1.293],[1.417,-0.848],[0.972,-1.406],[0.271,-1.615],[-0.221,-1.473],[-0.401,-1.103],[-0.231,-0.762],[0.205,-0.563],[1.029,-0.317],[2.014,0.251],[2.355,1.179],[2.109,2.003]],"c":true},"ix":2},"nm":"Path 11","mn":"ADBE Vector Shape - Group","hd":false},{"ind":11,"ty":"sh","ix":12,"ks":{"a":0,"k":{"i":[[0.29,-0.133],[0.391,0],[0.41,0.265],[0.152,0.442],[0,0],[-0.234,-0.164],[-0.29,0],[-0.133,0.095],[0,0.17],[0.12,0.082],[0.164,0.044],[0,0],[0.227,0.259],[0,0.354],[-0.158,0.234],[-0.284,0.133],[-0.373,0],[-0.373,-0.24],[-0.158,-0.417],[0,0],[0.215,0.139],[0.259,0],[0.12,-0.095],[0,-0.152],[-0.114,-0.082],[-0.177,-0.051],[0,0],[-0.227,-0.259],[0,-0.36],[0.164,-0.24]],"o":[[-0.29,0.133],[-0.549,0],[-0.404,-0.265],[0,0],[0.139,0.29],[0.234,0.164],[0.221,0],[0.139,-0.101],[0,-0.145],[-0.114,-0.088],[0,0],[-0.436,-0.126],[-0.221,-0.259],[0,-0.316],[0.164,-0.24],[0.29,-0.133],[0.486,0],[0.373,0.234],[0,0],[-0.082,-0.234],[-0.208,-0.139],[-0.208,0],[-0.12,0.095],[0,0.145],[0.114,0.082],[0,0],[0.429,0.12],[0.227,0.259],[0,0.309],[-0.164,0.234]],"v":[[6.292,2.552],[5.269,2.751],[3.829,2.353],[2.996,1.293],[3.924,0.848],[4.483,1.529],[5.269,1.776],[5.799,1.634],[6.007,1.226],[5.827,0.885],[5.411,0.687],[4.568,0.45],[3.574,-0.128],[3.242,-1.046],[3.479,-1.87],[4.151,-2.429],[5.146,-2.628],[6.434,-2.268],[7.229,-1.293],[6.282,-0.848],[5.837,-1.406],[5.136,-1.615],[4.644,-1.473],[4.464,-1.103],[4.634,-0.762],[5.07,-0.563],[5.894,-0.317],[6.879,0.251],[7.22,1.179],[6.973,2.003]],"c":true},"ix":2},"nm":"Path 12","mn":"ADBE Vector Shape - Group","hd":false},{"ind":12,"ty":"sh","ix":13,"ks":{"a":0,"k":{"i":[[0,0],[0,0],[0,0],[0,0],[0,0],[-0.284,0.126],[-0.354,0],[-0.391,-0.24],[-0.227,-0.41],[0,-0.505],[0.227,-0.41],[0.391,-0.24],[0.499,0],[0.271,0.101],[0.189,0.196]],"o":[[0,0],[0,0],[0,0],[0,0],[0.183,-0.227],[0.284,-0.126],[0.492,0],[0.391,0.234],[0.227,0.404],[0,0.505],[-0.227,0.404],[-0.391,0.234],[-0.316,0],[-0.271,-0.107],[0,0]],"v":[[9.414,4.532],[8.173,4.532],[8.173,-2.514],[9.338,-2.514],[9.338,-1.908],[10.039,-2.439],[10.995,-2.628],[12.321,-2.268],[13.249,-1.302],[13.59,0.062],[13.249,1.435],[12.321,2.401],[10.986,2.751],[10.105,2.6],[9.414,2.145]],"c":true},"ix":2},"nm":"Path 13","mn":"ADBE Vector Shape - Group","hd":false},{"ind":13,"ty":"sh","ix":14,"ks":{"a":0,"k":{"i":[[-0.215,-0.133],[-0.271,0],[-0.215,0.133],[-0.126,0.234],[0,0.297],[0.126,0.234],[0.221,0.133],[0.284,0],[0.221,-0.133],[0.126,-0.234],[0,-0.303],[-0.12,-0.234]],"o":[[0.221,0.133],[0.284,0],[0.221,-0.133],[0.126,-0.24],[0,-0.297],[-0.126,-0.234],[-0.215,-0.139],[-0.271,0],[-0.215,0.133],[-0.12,0.234],[0,0.303],[0.126,0.234]],"v":[[10.105,1.416],[10.844,1.615],[11.592,1.416],[12.113,0.867],[12.302,0.062],[12.113,-0.734],[11.592,-1.283],[10.844,-1.492],[10.105,-1.293],[9.594,-0.743],[9.414,0.062],[9.594,0.867]],"c":true},"ix":2},"nm":"Path 14","mn":"ADBE Vector Shape - Group","hd":false},{"ind":14,"ty":"sh","ix":15,"ks":{"a":0,"k":{"i":[[0,0],[0,0],[0,0],[0,0],[0,0],[-0.24,0.101],[-0.297,0],[-0.29,-0.164],[-0.164,-0.297],[0,-0.385],[0,0],[0,0],[0,0],[0.196,0.196],[0.303,0],[0.196,-0.202],[0,-0.335]],"o":[[0,0],[0,0],[0,0],[0,0],[0.145,-0.208],[0.24,-0.107],[0.379,0],[0.297,0.164],[0.164,0.29],[0,0],[0,0],[0,0],[0,-0.341],[-0.196,-0.202],[-0.303,0],[-0.196,0.202],[0,0]],"v":[[15.777,2.638],[14.536,2.638],[14.536,-4.532],[15.777,-4.532],[15.777,-2.003],[16.354,-2.467],[17.159,-2.628],[18.163,-2.382],[18.855,-1.69],[19.101,-0.677],[19.101,2.638],[17.86,2.638],[17.86,-0.384],[17.567,-1.189],[16.818,-1.492],[16.07,-1.189],[15.777,-0.384]],"c":true},"ix":2},"nm":"Path 15","mn":"ADBE Vector Shape - Group","hd":false},{"ind":15,"ty":"sh","ix":16,"ks":{"a":0,"k":{"i":[[0,0],[0,0],[0,0],[0,0],[0,0],[-0.24,0.114],[-0.316,0],[0,0],[0,0],[0,0],[0.221,-0.221],[0,-0.391]],"o":[[0,0],[0,0],[0,0],[0,0],[0.133,-0.297],[0.24,-0.114],[0,0],[0,0],[0,0],[-0.347,0],[-0.215,0.215],[0,0]],"v":[[21.391,2.638],[20.15,2.638],[20.15,-2.514],[21.315,-2.514],[21.315,-1.785],[21.874,-2.401],[22.707,-2.571],[23.01,-2.571],[23.01,-1.473],[22.565,-1.473],[21.713,-1.141],[21.391,-0.232]],"c":true},"ix":2},"nm":"Path 16","mn":"ADBE Vector Shape - Group","hd":false},{"ind":16,"ty":"sh","ix":17,"ks":{"a":0,"k":{"i":[[0,0],[0.669,0],[0.322,0.265],[0,0.455],[-0.29,0.284],[-0.606,0.101],[0,0],[0,0],[0.177,0.145],[0.284,0],[0.202,-0.145],[0.095,-0.234],[0,0],[-0.404,0.246],[-0.518,0],[-0.316,-0.158],[-0.183,-0.278],[0,-0.36],[0,0],[0,0]],"o":[[-0.404,0.442],[-0.537,0],[-0.322,-0.265],[0,-0.429],[0.29,-0.284],[0,0],[0,0],[0,-0.221],[-0.17,-0.152],[-0.271,0],[-0.202,0.139],[0,0],[0.152,-0.404],[0.404,-0.246],[0.423,0],[0.322,0.152],[0.183,0.278],[0,0],[0,0],[0,0]],"v":[[26.865,2.088],[25.255,2.751],[23.967,2.353],[23.484,1.274],[23.919,0.204],[25.264,-0.374],[26.798,-0.62],[26.798,-0.791],[26.533,-1.34],[25.851,-1.567],[25.141,-1.35],[24.696,-0.791],[23.683,-1.283],[24.516,-2.259],[25.899,-2.628],[27.007,-2.391],[27.764,-1.747],[28.039,-0.791],[28.039,2.638],[26.865,2.638]],"c":true},"ix":2},"nm":"Path 17","mn":"ADBE Vector Shape - Group","hd":false},{"ind":17,"ty":"sh","ix":18,"ks":{"a":0,"k":{"i":[[0,0],[0,-0.36],[-0.133,-0.107],[-0.208,0],[-0.24,0.246],[0,0.354],[0,0]],"o":[[-0.486,0.095],[0,0.177],[0.133,0.101],[0.391,0],[0.246,-0.246],[0,0],[0,0]],"v":[[25.501,0.545],[24.772,1.226],[24.971,1.653],[25.482,1.804],[26.429,1.435],[26.798,0.535],[26.798,0.327]],"c":true},"ix":2},"nm":"Path 18","mn":"ADBE Vector Shape - Group","hd":false},{"ind":18,"ty":"sh","ix":19,"ks":{"a":0,"k":{"i":[[0.29,-0.133],[0.391,0],[0.41,0.265],[0.152,0.442],[0,0],[-0.234,-0.164],[-0.29,0],[-0.133,0.095],[0,0.17],[0.12,0.082],[0.164,0.044],[0,0],[0.227,0.259],[0,0.354],[-0.158,0.234],[-0.284,0.133],[-0.373,0],[-0.373,-0.24],[-0.158,-0.417],[0,0],[0.215,0.139],[0.259,0],[0.12,-0.095],[0,-0.152],[-0.114,-0.082],[-0.177,-0.051],[0,0],[-0.227,-0.259],[0,-0.36],[0.164,-0.24]],"o":[[-0.29,0.133],[-0.549,0],[-0.404,-0.265],[0,0],[0.139,0.29],[0.234,0.164],[0.221,0],[0.139,-0.101],[0,-0.145],[-0.114,-0.088],[0,0],[-0.436,-0.126],[-0.221,-0.259],[0,-0.316],[0.164,-0.24],[0.29,-0.133],[0.486,0],[0.373,0.234],[0,0],[-0.082,-0.234],[-0.208,-0.139],[-0.208,0],[-0.12,0.095],[0,0.145],[0.114,0.082],[0,0],[0.429,0.12],[0.227,0.259],[0,0.309],[-0.164,0.234]],"v":[[32.169,2.552],[31.146,2.751],[29.707,2.353],[28.873,1.293],[29.801,0.848],[30.36,1.529],[31.146,1.776],[31.677,1.634],[31.885,1.226],[31.705,0.885],[31.288,0.687],[30.445,0.45],[29.451,-0.128],[29.12,-1.046],[29.356,-1.87],[30.029,-2.429],[31.023,-2.628],[32.311,-2.268],[33.107,-1.293],[32.16,-0.848],[31.714,-1.406],[31.014,-1.615],[30.521,-1.473],[30.341,-1.103],[30.512,-0.762],[30.947,-0.563],[31.771,-0.317],[32.756,0.251],[33.097,1.179],[32.851,2.003]],"c":true},"ix":2},"nm":"Path 19","mn":"ADBE Vector Shape - Group","hd":false},{"ind":19,"ty":"sh","ix":20,"ks":{"a":0,"k":{"i":[[0.398,-0.24],[0.524,0],[0.398,0.24],[0.221,0.41],[0,0.499],[-0.221,0.398],[-0.385,0.234],[-0.48,0],[-0.373,-0.234],[-0.196,-0.379],[0,-0.461],[0.013,-0.095],[0.025,-0.069],[0,0],[-0.253,-0.227],[-0.373,0],[-0.196,0.12],[-0.114,0.196],[0,0]],"o":[[-0.391,0.234],[-0.53,0],[-0.398,-0.24],[-0.221,-0.41],[0,-0.518],[0.227,-0.404],[0.391,-0.234],[0.537,0],[0.373,0.227],[0.196,0.379],[0,0.095],[-0.006,0.088],[0,0],[0.038,0.379],[0.253,0.227],[0.284,0],[0.202,-0.126],[0,0],[-0.158,0.366]],"v":[[37.867,2.401],[36.494,2.751],[35.102,2.391],[34.174,1.416],[33.842,0.052],[34.174,-1.321],[35.092,-2.278],[36.399,-2.628],[37.763,-2.278],[38.615,-1.368],[38.909,-0.109],[38.89,0.175],[38.843,0.412],[35.13,0.412],[35.566,1.321],[36.503,1.662],[37.223,1.482],[37.697,0.999],[38.701,1.492]],"c":true},"ix":2},"nm":"Path 20","mn":"ADBE Vector Shape - Group","hd":false},{"ind":20,"ty":"sh","ix":21,"ks":{"a":0,"k":{"i":[[0.221,0.196],[0.328,0],[0.227,-0.189],[0.069,-0.341],[0,0]],"o":[[-0.215,-0.202],[-0.309,0],[-0.221,0.183],[0,0],[-0.025,-0.316]],"v":[[37.214,-1.302],[36.399,-1.605],[35.594,-1.321],[35.159,-0.535],[37.583,-0.535]],"c":true},"ix":2},"nm":"Path 21","mn":"ADBE Vector Shape - Group","hd":false},{"ty":"mm","mm":1,"nm":"Merge Paths 1","mn":"ADBE Vector Filter - Merge","hd":false},{"ty":"fl","c":{"a":0,"k":[1,1,1,1],"ix":4},"o":{"a":0,"k":100,"ix":5},"r":1,"bm":0,"nm":"Fill 1","mn":"ADBE Vector Graphic - Fill","hd":false},{"ty":"tr","p":{"a":0,"k":[0,0],"ix":2},"a":{"a":0,"k":[0,0],"ix":1},"s":{"a":0,"k":[100,100],"ix":3},"r":{"a":0,"k":0,"ix":6},"o":{"a":0,"k":100,"ix":7},"sk":{"a":0,"k":0,"ix":4},"sa":{"a":0,"k":0,"ix":5},"nm":"Transform"}],"nm":"Enter Passphrase","np":23,"cix":2,"bm":0,"ix":1,"mn":"ADBE Vector Group","hd":false}],"ip":0,"op":300,"st":0,"bm":0},{"ddd":0,"ind":7,"ty":4,"nm":"Refrection","sr":1,"ks":{"o":{"a":0,"k":2,"ix":11},"r":{"a":0,"k":0,"ix":10},"p":{"a":0,"k":[50.33,103.241,0],"ix":2},"a":{"a":0,"k":[0,0,0],"ix":1},"s":{"a":0,"k":[100,100,100],"ix":6}},"ao":0,"shapes":[{"ty":"gr","it":[{"ind":0,"ty":"sh","ix":1,"ks":{"a":0,"k":{"i":[[0,0],[0,-2.851],[0,0],[-3.286,0],[0,0],[0,0]],"o":[[-2.851,0],[0,0],[0,3.286],[0,0],[0,0],[0,0]],"v":[[-32.263,-90.336],[-37.425,-85.173],[-37.425,84.385],[-31.474,90.336],[-0.322,90.336],[37.425,-90.336]],"c":true},"ix":2},"nm":"Path 1","mn":"ADBE Vector Shape - Group","hd":false},{"ty":"fl","c":{"a":0,"k":[1,1,1,1],"ix":4},"o":{"a":0,"k":100,"ix":5},"r":1,"bm":0,"nm":"Fill 1","mn":"ADBE Vector Graphic - Fill","hd":false},{"ty":"tr","p":{"a":0,"k":[0,0],"ix":2},"a":{"a":0,"k":[0,0],"ix":1},"s":{"a":0,"k":[100,100],"ix":3},"r":{"a":0,"k":0,"ix":6},"o":{"a":0,"k":100,"ix":7},"sk":{"a":0,"k":0,"ix":4},"sa":{"a":0,"k":0,"ix":5},"nm":"Transform"}],"nm":"Refrection","np":2,"cix":2,"bm":0,"ix":1,"mn":"ADBE Vector Group","hd":false}],"ip":0,"op":300,"st":0,"bm":0},{"ddd":0,"ind":8,"ty":4,"nm":"Screen","sr":1,"ks":{"o":{"a":0,"k":100,"ix":11},"r":{"a":0,"k":0,"ix":10},"p":{"a":0,"k":[68.397,103.241,0],"ix":2},"a":{"a":0,"k":[0,0,0],"ix":1},"s":{"a":0,"k":[100,100,100],"ix":6}},"ao":0,"shapes":[{"ty":"gr","it":[{"ind":0,"ty":"sh","ix":1,"ks":{"a":0,"k":{"i":[[0,0],[0,0],[0,0],[0,0]],"o":[[0,0],[0,0],[0,0],[0,0]],"v":[[55.492,-90.336],[-55.492,-90.336],[-55.492,90.336],[55.492,90.336]],"c":true},"ix":2},"nm":"Path 1","mn":"ADBE Vector Shape - Group","hd":false},{"ty":"rd","nm":"Round Corners 1","r":{"a":0,"k":5,"ix":1},"ix":2,"mn":"ADBE Vector Filter - RC","hd":false},{"ty":"fl","c":{"a":0,"k":[0.329299986362,0.329299986362,0.410700023174,1],"ix":4},"o":{"a":0,"k":100,"ix":5},"r":1,"bm":0,"nm":"Fill 1","mn":"ADBE Vector Graphic - Fill","hd":false},{"ty":"tr","p":{"a":0,"k":[0,0],"ix":2},"a":{"a":0,"k":[0,0],"ix":1},"s":{"a":0,"k":[100,100],"ix":3},"r":{"a":0,"k":0,"ix":6},"o":{"a":0,"k":100,"ix":7},"sk":{"a":0,"k":0,"ix":4},"sa":{"a":0,"k":0,"ix":5},"nm":"Transform"}],"nm":"Screen","np":3,"cix":2,"bm":0,"ix":1,"mn":"ADBE Vector Group","hd":false}],"ip":0,"op":300,"st":0,"bm":0},{"ddd":0,"ind":9,"ty":3,"nm":"▽ Body","sr":1,"ks":{"o":{"a":0,"k":100,"ix":11},"r":{"a":0,"k":0,"ix":10},"p":{"a":0,"k":[68.397,114.855,0],"ix":2},"a":{"a":0,"k":[68.397,114.855,0],"ix":1},"s":{"a":0,"k":[100,100,100],"ix":6}},"ao":0,"ip":0,"op":300,"st":0,"bm":0},{"ddd":0,"ind":10,"ty":4,"nm":"Top highlight","parent":9,"sr":1,"ks":{"o":{"a":0,"k":20,"ix":11},"r":{"a":0,"k":0,"ix":10},"p":{"a":0,"k":[68.397,9.034,0],"ix":2},"a":{"a":0,"k":[0,0,0],"ix":1},"s":{"a":0,"k":[100,100,100],"ix":6}},"ao":0,"shapes":[{"ty":"gr","it":[{"ind":0,"ty":"sh","ix":1,"ks":{"a":0,"k":{"i":[[0,0],[-8.553,0],[0,0],[0,-8.553],[0,0],[8.553,0],[0,0],[0,-8.553]],"o":[[0,-8.553],[0,0],[8.553,0],[0,0],[0,-8.553],[0,0],[-8.553,0],[0,0]],"v":[[-68.397,6.453],[-52.911,-9.034],[52.911,-9.034],[68.397,6.453],[68.397,9.034],[52.911,-6.453],[-52.911,-6.453],[-68.397,9.034]],"c":true},"ix":2},"nm":"Path 1","mn":"ADBE Vector Shape - Group","hd":false},{"ty":"fl","c":{"a":0,"k":[1,1,1,1],"ix":4},"o":{"a":0,"k":100,"ix":5},"r":1,"bm":0,"nm":"Fill 1","mn":"ADBE Vector Graphic - Fill","hd":false},{"ty":"tr","p":{"a":0,"k":[0,0],"ix":2},"a":{"a":0,"k":[0,0],"ix":1},"s":{"a":0,"k":[100,100],"ix":3},"r":{"a":0,"k":0,"ix":6},"o":{"a":0,"k":100,"ix":7},"sk":{"a":0,"k":0,"ix":4},"sa":{"a":0,"k":0,"ix":5},"nm":"Transform"}],"nm":"Top highlight","np":2,"cix":2,"bm":0,"ix":1,"mn":"ADBE Vector Group","hd":false}],"ip":0,"op":300,"st":0,"bm":0},{"ddd":0,"ind":11,"ty":4,"nm":"Shadow","parent":9,"sr":1,"ks":{"o":{"a":0,"k":20,"ix":11},"r":{"a":0,"k":0,"ix":10},"p":{"a":0,"k":[68.397,220.677,0],"ix":2},"a":{"a":0,"k":[0,0,0],"ix":1},"s":{"a":0,"k":[100,100,100],"ix":6}},"ao":0,"shapes":[{"ty":"gr","it":[{"ind":0,"ty":"sh","ix":1,"ks":{"a":0,"k":{"i":[[0,8.553],[0,0],[-8.553,0],[0,0],[0,8.553],[0,0],[8.553,0],[0,0]],"o":[[0,0],[0,8.553],[0,0],[8.553,0],[0,0],[0,8.553],[0,0],[-8.553,0]],"v":[[-68.397,-6.453],[-68.397,-9.034],[-52.911,6.453],[52.911,6.453],[68.397,-9.034],[68.397,-6.453],[52.911,9.034],[-52.911,9.034]],"c":true},"ix":2},"nm":"Path 1","mn":"ADBE Vector Shape - Group","hd":false},{"ty":"fl","c":{"a":0,"k":[0,0,0,1],"ix":4},"o":{"a":0,"k":100,"ix":5},"r":1,"bm":0,"nm":"Fill 1","mn":"ADBE Vector Graphic - Fill","hd":false},{"ty":"tr","p":{"a":0,"k":[0,0],"ix":2},"a":{"a":0,"k":[0,0],"ix":1},"s":{"a":0,"k":[100,100],"ix":3},"r":{"a":0,"k":0,"ix":6},"o":{"a":0,"k":100,"ix":7},"sk":{"a":0,"k":0,"ix":4},"sa":{"a":0,"k":0,"ix":5},"nm":"Transform"}],"nm":"Shadow","np":2,"cix":2,"bm":0,"ix":1,"mn":"ADBE Vector Group","hd":false}],"ip":0,"op":300,"st":0,"bm":0},{"ddd":0,"ind":12,"ty":4,"nm":"H highlight","parent":9,"sr":1,"ks":{"o":{"a":0,"k":10,"ix":11},"r":{"a":0,"k":0,"ix":10},"p":{"a":0,"k":[68.397,114.855,0],"ix":2},"a":{"a":0,"k":[0,0,0],"ix":1},"s":{"a":0,"k":[100,100,100],"ix":6}},"ao":0,"shapes":[{"ty":"gr","it":[{"ind":0,"ty":"sh","ix":1,"ks":{"a":0,"k":{"i":[[8.553,0],[0,0],[0,8.553],[0,0],[8.553,0],[0,0],[0,-8.553],[0,0]],"o":[[0,0],[8.553,0],[0,0],[0,-8.553],[0,0],[8.553,0],[0,0],[0,8.553]],"v":[[52.911,114.855],[50.33,114.855],[65.816,99.369],[65.816,-99.369],[50.33,-114.855],[52.911,-114.855],[68.397,-99.369],[68.397,99.369]],"c":true},"ix":2},"nm":"Path 1","mn":"ADBE Vector Shape - Group","hd":false},{"ind":1,"ty":"sh","ix":2,"ks":{"a":0,"k":{"i":[[0,0],[-8.553,0],[0,0],[0,-8.553],[0,0],[-8.553,0],[0,0],[0,8.553]],"o":[[0,-8.553],[0,0],[-8.553,0],[0,0],[0,8.553],[0,0],[-8.553,0],[0,0]],"v":[[-68.397,-99.369],[-52.911,-114.855],[-50.33,-114.855],[-65.816,-99.369],[-65.816,99.369],[-50.33,114.855],[-52.911,114.855],[-68.397,99.369]],"c":true},"ix":2},"nm":"Path 2","mn":"ADBE Vector Shape - Group","hd":false},{"ty":"mm","mm":1,"nm":"Merge Paths 1","mn":"ADBE Vector Filter - Merge","hd":false},{"ty":"fl","c":{"a":0,"k":[1,1,1,1],"ix":4},"o":{"a":0,"k":100,"ix":5},"r":1,"bm":0,"nm":"Fill 1","mn":"ADBE Vector Graphic - Fill","hd":false},{"ty":"tr","p":{"a":0,"k":[0,0],"ix":2},"a":{"a":0,"k":[0,0],"ix":1},"s":{"a":0,"k":[100,100],"ix":3},"r":{"a":0,"k":0,"ix":6},"o":{"a":0,"k":100,"ix":7},"sk":{"a":0,"k":0,"ix":4},"sa":{"a":0,"k":0,"ix":5},"nm":"Transform"}],"nm":"H highlight","np":4,"cix":2,"bm":0,"ix":1,"mn":"ADBE Vector Group","hd":false}],"ip":0,"op":300,"st":0,"bm":0},{"ddd":0,"ind":13,"ty":4,"nm":"Background","parent":9,"sr":1,"ks":{"o":{"a":0,"k":100,"ix":11},"r":{"a":0,"k":0,"ix":10},"p":{"a":0,"k":[68.397,114.855,0],"ix":2},"a":{"a":0,"k":[0,0,0],"ix":1},"s":{"a":0,"k":[100,100,100],"ix":6}},"ao":0,"shapes":[{"ty":"gr","it":[{"ty":"rc","d":1,"s":{"a":0,"k":[136.794,229.71],"ix":2},"p":{"a":0,"k":[0,0],"ix":3},"r":{"a":0,"k":15,"ix":4},"nm":"Rectangle Path 1","mn":"ADBE Vector Shape - Rect","hd":false},{"ty":"fl","c":{"a":0,"k":[0.45360827446,0.45360827446,0.54639172554,1],"ix":4},"o":{"a":0,"k":100,"ix":5},"r":1,"bm":0,"nm":"Fill 1","mn":"ADBE Vector Graphic - Fill","hd":false},{"ty":"tr","p":{"a":0,"k":[0,0],"ix":2},"a":{"a":0,"k":[0,0],"ix":1},"s":{"a":0,"k":[100,100],"ix":3},"r":{"a":0,"k":0,"ix":6},"o":{"a":0,"k":100,"ix":7},"sk":{"a":0,"k":0,"ix":4},"sa":{"a":0,"k":0,"ix":5},"nm":"Transform"}],"nm":"Background","np":2,"cix":2,"bm":0,"ix":1,"mn":"ADBE Vector Group","hd":false}],"ip":0,"op":300,"st":0,"bm":0},{"ddd":0,"ind":14,"ty":3,"nm":"▽ Power Button","sr":1,"ks":{"o":{"a":0,"k":100,"ix":11},"r":{"a":0,"k":0,"ix":10},"p":{"a":0,"k":[133.567,56.782,0],"ix":2},"a":{"a":0,"k":[4.517,10.324,0],"ix":1},"s":{"a":0,"k":[100,100,100],"ix":6}},"ao":0,"ip":0,"op":300,"st":0,"bm":0},{"ddd":0,"ind":15,"ty":4,"nm":"Highlight","parent":14,"sr":1,"ks":{"o":{"a":0,"k":20,"ix":11},"r":{"a":0,"k":0,"ix":10},"p":{"a":0,"k":[8.388,10.324,0],"ix":2},"a":{"a":0,"k":[0,0,0],"ix":1},"s":{"a":0,"k":[100,100,100],"ix":6}},"ao":0,"shapes":[{"ty":"gr","it":[{"ind":0,"ty":"sh","ix":1,"ks":{"a":0,"k":{"i":[[0,0],[0,-0.713],[0,0],[0.713,0]],"o":[[0.713,0],[0,0],[0,0.713],[0,0]],"v":[[-0.645,-10.324],[0.645,-9.034],[0.645,9.034],[-0.645,10.324]],"c":true},"ix":2},"nm":"Path 1","mn":"ADBE Vector Shape - Group","hd":false},{"ty":"fl","c":{"a":0,"k":[1,1,1,1],"ix":4},"o":{"a":0,"k":100,"ix":5},"r":1,"bm":0,"nm":"Fill 1","mn":"ADBE Vector Graphic - Fill","hd":false},{"ty":"tr","p":{"a":0,"k":[0,0],"ix":2},"a":{"a":0,"k":[0,0],"ix":1},"s":{"a":0,"k":[100,100],"ix":3},"r":{"a":0,"k":0,"ix":6},"o":{"a":0,"k":100,"ix":7},"sk":{"a":0,"k":0,"ix":4},"sa":{"a":0,"k":0,"ix":5},"nm":"Transform"}],"nm":"Highlight","np":2,"cix":2,"bm":0,"ix":1,"mn":"ADBE Vector Group","hd":false}],"ip":0,"op":300,"st":0,"bm":0},{"ddd":0,"ind":16,"ty":4,"nm":"Background","parent":14,"sr":1,"ks":{"o":{"a":0,"k":100,"ix":11},"r":{"a":0,"k":0,"ix":10},"p":{"a":0,"k":[4.517,10.324,0],"ix":2},"a":{"a":0,"k":[0,0,0],"ix":1},"s":{"a":0,"k":[100,100,100],"ix":6}},"ao":0,"shapes":[{"ty":"gr","it":[{"ind":0,"ty":"sh","ix":1,"ks":{"a":0,"k":{"i":[[0,0],[0,0],[0,0],[0,0]],"o":[[0,0],[0,0],[0,0],[0,0]],"v":[[4.517,-10.324],[-4.517,-10.324],[-4.517,10.324],[4.517,10.324]],"c":true},"ix":2},"nm":"Path 1","mn":"ADBE Vector Shape - Group","hd":false},{"ty":"fl","c":{"a":0,"k":[0.45360827446,0.45360827446,0.54639172554,1],"ix":4},"o":{"a":0,"k":100,"ix":5},"r":1,"bm":0,"nm":"Fill 1","mn":"ADBE Vector Graphic - Fill","hd":false},{"ty":"tr","p":{"a":0,"k":[0,0],"ix":2},"a":{"a":0,"k":[0,0],"ix":1},"s":{"a":0,"k":[100,100],"ix":3},"r":{"a":0,"k":0,"ix":6},"o":{"a":0,"k":100,"ix":7},"sk":{"a":0,"k":0,"ix":4},"sa":{"a":0,"k":0,"ix":5},"nm":"Transform"}],"nm":"Background","np":2,"cix":2,"bm":0,"ix":1,"mn":"ADBE Vector Group","hd":false}],"ip":0,"op":300,"st":0,"bm":0},{"ddd":0,"ind":17,"ty":4,"nm":"_Assets / Touch / Default","sr":1,"ks":{"o":{"a":0,"k":100,"ix":11},"r":{"a":0,"k":0,"ix":10},"p":{"a":0,"k":[69.042,114.855,0],"ix":2},"a":{"a":0,"k":[0,0,0],"ix":1},"s":{"a":0,"k":[100,100,100],"ix":6}},"ao":0,"shapes":[{"ty":"gr","it":[{"ty":"rc","d":1,"s":{"a":0,"k":[138.084,229.71],"ix":2},"p":{"a":0,"k":[0,0],"ix":3},"r":{"a":0,"k":0,"ix":4},"nm":"Rectangle Path 1","mn":"ADBE Vector Shape - Rect","hd":false},{"ty":"tr","p":{"a":0,"k":[0,0],"ix":2},"a":{"a":0,"k":[0,0],"ix":1},"s":{"a":0,"k":[100,100],"ix":3},"r":{"a":0,"k":0,"ix":6},"o":{"a":0,"k":100,"ix":7},"sk":{"a":0,"k":0,"ix":4},"sa":{"a":0,"k":0,"ix":5},"nm":"Transform"}],"nm":"_Assets / Touch / Default","np":1,"cix":2,"bm":0,"ix":1,"mn":"ADBE Vector Group","hd":false}],"ip":0,"op":300,"st":0,"bm":0}]}],"fonts":{"list":[{"fName":"SFProDisplay-Heavy","fFamily":"SF Pro Display","fStyle":"Heavy","ascent":70.458984375}]},"layers":[{"ddd":0,"ind":1,"ty":5,"nm":"<empty text layer>","sr":1,"ks":{"o":{"a":0,"k":100,"ix":11},"r":{"a":0,"k":0,"ix":10},"p":{"a":0,"k":[176,95,0],"ix":2},"a":{"a":0,"k":[0,0,0],"ix":1},"s":{"a":0,"k":[100,100,100],"ix":6}},"ao":0,"t":{"d":{"k":[{"s":{"s":19,"f":"SFProDisplay-Heavy","t":"","j":2,"tr":0,"lh":22.8,"ls":0,"fc":[1,1,1]},"t":0},{"s":{"s":19,"f":"SFProDisplay-Heavy","t":"•","j":2,"tr":0,"lh":22.8,"ls":0,"fc":[1,1,1]},"t":20},{"s":{"s":19,"f":"SFProDisplay-Heavy","t":"••","j":2,"tr":0,"lh":22.8,"ls":0,"fc":[1,1,1]},"t":50},{"s":{"s":19,"f":"SFProDisplay-Heavy","t":"•••","j":2,"tr":0,"lh":22.8,"ls":0,"fc":[1,1,1]},"t":80},{"s":{"s":19,"f":"SFProDisplay-Heavy","t":"••••","j":2,"tr":0,"lh":22.8,"ls":0,"fc":[1,1,1]},"t":110},{"s":{"s":19,"f":"SFProDisplay-Heavy","t":"","j":2,"tr":0,"lh":22.8,"ls":0,"fc":[1,1,1]},"t":140}]},"p":{},"m":{"g":1,"a":{"a":0,"k":[0,0],"ix":2}},"a":[]},"ip":0,"op":300,"st":0,"bm":0},{"ddd":0,"ind":2,"ty":0,"nm":"Click or Tap","refId":"comp_0","sr":1,"ks":{"o":{"a":0,"k":100,"ix":11},"r":{"a":0,"k":0,"ix":10},"p":{"a":0,"k":[217,200.5,0],"ix":2},"a":{"a":0,"k":[50,50,0],"ix":1},"s":{"a":0,"k":[34,34,100],"ix":6}},"ao":0,"w":100,"h":100,"ip":135,"op":205,"st":135,"bm":0},{"ddd":0,"ind":3,"ty":0,"nm":"Click or Tap","refId":"comp_0","sr":1,"ks":{"o":{"a":0,"k":100,"ix":11},"r":{"a":0,"k":0,"ix":10},"p":{"a":0,"k":[170.5,160.5,0],"ix":2},"a":{"a":0,"k":[50,50,0],"ix":1},"s":{"a":0,"k":[34,34,100],"ix":6}},"ao":0,"w":100,"h":100,"ip":105,"op":175,"st":105,"bm":0},{"ddd":0,"ind":4,"ty":0,"nm":"Click or Tap","refId":"comp_0","sr":1,"ks":{"o":{"a":0,"k":100,"ix":11},"r":{"a":0,"k":0,"ix":10},"p":{"a":0,"k":[149.5,161,0],"ix":2},"a":{"a":0,"k":[50,50,0],"ix":1},"s":{"a":0,"k":[34,34,100],"ix":6}},"ao":0,"w":100,"h":100,"ip":75,"op":145,"st":75,"bm":0},{"ddd":0,"ind":5,"ty":0,"nm":"Click or Tap","refId":"comp_0","sr":1,"ks":{"o":{"a":0,"k":100,"ix":11},"r":{"a":0,"k":0,"ix":10},"p":{"a":0,"k":[202,159.5,0],"ix":2},"a":{"a":0,"k":[50,50,0],"ix":1},"s":{"a":0,"k":[34,34,100],"ix":6}},"ao":0,"w":100,"h":100,"ip":45,"op":115,"st":45,"bm":0},{"ddd":0,"ind":6,"ty":0,"nm":"Click or Tap","refId":"comp_0","sr":1,"ks":{"o":{"a":0,"k":100,"ix":11},"r":{"a":0,"k":0,"ix":10},"p":{"a":0,"k":[175.5,174,0],"ix":2},"a":{"a":0,"k":[50,50,0],"ix":1},"s":{"a":0,"k":[34,34,100],"ix":6}},"ao":0,"w":100,"h":100,"ip":15,"op":85,"st":15,"bm":0},{"ddd":0,"ind":8,"ty":0,"nm":"_Assets / Touch / Default 6","refId":"comp_1","sr":1,"ks":{"o":{"a":1,"k":[{"i":{"x":[0.667],"y":[1]},"o":{"x":[0.333],"y":[0]},"t":0,"s":[0]},{"i":{"x":[0.667],"y":[1]},"o":{"x":[0.333],"y":[0]},"t":15,"s":[100]},{"i":{"x":[0.667],"y":[1]},"o":{"x":[0.333],"y":[0]},"t":165,"s":[100]},{"t":180,"s":[0]}],"ix":11},"r":{"a":0,"k":0,"ix":10},"p":{"a":1,"k":[{"i":{"x":0.667,"y":1},"o":{"x":0.333,"y":0},"t":0,"s":[176.042,145.855,0],"to":[0,-1.667,0],"ti":[0,1.667,0]},{"i":{"x":0.667,"y":0.667},"o":{"x":0.333,"y":0.333},"t":15,"s":[176.042,135.855,0],"to":[0,0,0],"ti":[0,0,0]},{"i":{"x":0.667,"y":1},"o":{"x":0.333,"y":0},"t":165,"s":[176.042,135.855,0],"to":[0,1.667,0],"ti":[0,-1.667,0]},{"t":180,"s":[176.042,145.855,0]}],"ix":2},"a":{"a":0,"k":[69,115,0],"ix":1},"s":{"a":1,"k":[{"i":{"x":[0.667,0.667,0.667],"y":[1,1,1]},"o":{"x":[0.333,0.333,0.333],"y":[0,0,0]},"t":0,"s":[90,90,100]},{"i":{"x":[0.667,0.667,0.667],"y":[1,1,1]},"o":{"x":[0.333,0.333,0.333],"y":[0,0,0]},"t":15,"s":[100,100,100]},{"i":{"x":[0.667,0.667,0.667],"y":[1,1,1]},"o":{"x":[0.333,0.333,0.333],"y":[0,0,0]},"t":165,"s":[100,100,100]},{"t":180,"s":[90,90,100]}],"ix":6}},"ao":0,"w":138,"h":230,"ip":0,"op":300,"st":0,"bm":0}],"markers":[],"chars":[{"ch":"•","size":19,"style":"Heavy","w":44.73,"data":{"shapes":[{"ty":"gr","it":[{"ind":0,"ty":"sh","ix":1,"ks":{"a":0,"k":{"i":[[0,0],[7.666,0],[0,0],[0,-7.666],[0,0],[-7.666,0],[0,0],[0,7.666]],"o":[[0,-7.666],[0,0],[-7.666,0],[0,0],[0,7.666],[0,0],[7.666,0],[0,0]],"v":[[36.133,-28.76],[22.461,-42.48],[22.314,-42.48],[8.643,-28.76],[8.643,-28.613],[22.314,-14.941],[22.461,-14.941],[36.133,-28.613]],"c":true},"ix":2},"nm":"•","mn":"ADBE Vector Shape - Group","hd":false}],"nm":"•","np":3,"cix":2,"bm":0,"ix":1,"mn":"ADBE Vector Group","hd":false}]},"fFamily":"SF Pro Display"}]}