{"v":"4.8.0","meta":{"g":"LottieFiles AE 1.0.0","a":"","k":"","d":"","tc":""},"fr":60,"ip":0,"op":300,"w":352,"h":160,"nm":"illus / Mini / Bootloader Mode","ddd":0,"assets":[{"id":"comp_0","layers":[{"ddd":0,"ind":1,"ty":4,"nm":"Vector","sr":1,"ks":{"o":{"a":0,"k":100,"ix":11},"r":{"a":0,"k":0,"ix":10},"p":{"a":0,"k":[12.021,12,0],"ix":2},"a":{"a":0,"k":[0,0,0],"ix":1},"s":{"a":0,"k":[100,100,100],"ix":6}},"ao":0,"shapes":[{"ty":"gr","it":[{"ind":0,"ty":"sh","ix":1,"ks":{"a":0,"k":{"i":[[-0.049,0],[0,0],[-0.188,-0.188],[0,-0.265],[0,0],[0.188,-0.188],[0.265,0],[0,0],[0.041,-0.027],[0.02,-0.045],[0,-0.046],[-0.026,-0.038],[0,0],[-0.027,-0.19],[0.08,-0.174],[0.161,-0.103],[0.191,0],[0,0],[0.129,0.057],[0.095,0.105],[0,0],[0,0.248],[-0.166,0.184],[0,0],[-0.129,0.057],[-0.141,-0.001],[0,0],[-0.154,-0.102],[-0.077,-0.168],[0.027,-0.19],[0.125,-0.145],[0,0],[0,-0.046],[-0.026,-0.038],[-0.041,-0.027]],"o":[[0,0],[0.265,0],[0.188,0.188],[0,0],[0,0.265],[-0.188,0.188],[0,0],[-0.049,0],[-0.041,0.027],[-0.026,0.038],[0,0.046],[0,0],[0.125,0.145],[0.027,0.19],[-0.08,0.174],[-0.161,0.103],[0,0],[-0.141,0.001],[-0.129,-0.057],[0,0],[-0.166,-0.184],[0,-0.248],[0,0],[0.095,-0.105],[0.129,-0.057],[0,0],[0.184,0.007],[0.154,0.102],[0.08,0.174],[-0.027,0.19],[0,0],[-0.026,0.038],[0,0.046],[0.02,0.045],[0.041,0.027]],"v":[[-0.471,-3],[10.889,-3],[11.596,-2.707],[11.889,-2],[11.889,2],[11.596,2.707],[10.889,3],[-0.381,3],[-0.519,3.041],[-0.611,3.15],[-0.651,3.28],[-0.611,3.41],[3.619,8.35],[3.851,8.863],[3.769,9.42],[3.399,9.843],[2.859,10],[-2.831,10],[-3.242,9.915],[-3.581,9.67],[-11.631,0.67],[-11.889,0],[-11.631,-0.67],[-3.631,-9.67],[-3.292,-9.915],[-2.881,-10],[2.809,-10],[3.326,-9.833],[3.679,-9.42],[3.761,-8.863],[3.529,-8.35],[-0.701,-3.41],[-0.741,-3.28],[-0.701,-3.15],[-0.609,-3.041]],"c":true},"ix":2},"nm":"Path 1","mn":"ADBE Vector Shape - Group","hd":false},{"ty":"fl","c":{"a":0,"k":[0,0.721568644047,0.070588238537,1],"ix":4},"o":{"a":0,"k":100,"ix":5},"r":1,"bm":0,"nm":"Fill 1","mn":"ADBE Vector Graphic - Fill","hd":false},{"ty":"tr","p":{"a":0,"k":[0,0],"ix":2},"a":{"a":0,"k":[0,0],"ix":1},"s":{"a":0,"k":[100,100],"ix":3},"r":{"a":0,"k":0,"ix":6},"o":{"a":0,"k":100,"ix":7},"sk":{"a":0,"k":0,"ix":4},"sa":{"a":0,"k":0,"ix":5},"nm":"Transform"}],"nm":"Vector","np":2,"cix":2,"bm":0,"ix":1,"mn":"ADBE Vector Group","hd":false}],"ip":0,"op":300,"st":0,"bm":0},{"ddd":0,"ind":2,"ty":4,"nm":"Arrow Thick Left 3","sr":1,"ks":{"o":{"a":0,"k":100,"ix":11},"r":{"a":0,"k":0,"ix":10},"p":{"a":0,"k":[12,12,0],"ix":2},"a":{"a":0,"k":[0,0,0],"ix":1},"s":{"a":0,"k":[100,100,100],"ix":6}},"ao":0,"shapes":[{"ty":"gr","it":[{"ty":"rc","d":1,"s":{"a":0,"k":[24,24],"ix":2},"p":{"a":0,"k":[0,0],"ix":3},"r":{"a":0,"k":0,"ix":4},"nm":"Rectangle Path 1","mn":"ADBE Vector Shape - Rect","hd":false},{"ty":"tr","p":{"a":0,"k":[0,0],"ix":2},"a":{"a":0,"k":[0,0],"ix":1},"s":{"a":0,"k":[100,100],"ix":3},"r":{"a":0,"k":0,"ix":6},"o":{"a":0,"k":100,"ix":7},"sk":{"a":0,"k":0,"ix":4},"sa":{"a":0,"k":0,"ix":5},"nm":"Transform"}],"nm":"Arrow Thick Left 3","np":1,"cix":2,"bm":0,"ix":1,"mn":"ADBE Vector Group","hd":false}],"ip":0,"op":300,"st":0,"bm":0}]},{"id":"comp_1","layers":[{"ddd":0,"ind":1,"ty":4,"nm":"mat","td":1,"sr":1,"ks":{"o":{"a":0,"k":100,"ix":11},"r":{"a":0,"k":0,"ix":10},"p":{"a":0,"k":[100,25.772,0],"ix":2},"a":{"a":0,"k":[-18.512,-17.472,0],"ix":1},"s":{"a":0,"k":[100,78.571,100],"ix":6}},"ao":0,"shapes":[{"ty":"gr","it":[{"ty":"rc","d":1,"s":{"a":0,"k":[4,63.057],"ix":2},"p":{"a":0,"k":[0,0],"ix":3},"r":{"a":0,"k":9,"ix":4},"nm":"Rectangle Path 1","mn":"ADBE Vector Shape - Rect","hd":false},{"ty":"fl","c":{"a":0,"k":[1,0,0,1],"ix":4},"o":{"a":0,"k":100,"ix":5},"r":1,"bm":0,"nm":"Fill 1","mn":"ADBE Vector Graphic - Fill","hd":false},{"ty":"tr","p":{"a":0,"k":[-18.512,-17.472],"ix":2},"a":{"a":0,"k":[0,0],"ix":1},"s":{"a":0,"k":[100,100],"ix":3},"r":{"a":0,"k":0,"ix":6},"o":{"a":0,"k":100,"ix":7},"sk":{"a":0,"k":0,"ix":4},"sa":{"a":0,"k":0,"ix":5},"nm":"Transform"}],"nm":"Rectangle 1","np":3,"cix":2,"bm":0,"ix":1,"mn":"ADBE Vector Group","hd":false}],"ip":0,"op":30,"st":0,"bm":0},{"ddd":0,"ind":2,"ty":4,"nm":"line","tt":1,"sr":1,"ks":{"o":{"a":0,"k":100,"ix":11},"r":{"a":0,"k":0,"ix":10},"p":{"a":1,"k":[{"i":{"x":0.228,"y":1},"o":{"x":0.267,"y":0},"t":0,"s":[100,75.772,0],"to":[0,-16.333,0],"ti":[0,16.333,0]},{"t":30,"s":[100,-22.228,0]}],"ix":2},"a":{"a":0,"k":[-18.512,-17.472,0],"ix":1},"s":{"a":0,"k":[100,78.571,100],"ix":6}},"ao":0,"shapes":[{"ty":"gr","it":[{"ty":"rc","d":1,"s":{"a":0,"k":[4,63.057],"ix":2},"p":{"a":0,"k":[0,0],"ix":3},"r":{"a":0,"k":9,"ix":4},"nm":"Rectangle Path 1","mn":"ADBE Vector Shape - Rect","hd":false},{"ty":"fl","c":{"a":0,"k":[0,0.721568644047,0.070588238537,1],"ix":4},"o":{"a":0,"k":100,"ix":5},"r":1,"bm":0,"nm":"Fill 1","mn":"ADBE Vector Graphic - Fill","hd":false},{"ty":"tr","p":{"a":0,"k":[-18.512,-17.472],"ix":2},"a":{"a":0,"k":[0,0],"ix":1},"s":{"a":0,"k":[100,100],"ix":3},"r":{"a":0,"k":0,"ix":6},"o":{"a":0,"k":100,"ix":7},"sk":{"a":0,"k":0,"ix":4},"sa":{"a":0,"k":0,"ix":5},"nm":"Transform"}],"nm":"Rectangle 1","np":3,"cix":2,"bm":0,"ix":1,"mn":"ADBE Vector Group","hd":false}],"ip":0,"op":30,"st":0,"bm":0}]},{"id":"comp_2","layers":[{"ddd":0,"ind":1,"ty":3,"nm":"▽ Buttons","sr":1,"ks":{"o":{"a":0,"k":100,"ix":11},"r":{"a":0,"k":0,"ix":10},"p":{"a":0,"k":[51,124.95,0],"ix":2},"a":{"a":0,"k":[30.6,33.15,0],"ix":1},"s":{"a":0,"k":[100,100,100],"ix":6}},"ao":0,"ip":0,"op":300,"st":0,"bm":0},{"ddd":0,"ind":2,"ty":4,"nm":"Top highlight","parent":1,"sr":1,"ks":{"o":{"a":0,"k":40,"ix":11},"r":{"a":0,"k":0,"ix":10},"p":{"a":0,"k":[30.6,32.893,0],"ix":2},"a":{"a":0,"k":[0,0,0],"ix":1},"s":{"a":0,"k":[100,100,100],"ix":6}},"ao":0,"shapes":[{"ty":"gr","it":[{"ind":0,"ty":"sh","ix":1,"ks":{"a":0,"k":{"i":[[0,-0.469],[0.045,-0.103],[0.35,0],[0.13,-0.302],[0,0.12],[-0.469,0]],"o":[[0,0.12],[-0.13,-0.302],[-0.35,0],[-0.045,-0.103],[0,-0.469],[0.469,0]],"v":[[0.85,-32.043],[0.781,-31.707],[0,-32.22],[-0.781,-31.707],[-0.85,-32.043],[0,-32.893]],"c":true},"ix":2},"nm":"Path 1","mn":"ADBE Vector Shape - Group","hd":false},{"ind":1,"ty":"sh","ix":2,"ks":{"a":0,"k":{"i":[[0,-0.469],[0.045,-0.103],[0.35,0],[0.13,-0.302],[0,0.12],[-0.469,0]],"o":[[0,0.12],[-0.13,-0.302],[-0.35,0],[-0.045,-0.103],[0,-0.469],[0.469,0]],"v":[[4.25,-28.643],[4.181,-28.307],[3.4,-28.82],[2.619,-28.307],[2.55,-28.643],[3.4,-29.493]],"c":true},"ix":2},"nm":"Path 2","mn":"ADBE Vector Shape - Group","hd":false},{"ind":2,"ty":"sh","ix":3,"ks":{"a":0,"k":{"i":[[0,-0.469],[0.045,-0.103],[0.35,0],[0.13,-0.302],[0,0.12],[-0.469,0]],"o":[[0,0.12],[-0.13,-0.302],[-0.35,0],[-0.045,-0.103],[0,-0.469],[0.469,0]],"v":[[-2.55,-28.643],[-2.619,-28.307],[-3.4,-28.82],[-4.181,-28.307],[-4.25,-28.643],[-3.4,-29.493]],"c":true},"ix":2},"nm":"Path 3","mn":"ADBE Vector Shape - Group","hd":false},{"ind":3,"ty":"sh","ix":4,"ks":{"a":0,"k":{"i":[[0,-0.469],[0.045,-0.103],[0.35,0],[0.13,-0.302],[0,0.12],[-0.469,0]],"o":[[0,0.12],[-0.13,-0.302],[-0.35,0],[-0.045,-0.103],[0,-0.469],[0.469,0]],"v":[[7.65,-25.243],[7.581,-24.907],[6.8,-25.42],[6.019,-24.907],[5.95,-25.243],[6.8,-26.093]],"c":true},"ix":2},"nm":"Path 4","mn":"ADBE Vector Shape - Group","hd":false},{"ind":4,"ty":"sh","ix":5,"ks":{"a":0,"k":{"i":[[0,-0.469],[0.045,-0.103],[0.35,0],[0.13,-0.302],[0,0.12],[-0.469,0]],"o":[[0,0.12],[-0.13,-0.302],[-0.35,0],[-0.045,-0.103],[0,-0.469],[0.469,0]],"v":[[-5.95,-25.243],[-6.019,-24.907],[-6.8,-25.42],[-7.581,-24.907],[-7.65,-25.243],[-6.8,-26.093]],"c":true},"ix":2},"nm":"Path 5","mn":"ADBE Vector Shape - Group","hd":false},{"ind":5,"ty":"sh","ix":6,"ks":{"a":0,"k":{"i":[[0,-0.469],[0.045,-0.103],[0.35,0],[0.13,-0.302],[0,0.12],[-0.469,0]],"o":[[0,0.12],[-0.13,-0.302],[-0.35,0],[-0.045,-0.103],[0,-0.469],[0.469,0]],"v":[[-28.9,0.257],[-28.969,0.593],[-29.75,0.08],[-30.531,0.593],[-30.6,0.257],[-29.75,-0.593]],"c":true},"ix":2},"nm":"Path 6","mn":"ADBE Vector Shape - Group","hd":false},{"ind":6,"ty":"sh","ix":7,"ks":{"a":0,"k":{"i":[[0,-0.469],[0.045,-0.103],[0.35,0],[0.13,-0.302],[0,0.12],[-0.469,0]],"o":[[0,0.12],[-0.13,-0.302],[-0.35,0],[-0.045,-0.103],[0,-0.469],[0.469,0]],"v":[[-25.5,-3.143],[-25.569,-2.807],[-26.35,-3.32],[-27.131,-2.807],[-27.2,-3.143],[-26.35,-3.993]],"c":true},"ix":2},"nm":"Path 7","mn":"ADBE Vector Shape - Group","hd":false},{"ind":7,"ty":"sh","ix":8,"ks":{"a":0,"k":{"i":[[0,-0.469],[0.045,-0.103],[0.35,0],[0.13,-0.302],[0,0.12],[-0.469,0]],"o":[[0,0.12],[-0.13,-0.302],[-0.35,0],[-0.045,-0.103],[0,-0.469],[0.469,0]],"v":[[-25.5,3.657],[-25.569,3.993],[-26.35,3.48],[-27.131,3.993],[-27.2,3.657],[-26.35,2.807]],"c":true},"ix":2},"nm":"Path 8","mn":"ADBE Vector Shape - Group","hd":false},{"ind":8,"ty":"sh","ix":9,"ks":{"a":0,"k":{"i":[[0,-0.469],[0.045,-0.103],[0.35,0],[0.13,-0.302],[0,0.12],[-0.469,0]],"o":[[0,0.12],[-0.13,-0.302],[-0.35,0],[-0.045,-0.103],[0,-0.469],[0.469,0]],"v":[[-22.1,-6.543],[-22.169,-6.207],[-22.95,-6.72],[-23.731,-6.207],[-23.8,-6.543],[-22.95,-7.393]],"c":true},"ix":2},"nm":"Path 9","mn":"ADBE Vector Shape - Group","hd":false},{"ind":9,"ty":"sh","ix":10,"ks":{"a":0,"k":{"i":[[0,-0.469],[0.045,-0.103],[0.35,0],[0.13,-0.302],[0,0.12],[-0.469,0]],"o":[[0,0.12],[-0.13,-0.302],[-0.35,0],[-0.045,-0.103],[0,-0.469],[0.469,0]],"v":[[-22.1,7.057],[-22.169,7.393],[-22.95,6.88],[-23.731,7.393],[-23.8,7.057],[-22.95,6.207]],"c":true},"ix":2},"nm":"Path 10","mn":"ADBE Vector Shape - Group","hd":false},{"ind":10,"ty":"sh","ix":11,"ks":{"a":0,"k":{"i":[[0,-0.469],[0.045,-0.103],[0.35,0],[0.13,-0.302],[0,0.12],[-0.469,0]],"o":[[0,0.12],[-0.13,-0.302],[-0.35,0],[-0.045,-0.103],[0,-0.469],[0.469,0]],"v":[[0.85,32.557],[0.781,32.893],[0,32.38],[-0.781,32.893],[-0.85,32.557],[0,31.707]],"c":true},"ix":2},"nm":"Path 11","mn":"ADBE Vector Shape - Group","hd":false},{"ind":11,"ty":"sh","ix":12,"ks":{"a":0,"k":{"i":[[0,-0.469],[0.045,-0.103],[0.35,0],[0.13,-0.302],[0,0.12],[-0.469,0]],"o":[[0,0.12],[-0.13,-0.302],[-0.35,0],[-0.045,-0.103],[0,-0.469],[0.469,0]],"v":[[-2.55,29.157],[-2.619,29.493],[-3.4,28.98],[-4.181,29.493],[-4.25,29.157],[-3.4,28.307]],"c":true},"ix":2},"nm":"Path 12","mn":"ADBE Vector Shape - Group","hd":false},{"ind":12,"ty":"sh","ix":13,"ks":{"a":0,"k":{"i":[[0,-0.469],[0.045,-0.103],[0.35,0],[0.13,-0.302],[0,0.12],[-0.469,0]],"o":[[0,0.12],[-0.13,-0.302],[-0.35,0],[-0.045,-0.103],[0,-0.469],[0.469,0]],"v":[[4.25,29.157],[4.181,29.493],[3.4,28.98],[2.619,29.493],[2.55,29.157],[3.4,28.307]],"c":true},"ix":2},"nm":"Path 13","mn":"ADBE Vector Shape - Group","hd":false},{"ind":13,"ty":"sh","ix":14,"ks":{"a":0,"k":{"i":[[0,-0.469],[0.045,-0.103],[0.35,0],[0.13,-0.302],[0,0.12],[-0.469,0]],"o":[[0,0.12],[-0.13,-0.302],[-0.35,0],[-0.045,-0.103],[0,-0.469],[0.469,0]],"v":[[-5.95,25.757],[-6.019,26.093],[-6.8,25.58],[-7.581,26.093],[-7.65,25.757],[-6.8,24.907]],"c":true},"ix":2},"nm":"Path 14","mn":"ADBE Vector Shape - Group","hd":false},{"ind":14,"ty":"sh","ix":15,"ks":{"a":0,"k":{"i":[[0,-0.469],[0.045,-0.103],[0.35,0],[0.13,-0.302],[0,0.12],[-0.469,0]],"o":[[0,0.12],[-0.13,-0.302],[-0.35,0],[-0.045,-0.103],[0,-0.469],[0.469,0]],"v":[[7.65,25.757],[7.581,26.093],[6.8,25.58],[6.019,26.093],[5.95,25.757],[6.8,24.907]],"c":true},"ix":2},"nm":"Path 15","mn":"ADBE Vector Shape - Group","hd":false},{"ind":15,"ty":"sh","ix":16,"ks":{"a":0,"k":{"i":[[0,-0.469],[0.045,-0.103],[0.35,0],[0.13,-0.302],[0,0.12],[-0.469,0]],"o":[[0,0.12],[-0.13,-0.302],[-0.35,0],[-0.045,-0.103],[0,-0.469],[0.469,0]],"v":[[30.6,0.257],[30.531,0.593],[29.75,0.08],[28.969,0.593],[28.9,0.257],[29.75,-0.593]],"c":true},"ix":2},"nm":"Path 16","mn":"ADBE Vector Shape - Group","hd":false},{"ind":16,"ty":"sh","ix":17,"ks":{"a":0,"k":{"i":[[0,-0.469],[0.045,-0.103],[0.35,0],[0.13,-0.302],[0,0.12],[-0.469,0]],"o":[[0,0.12],[-0.13,-0.302],[-0.35,0],[-0.045,-0.103],[0,-0.469],[0.469,0]],"v":[[27.2,3.657],[27.131,3.993],[26.35,3.48],[25.569,3.993],[25.5,3.657],[26.35,2.807]],"c":true},"ix":2},"nm":"Path 17","mn":"ADBE Vector Shape - Group","hd":false},{"ind":17,"ty":"sh","ix":18,"ks":{"a":0,"k":{"i":[[0,-0.469],[0.045,-0.103],[0.35,0],[0.13,-0.302],[0,0.12],[-0.469,0]],"o":[[0,0.12],[-0.13,-0.302],[-0.35,0],[-0.045,-0.103],[0,-0.469],[0.469,0]],"v":[[27.2,-3.143],[27.131,-2.807],[26.35,-3.32],[25.569,-2.807],[25.5,-3.143],[26.35,-3.993]],"c":true},"ix":2},"nm":"Path 18","mn":"ADBE Vector Shape - Group","hd":false},{"ind":18,"ty":"sh","ix":19,"ks":{"a":0,"k":{"i":[[0,-0.469],[0.045,-0.103],[0.35,0],[0.13,-0.302],[0,0.12],[-0.469,0]],"o":[[0,0.12],[-0.13,-0.302],[-0.35,0],[-0.045,-0.103],[0,-0.469],[0.469,0]],"v":[[23.8,7.057],[23.731,7.393],[22.95,6.88],[22.169,7.393],[22.1,7.057],[22.95,6.207]],"c":true},"ix":2},"nm":"Path 19","mn":"ADBE Vector Shape - Group","hd":false},{"ind":19,"ty":"sh","ix":20,"ks":{"a":0,"k":{"i":[[0,-0.469],[0.045,-0.103],[0.35,0],[0.13,-0.302],[0,0.12],[-0.469,0]],"o":[[0,0.12],[-0.13,-0.302],[-0.35,0],[-0.045,-0.103],[0,-0.469],[0.469,0]],"v":[[23.8,-6.543],[23.731,-6.207],[22.95,-6.72],[22.169,-6.207],[22.1,-6.543],[22.95,-7.393]],"c":true},"ix":2},"nm":"Path 20","mn":"ADBE Vector Shape - Group","hd":false},{"ty":"mm","mm":1,"nm":"Merge Paths 1","mn":"ADBE Vector Filter - Merge","hd":false},{"ty":"fl","c":{"a":0,"k":[1,1,1,1],"ix":4},"o":{"a":0,"k":100,"ix":5},"r":1,"bm":0,"nm":"Fill 1","mn":"ADBE Vector Graphic - Fill","hd":false},{"ty":"tr","p":{"a":0,"k":[0,0],"ix":2},"a":{"a":0,"k":[0,0],"ix":1},"s":{"a":0,"k":[100,100],"ix":3},"r":{"a":0,"k":0,"ix":6},"o":{"a":0,"k":100,"ix":7},"sk":{"a":0,"k":0,"ix":4},"sa":{"a":0,"k":0,"ix":5},"nm":"Transform"}],"nm":"Top highlight","np":22,"cix":2,"bm":0,"ix":1,"mn":"ADBE Vector Group","hd":false}],"ip":0,"op":300,"st":0,"bm":0},{"ddd":0,"ind":3,"ty":4,"nm":"Shadow","parent":1,"sr":1,"ks":{"o":{"a":0,"k":20,"ix":11},"r":{"a":0,"k":0,"ix":10},"p":{"a":0,"k":[30.6,33.15,0],"ix":2},"a":{"a":0,"k":[0,0,0],"ix":1},"s":{"a":0,"k":[100,100,100],"ix":6}},"ao":0,"shapes":[{"ty":"gr","it":[{"ind":0,"ty":"sh","ix":1,"ks":{"a":0,"k":{"i":[[-0.469,0],[0,0.469],[0.469,0],[0,-0.469]],"o":[[0.469,0],[0,-0.469],[-0.469,0],[0,0.469]],"v":[[0,-31.45],[0.85,-32.3],[0,-33.15],[-0.85,-32.3]],"c":true},"ix":2},"nm":"Path 1","mn":"ADBE Vector Shape - Group","hd":false},{"ind":1,"ty":"sh","ix":2,"ks":{"a":0,"k":{"i":[[-0.469,0],[0,0.469],[0.469,0],[0,-0.469]],"o":[[0.469,0],[0,-0.469],[-0.469,0],[0,0.469]],"v":[[3.4,-28.05],[4.25,-28.9],[3.4,-29.75],[2.55,-28.9]],"c":true},"ix":2},"nm":"Path 2","mn":"ADBE Vector Shape - Group","hd":false},{"ind":2,"ty":"sh","ix":3,"ks":{"a":0,"k":{"i":[[-0.469,0],[0,0.469],[0.469,0],[0,-0.469]],"o":[[0.469,0],[0,-0.469],[-0.469,0],[0,0.469]],"v":[[-3.4,-28.05],[-2.55,-28.9],[-3.4,-29.75],[-4.25,-28.9]],"c":true},"ix":2},"nm":"Path 3","mn":"ADBE Vector Shape - Group","hd":false},{"ind":3,"ty":"sh","ix":4,"ks":{"a":0,"k":{"i":[[-0.469,0],[0,0.469],[0.469,0],[0,-0.469]],"o":[[0.469,0],[0,-0.469],[-0.469,0],[0,0.469]],"v":[[6.8,-24.65],[7.65,-25.5],[6.8,-26.35],[5.95,-25.5]],"c":true},"ix":2},"nm":"Path 4","mn":"ADBE Vector Shape - Group","hd":false},{"ind":4,"ty":"sh","ix":5,"ks":{"a":0,"k":{"i":[[-0.469,0],[0,0.469],[0.469,0],[0,-0.469]],"o":[[0.469,0],[0,-0.469],[-0.469,0],[0,0.469]],"v":[[-6.8,-24.65],[-5.95,-25.5],[-6.8,-26.35],[-7.65,-25.5]],"c":true},"ix":2},"nm":"Path 5","mn":"ADBE Vector Shape - Group","hd":false},{"ind":5,"ty":"sh","ix":6,"ks":{"a":0,"k":{"i":[[-0.469,0],[0,0.469],[0.469,0],[0,-0.469]],"o":[[0.469,0],[0,-0.469],[-0.469,0],[0,0.469]],"v":[[-29.75,0.85],[-28.9,0],[-29.75,-0.85],[-30.6,0]],"c":true},"ix":2},"nm":"Path 6","mn":"ADBE Vector Shape - Group","hd":false},{"ind":6,"ty":"sh","ix":7,"ks":{"a":0,"k":{"i":[[-0.469,0],[0,0.469],[0.469,0],[0,-0.469]],"o":[[0.469,0],[0,-0.469],[-0.469,0],[0,0.469]],"v":[[-26.35,-2.55],[-25.5,-3.4],[-26.35,-4.25],[-27.2,-3.4]],"c":true},"ix":2},"nm":"Path 7","mn":"ADBE Vector Shape - Group","hd":false},{"ind":7,"ty":"sh","ix":8,"ks":{"a":0,"k":{"i":[[-0.469,0],[0,0.469],[0.469,0],[0,-0.469]],"o":[[0.469,0],[0,-0.469],[-0.469,0],[0,0.469]],"v":[[-26.35,4.25],[-25.5,3.4],[-26.35,2.55],[-27.2,3.4]],"c":true},"ix":2},"nm":"Path 8","mn":"ADBE Vector Shape - Group","hd":false},{"ind":8,"ty":"sh","ix":9,"ks":{"a":0,"k":{"i":[[-0.469,0],[0,0.469],[0.469,0],[0,-0.469]],"o":[[0.469,0],[0,-0.469],[-0.469,0],[0,0.469]],"v":[[-22.95,-5.95],[-22.1,-6.8],[-22.95,-7.65],[-23.8,-6.8]],"c":true},"ix":2},"nm":"Path 9","mn":"ADBE Vector Shape - Group","hd":false},{"ind":9,"ty":"sh","ix":10,"ks":{"a":0,"k":{"i":[[-0.469,0],[0,0.469],[0.469,0],[0,-0.469]],"o":[[0.469,0],[0,-0.469],[-0.469,0],[0,0.469]],"v":[[-22.95,7.65],[-22.1,6.8],[-22.95,5.95],[-23.8,6.8]],"c":true},"ix":2},"nm":"Path 10","mn":"ADBE Vector Shape - Group","hd":false},{"ind":10,"ty":"sh","ix":11,"ks":{"a":0,"k":{"i":[[-0.469,0],[0,0.469],[0.469,0],[0,-0.469]],"o":[[0.469,0],[0,-0.469],[-0.469,0],[0,0.469]],"v":[[0,33.15],[0.85,32.3],[0,31.45],[-0.85,32.3]],"c":true},"ix":2},"nm":"Path 11","mn":"ADBE Vector Shape - Group","hd":false},{"ind":11,"ty":"sh","ix":12,"ks":{"a":0,"k":{"i":[[-0.469,0],[0,0.469],[0.469,0],[0,-0.469]],"o":[[0.469,0],[0,-0.469],[-0.469,0],[0,0.469]],"v":[[-3.4,29.75],[-2.55,28.9],[-3.4,28.05],[-4.25,28.9]],"c":true},"ix":2},"nm":"Path 12","mn":"ADBE Vector Shape - Group","hd":false},{"ind":12,"ty":"sh","ix":13,"ks":{"a":0,"k":{"i":[[-0.469,0],[0,0.469],[0.469,0],[0,-0.469]],"o":[[0.469,0],[0,-0.469],[-0.469,0],[0,0.469]],"v":[[3.4,29.75],[4.25,28.9],[3.4,28.05],[2.55,28.9]],"c":true},"ix":2},"nm":"Path 13","mn":"ADBE Vector Shape - Group","hd":false},{"ind":13,"ty":"sh","ix":14,"ks":{"a":0,"k":{"i":[[-0.469,0],[0,0.469],[0.469,0],[0,-0.469]],"o":[[0.469,0],[0,-0.469],[-0.469,0],[0,0.469]],"v":[[-6.8,26.35],[-5.95,25.5],[-6.8,24.65],[-7.65,25.5]],"c":true},"ix":2},"nm":"Path 14","mn":"ADBE Vector Shape - Group","hd":false},{"ind":14,"ty":"sh","ix":15,"ks":{"a":0,"k":{"i":[[-0.469,0],[0,0.469],[0.469,0],[0,-0.469]],"o":[[0.469,0],[0,-0.469],[-0.469,0],[0,0.469]],"v":[[6.8,26.35],[7.65,25.5],[6.8,24.65],[5.95,25.5]],"c":true},"ix":2},"nm":"Path 15","mn":"ADBE Vector Shape - Group","hd":false},{"ind":15,"ty":"sh","ix":16,"ks":{"a":0,"k":{"i":[[-0.469,0],[0,0.469],[0.469,0],[0,-0.469]],"o":[[0.469,0],[0,-0.469],[-0.469,0],[0,0.469]],"v":[[29.75,0.85],[30.6,0],[29.75,-0.85],[28.9,0]],"c":true},"ix":2},"nm":"Path 16","mn":"ADBE Vector Shape - Group","hd":false},{"ind":16,"ty":"sh","ix":17,"ks":{"a":0,"k":{"i":[[-0.469,0],[0,0.469],[0.469,0],[0,-0.469]],"o":[[0.469,0],[0,-0.469],[-0.469,0],[0,0.469]],"v":[[26.35,4.25],[27.2,3.4],[26.35,2.55],[25.5,3.4]],"c":true},"ix":2},"nm":"Path 17","mn":"ADBE Vector Shape - Group","hd":false},{"ind":17,"ty":"sh","ix":18,"ks":{"a":0,"k":{"i":[[-0.469,0],[0,0.469],[0.469,0],[0,-0.469]],"o":[[0.469,0],[0,-0.469],[-0.469,0],[0,0.469]],"v":[[26.35,-2.55],[27.2,-3.4],[26.35,-4.25],[25.5,-3.4]],"c":true},"ix":2},"nm":"Path 18","mn":"ADBE Vector Shape - Group","hd":false},{"ind":18,"ty":"sh","ix":19,"ks":{"a":0,"k":{"i":[[-0.469,0],[0,0.469],[0.469,0],[0,-0.469]],"o":[[0.469,0],[0,-0.469],[-0.469,0],[0,0.469]],"v":[[22.95,7.65],[23.8,6.8],[22.95,5.95],[22.1,6.8]],"c":true},"ix":2},"nm":"Path 19","mn":"ADBE Vector Shape - Group","hd":false},{"ind":19,"ty":"sh","ix":20,"ks":{"a":0,"k":{"i":[[-0.469,0],[0,0.469],[0.469,0],[0,-0.469]],"o":[[0.469,0],[0,-0.469],[-0.469,0],[0,0.469]],"v":[[22.95,-5.95],[23.8,-6.8],[22.95,-7.65],[22.1,-6.8]],"c":true},"ix":2},"nm":"Path 20","mn":"ADBE Vector Shape - Group","hd":false},{"ty":"mm","mm":1,"nm":"Merge Paths 1","mn":"ADBE Vector Filter - Merge","hd":false},{"ty":"fl","c":{"a":0,"k":[0,0,0,1],"ix":4},"o":{"a":0,"k":100,"ix":5},"r":1,"bm":0,"nm":"Fill 1","mn":"ADBE Vector Graphic - Fill","hd":false},{"ty":"tr","p":{"a":0,"k":[0,0],"ix":2},"a":{"a":0,"k":[0,0],"ix":1},"s":{"a":0,"k":[100,100],"ix":3},"r":{"a":0,"k":0,"ix":6},"o":{"a":0,"k":100,"ix":7},"sk":{"a":0,"k":0,"ix":4},"sa":{"a":0,"k":0,"ix":5},"nm":"Transform"}],"nm":"Shadow","np":22,"cix":2,"bm":0,"ix":1,"mn":"ADBE Vector Group","hd":false}],"ip":0,"op":300,"st":0,"bm":0},{"ddd":0,"ind":4,"ty":3,"nm":"▽ Screen","sr":1,"ks":{"o":{"a":0,"k":100,"ix":11},"r":{"a":0,"k":0,"ix":10},"p":{"a":0,"k":[51,47.6,0],"ix":2},"a":{"a":0,"k":[34,34,0],"ix":1},"s":{"a":0,"k":[100,100,100],"ix":6}},"ao":0,"ip":0,"op":300,"st":0,"bm":0},{"ddd":0,"ind":5,"ty":4,"nm":"Shadow","parent":4,"sr":1,"ks":{"o":{"a":0,"k":20,"ix":11},"r":{"a":0,"k":0,"ix":10},"p":{"a":0,"k":[34,2.55,0],"ix":2},"a":{"a":0,"k":[0,0,0],"ix":1},"s":{"a":0,"k":[100,100,100],"ix":6}},"ao":0,"shapes":[{"ty":"gr","it":[{"ind":0,"ty":"sh","ix":1,"ks":{"a":0,"k":{"i":[[0,0],[-1.878,0],[0,0],[0,-1.878],[0,0],[1.878,0],[0,0],[0,-1.878]],"o":[[0,-1.878],[0,0],[1.878,0],[0,0],[0,-1.878],[0,0],[-1.878,0],[0,0]],"v":[[-34,0.85],[-30.6,-2.55],[30.6,-2.55],[34,0.85],[34,2.55],[30.6,-0.85],[-30.6,-0.85],[-34,2.55]],"c":true},"ix":2},"nm":"Path 1","mn":"ADBE Vector Shape - Group","hd":false},{"ty":"fl","c":{"a":0,"k":[0,0,0,1],"ix":4},"o":{"a":0,"k":100,"ix":5},"r":1,"bm":0,"nm":"Fill 1","mn":"ADBE Vector Graphic - Fill","hd":false},{"ty":"tr","p":{"a":0,"k":[0,0],"ix":2},"a":{"a":0,"k":[0,0],"ix":1},"s":{"a":0,"k":[100,100],"ix":3},"r":{"a":0,"k":0,"ix":6},"o":{"a":0,"k":100,"ix":7},"sk":{"a":0,"k":0,"ix":4},"sa":{"a":0,"k":0,"ix":5},"nm":"Transform"}],"nm":"Shadow","np":2,"cix":2,"bm":0,"ix":1,"mn":"ADBE Vector Group","hd":false}],"ip":0,"op":300,"st":0,"bm":0},{"ddd":0,"ind":6,"ty":4,"nm":"Highlight","parent":4,"sr":1,"ks":{"o":{"a":0,"k":30,"ix":11},"r":{"a":0,"k":0,"ix":10},"p":{"a":0,"k":[34,65.45,0],"ix":2},"a":{"a":0,"k":[0,0,0],"ix":1},"s":{"a":0,"k":[100,100,100],"ix":6}},"ao":0,"shapes":[{"ty":"gr","it":[{"ind":0,"ty":"sh","ix":1,"ks":{"a":0,"k":{"i":[[0,1.878],[0,0],[-1.878,0],[0,0],[0,1.878],[0,0],[1.878,0],[0,0]],"o":[[0,0],[0,1.878],[0,0],[1.878,0],[0,0],[0,1.878],[0,0],[-1.878,0]],"v":[[-34,-0.85],[-34,-2.55],[-30.6,0.85],[30.6,0.85],[34,-2.55],[34,-0.85],[30.6,2.55],[-30.6,2.55]],"c":true},"ix":2},"nm":"Path 1","mn":"ADBE Vector Shape - Group","hd":false},{"ty":"fl","c":{"a":0,"k":[1,1,1,1],"ix":4},"o":{"a":0,"k":100,"ix":5},"r":1,"bm":0,"nm":"Fill 1","mn":"ADBE Vector Graphic - Fill","hd":false},{"ty":"tr","p":{"a":0,"k":[0,0],"ix":2},"a":{"a":0,"k":[0,0],"ix":1},"s":{"a":0,"k":[100,100],"ix":3},"r":{"a":0,"k":0,"ix":6},"o":{"a":0,"k":100,"ix":7},"sk":{"a":0,"k":0,"ix":4},"sa":{"a":0,"k":0,"ix":5},"nm":"Transform"}],"nm":"Highlight","np":2,"cix":2,"bm":0,"ix":1,"mn":"ADBE Vector Group","hd":false}],"ip":0,"op":300,"st":0,"bm":0},{"ddd":0,"ind":7,"ty":4,"nm":"Background","parent":4,"sr":1,"ks":{"o":{"a":0,"k":100,"ix":11},"r":{"a":0,"k":0,"ix":10},"p":{"a":0,"k":[34,34,0],"ix":2},"a":{"a":0,"k":[0,0,0],"ix":1},"s":{"a":0,"k":[100,100,100],"ix":6}},"ao":0,"shapes":[{"ty":"gr","it":[{"ty":"rc","d":1,"s":{"a":0,"k":[68,68],"ix":2},"p":{"a":0,"k":[0,0],"ix":3},"r":{"a":0,"k":3,"ix":4},"nm":"Rectangle Path 1","mn":"ADBE Vector Shape - Rect","hd":false},{"ty":"fl","c":{"a":0,"k":[0.329299986362,0.329299986362,0.410700023174,1],"ix":4},"o":{"a":0,"k":100,"ix":5},"r":1,"bm":0,"nm":"Fill 1","mn":"ADBE Vector Graphic - Fill","hd":false},{"ty":"tr","p":{"a":0,"k":[0,0],"ix":2},"a":{"a":0,"k":[0,0],"ix":1},"s":{"a":0,"k":[100,100],"ix":3},"r":{"a":0,"k":0,"ix":6},"o":{"a":0,"k":100,"ix":7},"sk":{"a":0,"k":0,"ix":4},"sa":{"a":0,"k":0,"ix":5},"nm":"Transform"}],"nm":"Background","np":2,"cix":2,"bm":0,"ix":1,"mn":"ADBE Vector Group","hd":false}],"ip":0,"op":300,"st":0,"bm":0},{"ddd":0,"ind":8,"ty":3,"nm":"▽ Body","sr":1,"ks":{"o":{"a":0,"k":100,"ix":11},"r":{"a":0,"k":0,"ix":10},"p":{"a":0,"k":[51,86.7,0],"ix":2},"a":{"a":0,"k":[47.6,86.7,0],"ix":1},"s":{"a":0,"k":[100,100,100],"ix":6}},"ao":0,"ip":0,"op":300,"st":0,"bm":0},{"ddd":0,"ind":9,"ty":4,"nm":"Top highlight","parent":8,"sr":1,"ks":{"o":{"a":0,"k":20,"ix":11},"r":{"a":0,"k":0,"ix":10},"p":{"a":0,"k":[47.6,5.95,0],"ix":2},"a":{"a":0,"k":[0,0,0],"ix":1},"s":{"a":0,"k":[100,100,100],"ix":6}},"ao":0,"shapes":[{"ty":"gr","it":[{"ind":0,"ty":"sh","ix":1,"ks":{"a":0,"k":{"i":[[0,0],[-5.633,0],[0,0],[0,-5.633],[0,0],[5.633,0],[0,0],[0,-5.633]],"o":[[0,-5.633],[0,0],[5.633,0],[0,0],[0,-5.633],[0,0],[-5.633,0],[0,0]],"v":[[-47.6,4.25],[-37.4,-5.95],[37.4,-5.95],[47.6,4.25],[47.6,5.95],[37.4,-4.25],[-37.4,-4.25],[-47.6,5.95]],"c":true},"ix":2},"nm":"Path 1","mn":"ADBE Vector Shape - Group","hd":false},{"ty":"fl","c":{"a":0,"k":[1,1,1,1],"ix":4},"o":{"a":0,"k":100,"ix":5},"r":1,"bm":0,"nm":"Fill 1","mn":"ADBE Vector Graphic - Fill","hd":false},{"ty":"tr","p":{"a":0,"k":[0,0],"ix":2},"a":{"a":0,"k":[0,0],"ix":1},"s":{"a":0,"k":[100,100],"ix":3},"r":{"a":0,"k":0,"ix":6},"o":{"a":0,"k":100,"ix":7},"sk":{"a":0,"k":0,"ix":4},"sa":{"a":0,"k":0,"ix":5},"nm":"Transform"}],"nm":"Top highlight","np":2,"cix":2,"bm":0,"ix":1,"mn":"ADBE Vector Group","hd":false}],"ip":0,"op":300,"st":0,"bm":0},{"ddd":0,"ind":10,"ty":4,"nm":"Shadow","parent":8,"sr":1,"ks":{"o":{"a":0,"k":20,"ix":11},"r":{"a":0,"k":0,"ix":10},"p":{"a":0,"k":[47.6,167.45,0],"ix":2},"a":{"a":0,"k":[0,0,0],"ix":1},"s":{"a":0,"k":[100,100,100],"ix":6}},"ao":0,"shapes":[{"ty":"gr","it":[{"ind":0,"ty":"sh","ix":1,"ks":{"a":0,"k":{"i":[[0,5.633],[0,0],[-5.633,0],[0,0],[0,5.633],[0,0],[5.633,0],[0,0]],"o":[[0,0],[0,5.633],[0,0],[5.633,0],[0,0],[0,5.633],[0,0],[-5.633,0]],"v":[[-47.6,-4.25],[-47.6,-5.95],[-37.4,4.25],[37.4,4.25],[47.6,-5.95],[47.6,-4.25],[37.4,5.95],[-37.4,5.95]],"c":true},"ix":2},"nm":"Path 1","mn":"ADBE Vector Shape - Group","hd":false},{"ty":"fl","c":{"a":0,"k":[0,0,0,1],"ix":4},"o":{"a":0,"k":100,"ix":5},"r":1,"bm":0,"nm":"Fill 1","mn":"ADBE Vector Graphic - Fill","hd":false},{"ty":"tr","p":{"a":0,"k":[0,0],"ix":2},"a":{"a":0,"k":[0,0],"ix":1},"s":{"a":0,"k":[100,100],"ix":3},"r":{"a":0,"k":0,"ix":6},"o":{"a":0,"k":100,"ix":7},"sk":{"a":0,"k":0,"ix":4},"sa":{"a":0,"k":0,"ix":5},"nm":"Transform"}],"nm":"Shadow","np":2,"cix":2,"bm":0,"ix":1,"mn":"ADBE Vector Group","hd":false}],"ip":0,"op":300,"st":0,"bm":0},{"ddd":0,"ind":11,"ty":4,"nm":"H highlight","parent":8,"sr":1,"ks":{"o":{"a":0,"k":10,"ix":11},"r":{"a":0,"k":0,"ix":10},"p":{"a":0,"k":[47.6,86.7,0],"ix":2},"a":{"a":0,"k":[0,0,0],"ix":1},"s":{"a":0,"k":[100,100,100],"ix":6}},"ao":0,"shapes":[{"ty":"gr","it":[{"ind":0,"ty":"sh","ix":1,"ks":{"a":0,"k":{"i":[[5.633,0],[0,0],[0,5.633],[0,0],[5.633,0],[0,0],[0,-5.633],[0,0]],"o":[[0,0],[5.633,0],[0,0],[0,-5.633],[0,0],[5.633,0],[0,0],[0,5.633]],"v":[[37.4,86.7],[35.7,86.7],[45.9,76.5],[45.9,-76.5],[35.7,-86.7],[37.4,-86.7],[47.6,-76.5],[47.6,76.5]],"c":true},"ix":2},"nm":"Path 1","mn":"ADBE Vector Shape - Group","hd":false},{"ind":1,"ty":"sh","ix":2,"ks":{"a":0,"k":{"i":[[0,0],[-5.633,0],[0,0],[0,-5.633],[0,0],[-5.633,0],[0,0],[0,5.633]],"o":[[0,-5.633],[0,0],[-5.633,0],[0,0],[0,5.633],[0,0],[-5.633,0],[0,0]],"v":[[-47.6,-76.5],[-37.4,-86.7],[-35.7,-86.7],[-45.9,-76.5],[-45.9,76.5],[-35.7,86.7],[-37.4,86.7],[-47.6,76.5]],"c":true},"ix":2},"nm":"Path 2","mn":"ADBE Vector Shape - Group","hd":false},{"ty":"mm","mm":1,"nm":"Merge Paths 1","mn":"ADBE Vector Filter - Merge","hd":false},{"ty":"fl","c":{"a":0,"k":[1,1,1,1],"ix":4},"o":{"a":0,"k":100,"ix":5},"r":1,"bm":0,"nm":"Fill 1","mn":"ADBE Vector Graphic - Fill","hd":false},{"ty":"tr","p":{"a":0,"k":[0,0],"ix":2},"a":{"a":0,"k":[0,0],"ix":1},"s":{"a":0,"k":[100,100],"ix":3},"r":{"a":0,"k":0,"ix":6},"o":{"a":0,"k":100,"ix":7},"sk":{"a":0,"k":0,"ix":4},"sa":{"a":0,"k":0,"ix":5},"nm":"Transform"}],"nm":"H highlight","np":4,"cix":2,"bm":0,"ix":1,"mn":"ADBE Vector Group","hd":false}],"ip":0,"op":300,"st":0,"bm":0},{"ddd":0,"ind":12,"ty":4,"nm":"Background","parent":8,"sr":1,"ks":{"o":{"a":0,"k":100,"ix":11},"r":{"a":0,"k":0,"ix":10},"p":{"a":0,"k":[47.6,86.7,0],"ix":2},"a":{"a":0,"k":[0,0,0],"ix":1},"s":{"a":0,"k":[100,100,100],"ix":6}},"ao":0,"shapes":[{"ty":"gr","it":[{"ty":"rc","d":1,"s":{"a":0,"k":[95.2,173.4],"ix":2},"p":{"a":0,"k":[0,0],"ix":3},"r":{"a":0,"k":10,"ix":4},"nm":"Rectangle Path 1","mn":"ADBE Vector Shape - Rect","hd":false},{"ty":"fl","c":{"a":0,"k":[0.45360827446,0.45360827446,0.54639172554,1],"ix":4},"o":{"a":0,"k":100,"ix":5},"r":1,"bm":0,"nm":"Fill 1","mn":"ADBE Vector Graphic - Fill","hd":false},{"ty":"tr","p":{"a":0,"k":[0,0],"ix":2},"a":{"a":0,"k":[0,0],"ix":1},"s":{"a":0,"k":[100,100],"ix":3},"r":{"a":0,"k":0,"ix":6},"o":{"a":0,"k":100,"ix":7},"sk":{"a":0,"k":0,"ix":4},"sa":{"a":0,"k":0,"ix":5},"nm":"Transform"}],"nm":"Background","np":2,"cix":2,"bm":0,"ix":1,"mn":"ADBE Vector Group","hd":false}],"ip":0,"op":300,"st":0,"bm":0},{"ddd":0,"ind":13,"ty":3,"nm":"▽ Power Button","sr":1,"ks":{"o":{"a":0,"k":100,"ix":11},"r":{"a":0,"k":0,"ix":10},"p":{"a":0,"k":[98.175,86.7,0],"ix":2},"a":{"a":0,"k":[2.975,6.8,0],"ix":1},"s":{"a":0,"k":[100,100,100],"ix":6}},"ao":0,"ip":0,"op":300,"st":0,"bm":0},{"ddd":0,"ind":14,"ty":4,"nm":"Highlight","parent":13,"sr":1,"ks":{"o":{"a":0,"k":20,"ix":11},"r":{"a":0,"k":0,"ix":10},"p":{"a":0,"k":[5.525,6.8,0],"ix":2},"a":{"a":0,"k":[0,0,0],"ix":1},"s":{"a":0,"k":[100,100,100],"ix":6}},"ao":0,"shapes":[{"ty":"gr","it":[{"ind":0,"ty":"sh","ix":1,"ks":{"a":0,"k":{"i":[[0,0],[0,-0.469],[0,0],[0.469,0]],"o":[[0.469,0],[0,0],[0,0.469],[0,0]],"v":[[-0.425,-6.8],[0.425,-5.95],[0.425,5.95],[-0.425,6.8]],"c":true},"ix":2},"nm":"Path 1","mn":"ADBE Vector Shape - Group","hd":false},{"ty":"fl","c":{"a":0,"k":[1,1,1,1],"ix":4},"o":{"a":0,"k":100,"ix":5},"r":1,"bm":0,"nm":"Fill 1","mn":"ADBE Vector Graphic - Fill","hd":false},{"ty":"tr","p":{"a":0,"k":[0,0],"ix":2},"a":{"a":0,"k":[0,0],"ix":1},"s":{"a":0,"k":[100,100],"ix":3},"r":{"a":0,"k":0,"ix":6},"o":{"a":0,"k":100,"ix":7},"sk":{"a":0,"k":0,"ix":4},"sa":{"a":0,"k":0,"ix":5},"nm":"Transform"}],"nm":"Highlight","np":2,"cix":2,"bm":0,"ix":1,"mn":"ADBE Vector Group","hd":false}],"ip":0,"op":300,"st":0,"bm":0},{"ddd":0,"ind":15,"ty":4,"nm":"Background","parent":13,"sr":1,"ks":{"o":{"a":0,"k":100,"ix":11},"r":{"a":0,"k":0,"ix":10},"p":{"a":0,"k":[2.975,6.8,0],"ix":2},"a":{"a":0,"k":[0,0,0],"ix":1},"s":{"a":0,"k":[100,100,100],"ix":6}},"ao":0,"shapes":[{"ty":"gr","it":[{"ind":0,"ty":"sh","ix":1,"ks":{"a":0,"k":{"i":[[0,0],[0,0],[0,0],[0,0]],"o":[[0,0],[0,0],[0,0],[0,0]],"v":[[2.975,-6.8],[-2.975,-6.8],[-2.975,6.8],[2.975,6.8]],"c":true},"ix":2},"nm":"Path 1","mn":"ADBE Vector Shape - Group","hd":false},{"ty":"fl","c":{"a":0,"k":[0.45360827446,0.45360827446,0.54639172554,1],"ix":4},"o":{"a":0,"k":100,"ix":5},"r":1,"bm":0,"nm":"Fill 1","mn":"ADBE Vector Graphic - Fill","hd":false},{"ty":"tr","p":{"a":0,"k":[0,0],"ix":2},"a":{"a":0,"k":[0,0],"ix":1},"s":{"a":0,"k":[100,100],"ix":3},"r":{"a":0,"k":0,"ix":6},"o":{"a":0,"k":100,"ix":7},"sk":{"a":0,"k":0,"ix":4},"sa":{"a":0,"k":0,"ix":5},"nm":"Transform"}],"nm":"Background","np":2,"cix":2,"bm":0,"ix":1,"mn":"ADBE Vector Group","hd":false}],"ip":0,"op":300,"st":0,"bm":0},{"ddd":0,"ind":16,"ty":4,"nm":"illus / Mini","sr":1,"ks":{"o":{"a":0,"k":100,"ix":11},"r":{"a":0,"k":0,"ix":10},"p":{"a":0,"k":[51,86.7,0],"ix":2},"a":{"a":0,"k":[0,0,0],"ix":1},"s":{"a":0,"k":[100,100,100],"ix":6}},"ao":0,"shapes":[{"ty":"gr","it":[{"ty":"rc","d":1,"s":{"a":0,"k":[102,173.4],"ix":2},"p":{"a":0,"k":[0,0],"ix":3},"r":{"a":0,"k":0,"ix":4},"nm":"Rectangle Path 1","mn":"ADBE Vector Shape - Rect","hd":false},{"ty":"tr","p":{"a":0,"k":[0,0],"ix":2},"a":{"a":0,"k":[0,0],"ix":1},"s":{"a":0,"k":[100,100],"ix":3},"r":{"a":0,"k":0,"ix":6},"o":{"a":0,"k":100,"ix":7},"sk":{"a":0,"k":0,"ix":4},"sa":{"a":0,"k":0,"ix":5},"nm":"Transform"}],"nm":"illus / Mini","np":1,"cix":2,"bm":0,"ix":1,"mn":"ADBE Vector Group","hd":false}],"ip":0,"op":300,"st":0,"bm":0}]},{"id":"comp_3","layers":[{"ddd":0,"ind":1,"ty":3,"nm":"▽ Bottom","sr":1,"ks":{"o":{"a":0,"k":100,"ix":11},"r":{"a":0,"k":0,"ix":10},"p":{"a":0,"k":[17,77,0],"ix":2},"a":{"a":0,"k":[5,20,0],"ix":1},"s":{"a":0,"k":[100,100,100],"ix":6}},"ao":0,"ip":0,"op":300,"st":0,"bm":0},{"ddd":0,"ind":2,"ty":4,"nm":"Top_shadow","parent":1,"sr":1,"ks":{"o":{"a":0,"k":20,"ix":11},"r":{"a":0,"k":0,"ix":10},"p":{"a":0,"k":[5,1,0],"ix":2},"a":{"a":0,"k":[0,0,0],"ix":1},"s":{"a":0,"k":[100,100,100],"ix":6}},"ao":0,"shapes":[{"ty":"gr","it":[{"ty":"rc","d":1,"s":{"a":0,"k":[10,2],"ix":2},"p":{"a":0,"k":[0,0],"ix":3},"r":{"a":0,"k":0,"ix":4},"nm":"Rectangle Path 1","mn":"ADBE Vector Shape - Rect","hd":false},{"ty":"fl","c":{"a":0,"k":[0,0,0,1],"ix":4},"o":{"a":0,"k":100,"ix":5},"r":1,"bm":0,"nm":"Fill 1","mn":"ADBE Vector Graphic - Fill","hd":false},{"ty":"tr","p":{"a":0,"k":[0,0],"ix":2},"a":{"a":0,"k":[0,0],"ix":1},"s":{"a":0,"k":[100,100],"ix":3},"r":{"a":0,"k":0,"ix":6},"o":{"a":0,"k":100,"ix":7},"sk":{"a":0,"k":0,"ix":4},"sa":{"a":0,"k":0,"ix":5},"nm":"Transform"}],"nm":"Top_shadow","np":2,"cix":2,"bm":0,"ix":1,"mn":"ADBE Vector Group","hd":false}],"ip":0,"op":300,"st":0,"bm":0},{"ddd":0,"ind":3,"ty":4,"nm":"Body","parent":1,"sr":1,"ks":{"o":{"a":0,"k":100,"ix":11},"r":{"a":0,"k":0,"ix":10},"p":{"a":0,"k":[5,20,0],"ix":2},"a":{"a":0,"k":[0,0,0],"ix":1},"s":{"a":0,"k":[100,100,100],"ix":6}},"ao":0,"shapes":[{"ty":"gr","it":[{"ty":"rc","d":1,"s":{"a":0,"k":[10,40],"ix":2},"p":{"a":0,"k":[0,0],"ix":3},"r":{"a":0,"k":0,"ix":4},"nm":"Rectangle Path 1","mn":"ADBE Vector Shape - Rect","hd":false},{"ty":"fl","c":{"a":0,"k":[0.45360827446,0.45360827446,0.54639172554,1],"ix":4},"o":{"a":0,"k":100,"ix":5},"r":1,"bm":0,"nm":"Fill 1","mn":"ADBE Vector Graphic - Fill","hd":false},{"ty":"tr","p":{"a":0,"k":[0,0],"ix":2},"a":{"a":0,"k":[0,0],"ix":1},"s":{"a":0,"k":[100,100],"ix":3},"r":{"a":0,"k":0,"ix":6},"o":{"a":0,"k":100,"ix":7},"sk":{"a":0,"k":0,"ix":4},"sa":{"a":0,"k":0,"ix":5},"nm":"Transform"}],"nm":"Body","np":2,"cix":2,"bm":0,"ix":1,"mn":"ADBE Vector Group","hd":false}],"ip":0,"op":300,"st":0,"bm":0},{"ddd":0,"ind":4,"ty":3,"nm":"▽ Middle","sr":1,"ks":{"o":{"a":0,"k":100,"ix":11},"r":{"a":0,"k":0,"ix":10},"p":{"a":0,"k":[17,37,0],"ix":2},"a":{"a":0,"k":[17,20,0],"ix":1},"s":{"a":0,"k":[100,100,100],"ix":6}},"ao":0,"ip":0,"op":300,"st":0,"bm":0},{"ddd":0,"ind":5,"ty":4,"nm":"Bottom_shadow","parent":4,"sr":1,"ks":{"o":{"a":0,"k":10,"ix":11},"r":{"a":0,"k":0,"ix":10},"p":{"a":0,"k":[17,37.5,0],"ix":2},"a":{"a":0,"k":[0,0,0],"ix":1},"s":{"a":0,"k":[100,100,100],"ix":6}},"ao":0,"shapes":[{"ty":"gr","it":[{"ind":0,"ty":"sh","ix":1,"ks":{"a":0,"k":{"i":[[0,2.209],[0,0],[-2.209,0],[0,0],[0,2.209],[0,0],[2.209,0],[0,0]],"o":[[0,0],[0,2.209],[0,0],[2.209,0],[0,0],[0,2.209],[0,0],[-2.209,0]],"v":[[-17,-1.5],[-17,-2.5],[-13,1.5],[13,1.5],[17,-2.5],[17,-1.5],[13,2.5],[-13,2.5]],"c":true},"ix":2},"nm":"Path 1","mn":"ADBE Vector Shape - Group","hd":false},{"ty":"fl","c":{"a":0,"k":[0,0,0,1],"ix":4},"o":{"a":0,"k":100,"ix":5},"r":1,"bm":0,"nm":"Fill 1","mn":"ADBE Vector Graphic - Fill","hd":false},{"ty":"tr","p":{"a":0,"k":[0,0],"ix":2},"a":{"a":0,"k":[0,0],"ix":1},"s":{"a":0,"k":[100,100],"ix":3},"r":{"a":0,"k":0,"ix":6},"o":{"a":0,"k":100,"ix":7},"sk":{"a":0,"k":0,"ix":4},"sa":{"a":0,"k":0,"ix":5},"nm":"Transform"}],"nm":"Bottom_shadow","np":2,"cix":2,"bm":0,"ix":1,"mn":"ADBE Vector Group","hd":false}],"ip":0,"op":300,"st":0,"bm":0},{"ddd":0,"ind":6,"ty":4,"nm":"Highlight","parent":4,"sr":1,"ks":{"o":{"a":0,"k":20,"ix":11},"r":{"a":0,"k":0,"ix":10},"p":{"a":0,"k":[17,20,0],"ix":2},"a":{"a":0,"k":[0,0,0],"ix":1},"s":{"a":0,"k":[100,100,100],"ix":6}},"ao":0,"shapes":[{"ty":"gr","it":[{"ind":0,"ty":"sh","ix":1,"ks":{"a":0,"k":{"i":[[2.209,0],[0,0],[0,2.209],[0,0],[0.552,0],[0,0],[0,-0.552],[0,0]],"o":[[0,0],[2.209,0],[0,0],[0,-0.552],[0,0],[0.552,0],[0,0],[0,2.209]],"v":[[13,20],[12,20],[16,16],[16,-19],[15,-20],[16,-20],[17,-19],[17,16]],"c":true},"ix":2},"nm":"Path 1","mn":"ADBE Vector Shape - Group","hd":false},{"ind":1,"ty":"sh","ix":2,"ks":{"a":0,"k":{"i":[[0,0],[-0.552,0],[0,0],[0,-0.552],[0,0],[-2.209,0],[0,0],[0,2.209]],"o":[[0,-0.552],[0,0],[-0.552,0],[0,0],[0,2.209],[0,0],[-2.209,0],[0,0]],"v":[[-17,-19],[-16,-20],[-15,-20],[-16,-19],[-16,16],[-12,20],[-13,20],[-17,16]],"c":true},"ix":2},"nm":"Path 2","mn":"ADBE Vector Shape - Group","hd":false},{"ty":"mm","mm":1,"nm":"Merge Paths 1","mn":"ADBE Vector Filter - Merge","hd":false},{"ty":"fl","c":{"a":0,"k":[1,1,1,1],"ix":4},"o":{"a":0,"k":100,"ix":5},"r":1,"bm":0,"nm":"Fill 1","mn":"ADBE Vector Graphic - Fill","hd":false},{"ty":"tr","p":{"a":0,"k":[0,0],"ix":2},"a":{"a":0,"k":[0,0],"ix":1},"s":{"a":0,"k":[100,100],"ix":3},"r":{"a":0,"k":0,"ix":6},"o":{"a":0,"k":100,"ix":7},"sk":{"a":0,"k":0,"ix":4},"sa":{"a":0,"k":0,"ix":5},"nm":"Transform"}],"nm":"Highlight","np":4,"cix":2,"bm":0,"ix":1,"mn":"ADBE Vector Group","hd":false}],"ip":0,"op":300,"st":0,"bm":0},{"ddd":0,"ind":7,"ty":4,"nm":"Body","parent":4,"sr":1,"ks":{"o":{"a":0,"k":100,"ix":11},"r":{"a":0,"k":0,"ix":10},"p":{"a":0,"k":[17,20,0],"ix":2},"a":{"a":0,"k":[0,0,0],"ix":1},"s":{"a":0,"k":[100,100,100],"ix":6}},"ao":0,"shapes":[{"ty":"gr","it":[{"ind":0,"ty":"sh","ix":1,"ks":{"a":0,"k":{"i":[[0,0],[0,-0.552],[0,0],[-2.209,0],[0,0],[0,2.209],[0,0],[0.552,0]],"o":[[-0.552,0],[0,0],[0,2.209],[0,0],[2.209,0],[0,0],[0,-0.552],[0,0]],"v":[[-16,-20],[-17,-19],[-17,16],[-13,20],[13,20],[17,16],[17,-19],[16,-20]],"c":true},"ix":2},"nm":"Path 1","mn":"ADBE Vector Shape - Group","hd":false},{"ty":"fl","c":{"a":0,"k":[0.45360827446,0.45360827446,0.54639172554,1],"ix":4},"o":{"a":0,"k":100,"ix":5},"r":1,"bm":0,"nm":"Fill 1","mn":"ADBE Vector Graphic - Fill","hd":false},{"ty":"tr","p":{"a":0,"k":[0,0],"ix":2},"a":{"a":0,"k":[0,0],"ix":1},"s":{"a":0,"k":[100,100],"ix":3},"r":{"a":0,"k":0,"ix":6},"o":{"a":0,"k":100,"ix":7},"sk":{"a":0,"k":0,"ix":4},"sa":{"a":0,"k":0,"ix":5},"nm":"Transform"}],"nm":"Body","np":2,"cix":2,"bm":0,"ix":1,"mn":"ADBE Vector Group","hd":false}],"ip":0,"op":300,"st":0,"bm":0},{"ddd":0,"ind":8,"ty":3,"nm":"▽ Top","sr":1,"ks":{"o":{"a":0,"k":100,"ix":11},"r":{"a":0,"k":0,"ix":10},"p":{"a":0,"k":[17,8.5,0],"ix":2},"a":{"a":0,"k":[10,8.5,0],"ix":1},"s":{"a":0,"k":[100,100,100],"ix":6}},"ao":0,"ip":0,"op":300,"st":0,"bm":0},{"ddd":0,"ind":9,"ty":4,"nm":"Highlight","parent":8,"sr":1,"ks":{"o":{"a":0,"k":20,"ix":11},"r":{"a":0,"k":0,"ix":10},"p":{"a":0,"k":[10,8.5,0],"ix":2},"a":{"a":0,"k":[0,0,0],"ix":1},"s":{"a":0,"k":[100,100,100],"ix":6}},"ao":0,"shapes":[{"ty":"gr","it":[{"ind":0,"ty":"sh","ix":1,"ks":{"a":0,"k":{"i":[[0,0],[0,0],[0,0],[0.552,0],[0,0],[0,-0.552]],"o":[[0,0],[0,0],[0,-0.552],[0,0],[0.552,0],[0,0]],"v":[[10,8.5],[9,8.5],[9,-7.5],[8,-8.5],[9,-8.5],[10,-7.5]],"c":true},"ix":2},"nm":"Path 1","mn":"ADBE Vector Shape - Group","hd":false},{"ind":1,"ty":"sh","ix":2,"ks":{"a":0,"k":{"i":[[0,0],[-0.552,0],[0,0],[0,-0.552],[0,0],[0,0]],"o":[[0,-0.552],[0,0],[-0.552,0],[0,0],[0,0],[0,0]],"v":[[-10,-7.5],[-9,-8.5],[-8,-8.5],[-9,-7.5],[-9,8.5],[-10,8.5]],"c":true},"ix":2},"nm":"Path 2","mn":"ADBE Vector Shape - Group","hd":false},{"ty":"mm","mm":1,"nm":"Merge Paths 1","mn":"ADBE Vector Filter - Merge","hd":false},{"ty":"fl","c":{"a":0,"k":[1,1,1,1],"ix":4},"o":{"a":0,"k":100,"ix":5},"r":1,"bm":0,"nm":"Fill 1","mn":"ADBE Vector Graphic - Fill","hd":false},{"ty":"tr","p":{"a":0,"k":[0,0],"ix":2},"a":{"a":0,"k":[0,0],"ix":1},"s":{"a":0,"k":[100,100],"ix":3},"r":{"a":0,"k":0,"ix":6},"o":{"a":0,"k":100,"ix":7},"sk":{"a":0,"k":0,"ix":4},"sa":{"a":0,"k":0,"ix":5},"nm":"Transform"}],"nm":"Highlight","np":4,"cix":2,"bm":0,"ix":1,"mn":"ADBE Vector Group","hd":false}],"ip":0,"op":300,"st":0,"bm":0},{"ddd":0,"ind":10,"ty":4,"nm":"Body","parent":8,"sr":1,"ks":{"o":{"a":0,"k":100,"ix":11},"r":{"a":0,"k":0,"ix":10},"p":{"a":0,"k":[10,8.5,0],"ix":2},"a":{"a":0,"k":[0,0,0],"ix":1},"s":{"a":0,"k":[100,100,100],"ix":6}},"ao":0,"shapes":[{"ty":"gr","it":[{"ind":0,"ty":"sh","ix":1,"ks":{"a":0,"k":{"i":[[0,0],[0,-0.552],[0,0],[0,0],[0,0],[0.552,0]],"o":[[-0.552,0],[0,0],[0,0],[0,0],[0,-0.552],[0,0]],"v":[[-9,-8.5],[-10,-7.5],[-10,8.5],[10,8.5],[10,-7.5],[9,-8.5]],"c":true},"ix":2},"nm":"Path 1","mn":"ADBE Vector Shape - Group","hd":false},{"ty":"fl","c":{"a":0,"k":[0.700299978256,0.700299978256,0.759700059891,1],"ix":4},"o":{"a":0,"k":100,"ix":5},"r":1,"bm":0,"nm":"Fill 1","mn":"ADBE Vector Graphic - Fill","hd":false},{"ty":"tr","p":{"a":0,"k":[0,0],"ix":2},"a":{"a":0,"k":[0,0],"ix":1},"s":{"a":0,"k":[100,100],"ix":3},"r":{"a":0,"k":0,"ix":6},"o":{"a":0,"k":100,"ix":7},"sk":{"a":0,"k":0,"ix":4},"sa":{"a":0,"k":0,"ix":5},"nm":"Transform"}],"nm":"Body","np":2,"cix":2,"bm":0,"ix":1,"mn":"ADBE Vector Group","hd":false}],"ip":0,"op":300,"st":0,"bm":0},{"ddd":0,"ind":11,"ty":4,"nm":"illus / USB","sr":1,"ks":{"o":{"a":0,"k":100,"ix":11},"r":{"a":0,"k":0,"ix":10},"p":{"a":0,"k":[17,48.5,0],"ix":2},"a":{"a":0,"k":[0,0,0],"ix":1},"s":{"a":0,"k":[100,100,100],"ix":6}},"ao":0,"shapes":[{"ty":"gr","it":[{"ty":"rc","d":1,"s":{"a":0,"k":[34,97],"ix":2},"p":{"a":0,"k":[0,0],"ix":3},"r":{"a":0,"k":0,"ix":4},"nm":"Rectangle Path 1","mn":"ADBE Vector Shape - Rect","hd":false},{"ty":"tr","p":{"a":0,"k":[0,0],"ix":2},"a":{"a":0,"k":[0,0],"ix":1},"s":{"a":0,"k":[100,100],"ix":3},"r":{"a":0,"k":0,"ix":6},"o":{"a":0,"k":100,"ix":7},"sk":{"a":0,"k":0,"ix":4},"sa":{"a":0,"k":0,"ix":5},"nm":"Transform"}],"nm":"illus / USB","np":1,"cix":2,"bm":0,"ix":1,"mn":"ADBE Vector Group","hd":false}],"ip":0,"op":300,"st":0,"bm":0}]}],"fonts":{"list":[{"fName":"Inter-Regular","fFamily":"Inter","fStyle":"Regular","ascent":72.7264404296875}]},"layers":[{"ddd":0,"ind":1,"ty":5,"nm":"Bootloader","parent":8,"sr":1,"ks":{"o":{"a":1,"k":[{"i":{"x":[0.667],"y":[1]},"o":{"x":[0.333],"y":[0]},"t":195,"s":[0]},{"i":{"x":[0.667],"y":[1]},"o":{"x":[0.333],"y":[0]},"t":210,"s":[100]},{"i":{"x":[0.667],"y":[1]},"o":{"x":[0.333],"y":[0]},"t":240,"s":[100]},{"t":255,"s":[0]}],"ix":11},"r":{"a":0,"k":0,"ix":10},"p":{"a":0,"k":[26,51,0],"ix":2},"a":{"a":0,"k":[0,0,0],"ix":1},"s":{"a":0,"k":[111.111,111.111,100],"ix":6}},"ao":0,"t":{"d":{"k":[{"s":{"s":9,"f":"Inter-Regular","t":"Bootloader","j":0,"tr":0,"lh":10.8,"ls":0,"fc":[0.922,0.922,0.922]},"t":0}]},"p":{},"m":{"g":1,"a":{"a":0,"k":[0,0],"ix":2}},"a":[]},"ip":0,"op":300,"st":0,"bm":0},{"ddd":0,"ind":2,"ty":4,"nm":"Hold","parent":8,"sr":1,"ks":{"o":{"a":1,"k":[{"i":{"x":[0.833],"y":[0.833]},"o":{"x":[0.167],"y":[0.167]},"t":30,"s":[0]},{"t":45,"s":[100]}],"ix":11},"r":{"a":0,"k":0,"ix":10},"p":{"a":0,"k":[36.5,66.8,0],"ix":2},"a":{"a":0,"k":[0,0,0],"ix":1},"s":{"a":0,"k":[100,100,100],"ix":6}},"ao":0,"shapes":[{"ty":"gr","it":[{"d":1,"ty":"el","s":{"a":0,"k":[40,40],"ix":2},"p":{"a":0,"k":[0,0],"ix":3},"nm":"Ellipse Path 1","mn":"ADBE Vector Shape - Ellipse","hd":false},{"ty":"st","c":{"a":0,"k":[0,0.721568644047,0.070588238537,1],"ix":3},"o":{"a":0,"k":100,"ix":4},"w":{"a":0,"k":2,"ix":5},"lc":2,"lj":1,"ml":4,"bm":0,"nm":"Stroke 1","mn":"ADBE Vector Graphic - Stroke","hd":false},{"ty":"tr","p":{"a":0,"k":[71.667,18.993],"ix":2},"a":{"a":0,"k":[0,0],"ix":1},"s":{"a":0,"k":[100,100],"ix":3},"r":{"a":0,"k":0,"ix":6},"o":{"a":0,"k":100,"ix":7},"sk":{"a":0,"k":0,"ix":4},"sa":{"a":0,"k":0,"ix":5},"nm":"Transform"}],"nm":"Ellipse 1","np":3,"cix":2,"bm":0,"ix":1,"mn":"ADBE Vector Group","hd":false},{"ty":"tm","s":{"a":1,"k":[{"i":{"x":[0.833],"y":[0.833]},"o":{"x":[0.167],"y":[0.167]},"t":45,"s":[0]},{"t":210,"s":[100]}],"ix":1},"e":{"a":0,"k":100,"ix":2},"o":{"a":0,"k":0,"ix":3},"m":1,"ix":2,"nm":"Trim Paths 1","mn":"ADBE Vector Filter - Trim","hd":false}],"ip":0,"op":300,"st":0,"bm":0},{"ddd":0,"ind":3,"ty":0,"nm":"Arrow Thick Left","parent":8,"refId":"comp_0","sr":1,"ks":{"o":{"a":1,"k":[{"i":{"x":[0.667],"y":[1]},"o":{"x":[0.333],"y":[0]},"t":30,"s":[0]},{"i":{"x":[0.667],"y":[1]},"o":{"x":[0.333],"y":[0]},"t":45,"s":[100]},{"i":{"x":[0.667],"y":[1]},"o":{"x":[0.333],"y":[0]},"t":210,"s":[100]},{"t":225,"s":[0]}],"ix":11},"r":{"a":0,"k":0,"ix":10},"p":{"a":1,"k":[{"i":{"x":0.667,"y":1},"o":{"x":0.333,"y":0},"t":30,"s":[118,86.3,0],"to":[-1.333,0,0],"ti":[1.333,0,0]},{"i":{"x":0.667,"y":0.667},"o":{"x":0.333,"y":0.333},"t":45,"s":[110,86.3,0],"to":[0,0,0],"ti":[0,0,0]},{"i":{"x":0.667,"y":1},"o":{"x":0.333,"y":0},"t":210,"s":[110,86.3,0],"to":[1.333,0,0],"ti":[-1.333,0,0]},{"t":225,"s":[118,86.3,0]}],"ix":2},"a":{"a":0,"k":[12,12,0],"ix":1},"s":{"a":0,"k":[73,73,100],"ix":6}},"ao":0,"w":24,"h":24,"ip":30,"op":300,"st":0,"bm":0},{"ddd":0,"ind":4,"ty":0,"nm":"Line Popup","refId":"comp_1","sr":1,"ks":{"o":{"a":0,"k":100,"ix":11},"r":{"a":0,"k":-119,"ix":10},"p":{"a":0,"k":[176,84,0],"ix":2},"a":{"a":0,"k":[100,100,0],"ix":1},"s":{"a":0,"k":[100,100,100],"ix":6}},"ao":0,"w":200,"h":200,"ip":135,"op":206,"st":135,"bm":0},{"ddd":0,"ind":5,"ty":0,"nm":"Line Popup","refId":"comp_1","sr":1,"ks":{"o":{"a":0,"k":100,"ix":11},"r":{"a":0,"k":-135,"ix":10},"p":{"a":0,"k":[176,84,0],"ix":2},"a":{"a":0,"k":[100,100,0],"ix":1},"s":{"a":0,"k":[100,100,100],"ix":6}},"ao":0,"w":200,"h":200,"ip":135,"op":206,"st":135,"bm":0},{"ddd":0,"ind":6,"ty":0,"nm":"Line Popup","refId":"comp_1","sr":1,"ks":{"o":{"a":0,"k":100,"ix":11},"r":{"a":0,"k":-224,"ix":10},"p":{"a":0,"k":[176,84,0],"ix":2},"a":{"a":0,"k":[100,100,0],"ix":1},"s":{"a":0,"k":[100,100,100],"ix":6}},"ao":0,"w":200,"h":200,"ip":135,"op":206,"st":135,"bm":0},{"ddd":0,"ind":7,"ty":0,"nm":"Line Popup","refId":"comp_1","sr":1,"ks":{"o":{"a":0,"k":100,"ix":11},"r":{"a":0,"k":-239,"ix":10},"p":{"a":0,"k":[176,84,0],"ix":2},"a":{"a":0,"k":[100,100,0],"ix":1},"s":{"a":0,"k":[100,100,100],"ix":6}},"ao":0,"w":200,"h":200,"ip":135,"op":206,"st":135,"bm":0},{"ddd":0,"ind":8,"ty":0,"nm":"illus / Mini","refId":"comp_2","sr":1,"ks":{"o":{"a":1,"k":[{"i":{"x":[0.667],"y":[1]},"o":{"x":[0.333],"y":[0]},"t":0,"s":[0]},{"i":{"x":[0.667],"y":[1]},"o":{"x":[0.333],"y":[0]},"t":15,"s":[100]},{"i":{"x":[0.667],"y":[1]},"o":{"x":[0.333],"y":[0]},"t":240,"s":[100]},{"t":255,"s":[0]}],"ix":11},"r":{"a":0,"k":0,"ix":10},"p":{"a":1,"k":[{"i":{"x":0.667,"y":1},"o":{"x":0.333,"y":0},"t":0,"s":[176,107.7,0],"to":[0,-1.333,0],"ti":[0,1.333,0]},{"i":{"x":0.667,"y":0.667},"o":{"x":0.333,"y":0.333},"t":15,"s":[176,99.7,0],"to":[0,0,0],"ti":[0,0,0]},{"i":{"x":0.667,"y":1},"o":{"x":0.333,"y":0},"t":90,"s":[176,99.7,0],"to":[0,-14.167,0],"ti":[0,14.167,0]},{"i":{"x":0.667,"y":0.667},"o":{"x":0.333,"y":0.333},"t":105,"s":[176,14.7,0],"to":[0,0,0],"ti":[0,0,0]},{"i":{"x":0.667,"y":1},"o":{"x":0.333,"y":0},"t":135,"s":[176,14.7,0],"to":[0,-0.667,0],"ti":[0,0,0]},{"i":{"x":0.667,"y":1},"o":{"x":0.333,"y":0},"t":139,"s":[176,10.7,0],"to":[0,0,0],"ti":[0,-0.667,0]},{"i":{"x":0.667,"y":0.667},"o":{"x":0.333,"y":0.333},"t":143,"s":[176,14.7,0],"to":[0,0,0],"ti":[0,0,0]},{"i":{"x":0.667,"y":1},"o":{"x":0.333,"y":0},"t":165,"s":[176,14.7,0],"to":[0,14.167,0],"ti":[0,-14.167,0]},{"i":{"x":0.667,"y":0.667},"o":{"x":0.333,"y":0.333},"t":180,"s":[176,99.7,0],"to":[0,0,0],"ti":[0,0,0]},{"i":{"x":0.667,"y":1},"o":{"x":0.333,"y":0},"t":240,"s":[176,99.7,0],"to":[0,1.333,0],"ti":[0,-1.333,0]},{"t":255,"s":[176,107.7,0]}],"ix":2},"a":{"a":0,"k":[51,86.5,0],"ix":1},"s":{"a":1,"k":[{"i":{"x":[0.667,0.667,0.667],"y":[1,1,1]},"o":{"x":[0.333,0.333,0.333],"y":[0,0,0]},"t":0,"s":[90,90,100]},{"i":{"x":[0.667,0.667,0.667],"y":[1,1,1]},"o":{"x":[0.333,0.333,0.333],"y":[0,0,0]},"t":15,"s":[100,100,100]},{"i":{"x":[0.667,0.667,0.667],"y":[1,1,1]},"o":{"x":[0.333,0.333,0.333],"y":[0,0,0]},"t":240,"s":[100,100,100]},{"t":255,"s":[90,90,100]}],"ix":6}},"ao":0,"w":102,"h":173,"ip":0,"op":300,"st":0,"bm":0},{"ddd":0,"ind":9,"ty":0,"nm":"illus / USB","parent":8,"refId":"comp_3","sr":1,"ks":{"o":{"a":0,"k":100,"ix":11},"r":{"a":0,"k":0,"ix":10},"p":{"a":1,"k":[{"i":{"x":0.667,"y":1},"o":{"x":0.333,"y":0},"t":120,"s":[51,218.8,0],"to":[0,-3.167,0],"ti":[0,3.167,0]},{"t":135,"s":[51,199.8,0]}],"ix":2},"a":{"a":0,"k":[17,48.5,0],"ix":1},"s":{"a":0,"k":[85,85,100],"ix":6}},"ao":0,"w":34,"h":97,"ip":0,"op":300,"st":0,"bm":0}],"markers":[],"chars":[{"ch":"B","size":9,"style":"Regular","w":65.06,"data":{"shapes":[{"ty":"gr","it":[{"ind":0,"ty":"sh","ix":1,"ks":{"a":0,"k":{"i":[[0,0],[-3.575,1.705],[-1.657,2.912],[0,3.646],[1.515,2.652],[2.249,1.42],[2.225,0.142],[0,0],[-1.788,1.184],[-1.101,2.036],[0,3.125],[1.61,2.924],[3.29,1.74],[5.066,0],[0,0],[0,0]],"o":[[5.729,0],[3.574,-1.705],[1.657,-2.912],[0,-3.835],[-1.515,-2.651],[-2.249,-1.42],[0,0],[2.083,-0.568],[1.787,-1.184],[1.101,-2.036],[0,-3.551],[-1.61,-2.924],[-3.291,-1.74],[0,0],[0,0],[0,0]],"v":[[35.085,0],[49.041,-2.557],[56.889,-9.482],[59.375,-19.318],[57.102,-29.048],[51.456,-35.156],[44.744,-37.5],[44.744,-38.21],[50.55,-40.838],[54.883,-45.668],[56.534,-53.409],[54.119,-63.121],[46.768,-70.117],[34.233,-72.727],[8.807,-72.727],[8.807,0]],"c":true},"ix":2},"nm":"B","mn":"ADBE Vector Shape - Group","hd":false},{"ind":1,"ty":"sh","ix":2,"ks":{"a":0,"k":{"i":[[0,0],[0,0],[-2.32,-1.266],[-1.255,-2.095],[0,-2.462],[2.426,-2.237],[5.753,0],[0,0]],"o":[[0,0],[3.172,0],[2.32,1.267],[1.255,2.095],[0,3.196],[-2.427,2.237],[0,0],[0,0]],"v":[[17.614,-33.097],[35.511,-33.097],[43.75,-31.197],[49.112,-26.154],[50.994,-19.318],[47.354,-11.168],[35.085,-7.812],[17.614,-7.812]],"c":true},"ix":2},"nm":"B","mn":"ADBE Vector Shape - Group","hd":false},{"ind":2,"ty":"sh","ix":3,"ks":{"a":0,"k":{"i":[[0,0],[0,0],[-2.226,-2.237],[0,-3.196],[1.266,-1.894],[2.142,-1.041],[2.651,0],[0,0]],"o":[[0,0],[4.83,0],[2.225,2.237],[0,2.557],[-1.267,1.894],[-2.143,1.042],[0,0],[0,0]],"v":[[17.614,-64.915],[34.233,-64.915],[44.815,-61.559],[48.153,-53.409],[46.254,-46.733],[41.14,-42.33],[33.949,-40.767],[17.614,-40.767]],"c":true},"ix":2},"nm":"B","mn":"ADBE Vector Shape - Group","hd":false}],"nm":"B","np":6,"cix":2,"bm":0,"ix":1,"mn":"ADBE Vector Group","hd":false}]},"fFamily":"Inter"},{"ch":"o","size":9,"style":"Regular","w":59.66,"data":{"shapes":[{"ty":"gr","it":[{"ind":0,"ty":"sh","ix":1,"ks":{"a":0,"k":{"i":[[-3.705,2.344],[-2.072,4.214],[0,5.635],[2.071,4.238],[3.705,2.344],[4.924,0],[3.705,-2.344],[2.071,-4.238],[0,-5.682],[-2.072,-4.214],[-3.705,-2.344],[-4.924,0]],"o":[[3.705,-2.344],[2.071,-4.214],[0,-5.682],[-2.072,-4.238],[-3.705,-2.344],[-4.924,0],[-3.705,2.344],[-2.072,4.238],[0,5.635],[2.071,4.214],[3.705,2.344],[4.924,0]],"v":[[42.773,-2.379],[51.438,-12.216],[54.545,-26.989],[51.438,-41.868],[42.773,-51.74],[29.83,-55.256],[16.886,-51.74],[8.221,-41.868],[5.114,-26.989],[8.221,-12.216],[16.886,-2.379],[29.83,1.136]],"c":true},"ix":2},"nm":"o","mn":"ADBE Vector Shape - Group","hd":false},{"ind":1,"ty":"sh","ix":2,"ks":{"a":0,"k":{"i":[[2.415,1.918],[1.16,3.125],[0,3.646],[-1.16,3.149],[-2.415,1.941],[-3.741,0],[-2.415,-1.941],[-1.16,-3.148],[0,-3.645],[1.16,-3.125],[2.415,-1.918],[3.74,0]],"o":[[-2.415,-1.918],[-1.16,-3.125],[0,-3.645],[1.16,-3.148],[2.415,-1.941],[3.74,0],[2.415,1.941],[1.16,3.149],[0,3.646],[-1.16,3.125],[-2.415,1.918],[-3.741,0]],"v":[[20.597,-9.268],[15.234,-16.832],[13.494,-26.989],[15.234,-37.18],[20.597,-44.815],[29.83,-47.727],[39.062,-44.815],[44.425,-37.18],[46.165,-26.989],[44.425,-16.832],[39.062,-9.268],[29.83,-6.392]],"c":true},"ix":2},"nm":"o","mn":"ADBE Vector Shape - Group","hd":false}],"nm":"o","np":5,"cix":2,"bm":0,"ix":1,"mn":"ADBE Vector Group","hd":false}]},"fFamily":"Inter"},{"ch":"t","size":9,"style":"Regular","w":36.36,"data":{"shapes":[{"ty":"gr","it":[{"ind":0,"ty":"sh","ix":1,"ks":{"a":0,"k":{"i":[[0,0],[0,0],[0,0],[0,0]],"o":[[0,0],[0,0],[0,0],[0,0]],"v":[[3.125,-54.545],[3.125,-47.443],[31.392,-47.443],[31.392,-54.545]],"c":true},"ix":2},"nm":"t","mn":"ADBE Vector Shape - Group","hd":false},{"ind":1,"ty":"sh","ix":2,"ks":{"a":0,"k":{"i":[[0,0],[-1.48,-2.083],[-2.261,-1.018],[-2.368,0],[-1.018,0.225],[-0.568,0.213],[0,0],[0.591,-0.107],[0.923,0],[1.101,0.391],[0.698,1.172],[0,2.368],[0,0],[0,0]],"o":[[0,3.173],[1.479,2.084],[2.261,1.018],[1.562,0],[1.018,-0.225],[0,0],[-0.355,0.071],[-0.592,0.107],[-1.231,0],[-1.101,-0.391],[-0.699,-1.172],[0,0],[0,0],[0,0]],"v":[[11.364,-13.352],[13.583,-5.469],[19.194,-0.817],[26.136,0.71],[30.007,0.373],[32.386,-0.284],[30.682,-7.812],[29.261,-7.546],[26.989,-7.386],[23.491,-7.972],[20.792,-10.316],[19.744,-15.625],[19.744,-67.614],[11.364,-67.614]],"c":true},"ix":2},"nm":"t","mn":"ADBE Vector Shape - Group","hd":false}],"nm":"t","np":5,"cix":2,"bm":0,"ix":1,"mn":"ADBE Vector Group","hd":false}]},"fFamily":"Inter"},{"ch":"l","size":9,"style":"Regular","w":23.72,"data":{"shapes":[{"ty":"gr","it":[{"ind":0,"ty":"sh","ix":1,"ks":{"a":0,"k":{"i":[[0,0],[0,0],[0,0],[0,0]],"o":[[0,0],[0,0],[0,0],[0,0]],"v":[[7.67,-72.727],[7.67,0],[16.051,0],[16.051,-72.727]],"c":true},"ix":2},"nm":"l","mn":"ADBE Vector Shape - Group","hd":false}],"nm":"l","np":3,"cix":2,"bm":0,"ix":1,"mn":"ADBE Vector Group","hd":false}]},"fFamily":"Inter"},{"ch":"a","size":9,"style":"Regular","w":56.39,"data":{"shapes":[{"ty":"gr","it":[{"ind":0,"ty":"sh","ix":1,"ks":{"a":0,"k":{"i":[[-2.202,0.947],[-1.326,1.349],[-0.568,1.184],[0,0],[0,0],[0,0],[0,0],[1.42,2.581],[2.142,1.278],[2.284,0.414],[1.752,0],[2.829,-0.746],[2.379,-1.858],[1.42,-3.314],[0,0],[-2.273,1.752],[-4.001,0],[-1.906,-1.941],[0,-3.503],[0,0],[0.959,-0.544],[2.071,-0.225],[3.314,-0.426],[2.497,-0.556],[2.06,-1.113],[1.231,-1.953],[0,-3.125],[-1.657,-2.497],[-2.818,-1.314],[-3.457,0]],"o":[[2.202,-0.947],[1.326,-1.349],[0,0],[0,0],[0,0],[0,0],[0,-4.332],[-1.42,-2.58],[-2.143,-1.278],[-2.285,-0.414],[-2.747,0],[-2.829,0.746],[-2.379,1.859],[0,0],[0.923,-1.989],[2.273,-1.752],[3.859,0],[1.905,1.941],[0,0],[0,1.349],[-0.959,0.545],[-2.072,0.225],[-2.534,0.332],[-2.498,0.557],[-2.06,1.113],[-1.231,1.953],[0,3.551],[1.657,2.498],[2.817,1.314],[3.172,0]],"v":[[31.783,-0.142],[37.074,-3.587],[39.915,-7.386],[40.341,-7.386],[40.341,0],[48.722,0],[48.722,-35.938],[46.591,-46.307],[41.246,-52.095],[34.606,-54.634],[28.551,-55.256],[20.188,-54.137],[12.376,-50.231],[6.676,-42.472],[14.631,-39.631],[19.425,-45.241],[28.835,-47.869],[37.482,-44.957],[40.341,-36.79],[40.341,-36.506],[38.903,-33.665],[34.357,-32.511],[26.278,-31.534],[18.732,-30.202],[11.896,-27.699],[6.96,-23.1],[5.114,-15.483],[7.599,-6.41],[14.311,-0.692],[23.722,1.278]],"c":true},"ix":2},"nm":"a","mn":"ADBE Vector Shape - Group","hd":false},{"ind":1,"ty":"sh","ix":2,"ks":{"a":0,"k":{"i":[[2.166,1.48],[0,2.912],[-1.149,1.243],[-1.882,0.628],[-2.178,0.284],[-1.456,0.178],[-1.551,0.249],[-1.196,0.343],[-0.355,0.426],[0,0],[1.172,-2.06],[2.284,-1.302],[3.314,0]],"o":[[-2.166,-1.479],[0,-2.131],[1.148,-1.243],[1.882,-0.627],[0.899,-0.118],[1.456,-0.178],[1.55,-0.249],[1.195,-0.343],[0,0],[0,2.273],[-1.172,2.06],[-2.285,1.302],[-3.338,0]],"v":[[16.744,-8.469],[13.494,-15.057],[15.217,-20.117],[19.762,-22.923],[25.852,-24.29],[29.386,-24.734],[33.896,-25.373],[38.015,-26.261],[40.341,-27.415],[40.341,-19.744],[38.583,-13.246],[33.398,-8.203],[25,-6.25]],"c":true},"ix":2},"nm":"a","mn":"ADBE Vector Shape - Group","hd":false}],"nm":"a","np":5,"cix":2,"bm":0,"ix":1,"mn":"ADBE Vector Group","hd":false}]},"fFamily":"Inter"},{"ch":"d","size":9,"style":"Regular","w":62.07,"data":{"shapes":[{"ty":"gr","it":[{"ind":0,"ty":"sh","ix":1,"ks":{"a":0,"k":{"i":[[-2.107,1.172],[-1.136,1.504],[-0.616,0.994],[0,0],[0,0],[0,0],[0,0],[0,0],[0,0],[0,0],[1.101,1.48],[2.071,1.172],[3.551,0],[3.503,-2.296],[1.965,-4.214],[0,-5.729],[-1.965,-4.226],[-3.48,-2.308],[-4.545,0]],"o":[[2.107,-1.172],[1.136,-1.503],[0,0],[0,0],[0,0],[0,0],[0,0],[0,0],[0,0],[-0.616,-0.947],[-1.101,-1.479],[-2.072,-1.172],[-4.593,0],[-3.504,2.297],[-1.965,4.214],[0,5.777],[1.965,4.226],[3.48,2.308],[3.503,0]],"v":[[36.683,-0.621],[41.548,-4.634],[44.176,-8.381],[45.17,-8.381],[45.17,0],[53.267,0],[53.267,-72.727],[44.886,-72.727],[44.886,-45.881],[44.176,-45.881],[41.602,-49.521],[36.843,-53.498],[28.409,-55.256],[16.264,-51.811],[8.061,-42.045],[5.114,-27.131],[8.061,-12.127],[16.229,-2.326],[28.267,1.136]],"c":true},"ix":2},"nm":"d","mn":"ADBE Vector Shape - Group","hd":false},{"ind":1,"ty":"sh","ix":2,"ks":{"a":0,"k":{"i":[[2.355,1.859],[1.195,3.161],[0,3.883],[-1.172,3.089],[-2.356,1.811],[-3.551,0],[-2.32,-1.716],[-1.184,-3.066],[0,-4.072],[1.207,-3.137],[2.32,-1.763],[3.361,0]],"o":[[-2.356,-1.858],[-1.196,-3.161],[0,-3.835],[1.172,-3.089],[2.355,-1.811],[3.409,0],[2.32,1.717],[1.184,3.066],[0,4.119],[-1.207,3.137],[-2.32,1.764],[-3.504,0]],"v":[[20.614,-9.18],[15.288,-16.708],[13.494,-27.273],[15.252,-37.66],[20.543,-45.011],[29.403,-47.727],[37.997,-45.153],[43.253,-37.979],[45.028,-27.273],[43.217,-16.388],[37.926,-9.038],[29.403,-6.392]],"c":true},"ix":2},"nm":"d","mn":"ADBE Vector Shape - Group","hd":false}],"nm":"d","np":5,"cix":2,"bm":0,"ix":1,"mn":"ADBE Vector Group","hd":false}]},"fFamily":"Inter"},{"ch":"e","size":9,"style":"Regular","w":58.24,"data":{"shapes":[{"ty":"gr","it":[{"ind":0,"ty":"sh","ix":1,"ks":{"a":0,"k":{"i":[[-2.96,1.148],[-2.012,2.072],[-0.852,2.747],[0,0],[1.302,-1.266],[1.787,-0.627],[2.202,0],[2.557,1.48],[1.432,2.853],[0,4.119],[0,0],[-1.302,2.628],[-2.427,1.646],[-3.338,0],[-2.237,-1.397],[-1.22,-2.415],[0,-3.077],[0,0],[0,0],[0,0],[0,0],[1.349,3.48],[2.273,2.119],[2.77,0.947],[2.841,0],[3.681,-2.403],[2.047,-4.273],[0,-5.587],[-2.048,-4.202],[-3.8,-2.332],[-5.256,0]],"o":[[2.959,-1.148],[2.012,-2.071],[0,0],[-0.71,1.894],[-1.302,1.267],[-1.788,0.628],[-3.386,0],[-2.557,-1.479],[-1.433,-2.853],[0,0],[0,-3.006],[1.302,-2.628],[2.426,-1.645],[3.03,0],[2.237,1.397],[1.219,2.415],[0,0],[0,0],[0,0],[0,0],[0,-5.09],[-1.349,-3.48],[-2.273,-2.118],[-2.77,-0.947],[-4.924,0],[-3.682,2.403],[-2.048,4.274],[0,5.587],[2.047,4.203],[3.8,2.332],[3.693,0]],"v":[[40.518,-0.586],[47.976,-5.415],[52.273,-12.642],[44.176,-14.915],[41.158,-10.174],[36.523,-7.333],[30.54,-6.392],[21.626,-8.612],[15.643,-15.11],[13.494,-25.568],[13.494,-30.398],[15.447,-38.849],[21.04,-45.259],[29.688,-47.727],[37.589,-45.632],[42.773,-39.915],[44.602,-31.676],[11.08,-31.676],[11.08,-24.432],[53.125,-24.432],[53.125,-27.983],[51.101,-40.838],[45.668,-49.237],[38.104,-53.835],[29.688,-55.256],[16.779,-51.651],[8.185,-41.637],[5.114,-26.847],[8.185,-12.163],[16.957,-2.362],[30.54,1.136]],"c":true},"ix":2},"nm":"e","mn":"ADBE Vector Shape - Group","hd":false}],"nm":"e","np":3,"cix":2,"bm":0,"ix":1,"mn":"ADBE Vector Group","hd":false}]},"fFamily":"Inter"},{"ch":"r","size":9,"style":"Regular","w":37.22,"data":{"shapes":[{"ty":"gr","it":[{"ind":0,"ty":"sh","ix":1,"ks":{"a":0,"k":{"i":[[0,0],[0,0],[-1.196,1.93],[-2.072,1.101],[-2.652,0],[-1.007,-0.154],[-0.284,-0.071],[0,0],[0.923,0.024],[0.615,0],[2.604,-1.681],[0.994,-2.699],[0,0],[0,0],[0,0],[0,0]],"o":[[0,0],[0,-2.462],[1.195,-1.929],[2.071,-1.101],[1.113,0],[1.006,0.154],[0,0],[-0.474,-0.047],[-0.923,-0.023],[-3.267,0],[-2.605,1.681],[0,0],[0,0],[0,0],[0,0],[0,0]],"v":[[16.051,0],[16.051,-34.517],[17.844,-41.104],[22.745,-45.65],[29.83,-47.301],[33.008,-47.07],[34.943,-46.733],[34.943,-55.256],[32.848,-55.362],[30.54,-55.398],[21.733,-52.876],[16.335,-46.307],[15.767,-46.307],[15.767,-54.545],[7.67,-54.545],[7.67,0]],"c":true},"ix":2},"nm":"r","mn":"ADBE Vector Shape - Group","hd":false}],"nm":"r","np":3,"cix":2,"bm":0,"ix":1,"mn":"ADBE Vector Group","hd":false}]},"fFamily":"Inter"}]}